Workbook
Name asdasff: [1]!TORIHIKI_GET_B
Name asdasff: [1]!TORIHIKI_GET_B
Name brand: OFFSET([2]list!$W$8,0,0,COUNTA([2]list!$W:$W)-4,1)
Name compound: OFFSET([2]list!$BA$8,0,0,COUNTA([2]list!$BA:$BA)-4,1)
Name compulsoryRegistrationFlg: OFFSET([2]list!$B$8,0,0,COUNTA([2]list!$B:$B)-4,1)
Name data8012: #REF!
Name data8012: #REF!
Name data8012: #REF!
Name data8012: #REF!
Name dd: #REF!
Name dd: #REF!
Name dd: #REF!
Name dd: #REF!
Name disconCodeType: OFFSET([2]list!$AM$8,0,0,COUNTA([2]list!$AM:$AM)-4,1)
Name doubleSizeExpression: OFFSET([2]list!$AX$8,0,0,COUNTA([2]list!$AX:$AX)-4,1)
Name draftingDep: OFFSET([2]list!$H$8,0,0,COUNTA([2]list!$H:$H)-4,1)
Name draftingSbu: OFFSET([2]list!$G$8,0,0,COUNTA([2]list!$G:$G)-4,1)
Name expectedDevPole: OFFSET([2]list!$AP$8,0,0,COUNTA([2]list!$AP:$AP)-4,1)
Name extraLoadReinforced: OFFSET([2]list!$AE$8,0,0,COUNTA([2]list!$AE:$AE)-4,1)
Name FF_jisseki: #REF!
Name FF_jisseki: #REF!
Name FF_jisseki: #REF!
Name FF_jisseki: #REF!
Name gdcUse: OFFSET([2]list!$BE$8,0,0,COUNTA([2]list!$BE:$BE)-4,1)
Name holiday: [3]休日!$A$2:$A$999
Name ignoreFlg: OFFSET([2]list!$C$8,0,0,COUNTA([2]list!$C:$C)-4,1)
Name importantFlg: OFFSET([2]list!$BH$8,0,0,COUNTA([2]list!$BH:$BH)-4,1)
Name inSeasonAdd: OFFSET([2]list!$E$8,0,0,COUNTA([2]list!$E:$E)-4,1)
Name jisseki: #REF!
Name jisseki: #REF!
Name jisseki: #REF!
Name jisseki: #REF!
Name liAutoSettingYearbookCheck: OFFSET([2]list!$T$8,0,0,COUNTA([2]list!$T:$T)-4,1)
Name LLLF: '[4]4×4'!$A$1:$A$101
Name loadRange: OFFSET([2]list!$AD$8,0,0,COUNTA([2]list!$AD:$AD)-4,1)
Name moldInfo: OFFSET([2]list!$BJ$8,0,0,COUNTA([2]list!$BJ:$BJ)-4,1)
Name mudSnowExpression: OFFSET([2]list!$BC$8,0,0,COUNTA([2]list!$BC:$BC)-4,1)
Name oeCode: OFFSET([2]list!$L$8,0,0,COUNTA([2]list!$L:$L)-4,1)
Name offtake: OFFSET([2]list!$BF$8,0,0,COUNTA([2]list!$BF:$BF)-4,1)
Name patternType: OFFSET([2]list!$S$8,0,0,COUNTA([2]list!$S:$S)-4,1)
Name pfNecessity: OFFSET([2]list!$BI$8,0,0,COUNTA([2]list!$BI:$BI)-4,1)
Name plyRating: OFFSET([2]list!$AC$8,0,0,COUNTA([2]list!$AC:$AC)-4,1)
Name productCategory: OFFSET([2]list!$O$8,0,0,COUNTA([2]list!$O:$O)-4,1)
Name productGroupBsj: OFFSET([2]list!$V$8,0,0,COUNTA([2]list!$V:$V)-4,1)
Name productLayer: OFFSET([2]list!$BG$8,0,0,COUNTA([2]list!$BG:$BG)-4,1)
Name productName: OFFSET([5]list!$K$8,0,0,COUNTA([5]list!$K:$K)-4,1)
Name productName: OFFSET([6]list!$K$8,0,0,COUNTA([6]list!$K:$K)-4,1)
Name psReliable: OFFSET([2]list!$AO$8,0,0,COUNTA([2]list!$AO:$AO)-4,1)
Name radialBiasType: OFFSET([2]list!$AF$8,0,0,COUNTA([2]list!$AF:$AF)-4,1)
Name radialMark: OFFSET([2]list!$Z$8,0,0,COUNTA([2]list!$Z:$Z)-4,1)
Name radialMark: OFFSET([7]list!$Z$8,0,0,COUNTA([7]list!$Z:$Z)-4,1)
Name RE01ﾌﾟﾚﾐｱﾑ: #REF!
Name RE01ﾌﾟﾚﾐｱﾑ: #REF!
Name RE01ﾌﾟﾚﾐｱﾑ: #REF!
Name RE01ﾌﾟﾚﾐｱﾑ: #REF!
Name registrationFlg: OFFSET([2]list!$A$8,0,0,COUNTA([2]list!$A:$A)-5,1)
Name registrationReason: OFFSET([2]list!$I$8,0,0,COUNTA([2]list!$I:$I)-4,1)
Name regroovable: OFFSET([2]list!$AT$8,0,0,COUNTA([2]list!$AT:$AT)-4,1)
Name repOe: OFFSET([2]list!$J$8,0,0,COUNTA([2]list!$J:$J)-4,1)
Name rftType: OFFSET([2]list!$AG$8,0,0,COUNTA([2]list!$AG:$AG)-4,1)

Sheet Y26 Plan (2)
E1: =E10/E2 -> 1.3411669 | F1: =F10/F2 -> 1.1084074 | G1: =G10/G2 -> 1.1628278 | H1: =H10/H2 -> 1.181595 | I1: =I10/I2 -> 1.2740036 | J1: =J10/J2 -> 1.3341988 | K1: =K10/K2 -> 1.13946 | L1: =L10/L2 -> 1.2358083 | ... X1: =X10/X2 -> 1.0493254
C2: 25 Act | D2: Q'ty | E2: 13574 | F2: 22849 | G2: 26310 | H2: =+E2+F2+G2 -> 62733 | I2: 24788 | J2: 26574 | K2: 36964 | L2: =+I2+J2+K2 -> 88326 | M2: =L2+H2 -> 151059 | N2: 31347 | O2: 45956 | P2: 46959 | Q2: =+N2+O2+P2 -> 124262 | R2: 51299 | S2: 57760 | T2: 52316 | U2: =+R2+S2+T2 -> 161375 | V2: =U2+Q2 -> 285637 | W2: =V2+M2 -> 436696 | X2: 468043
D3: Net AMT | E3: 1.645403e+09 | F3: 2.4686141e+09 | G3: 2.7993785e+09 | H3: =+E3+F3+G3 -> 6.9133957e+09 | I3: 2.8310113e+09 | J3: 2.8958416e+09 | K3: 4.347935e+09 | L3: =+I3+J3+K3 -> 1.0074788e+10 | M3: =L3+H3 -> 1.6988184e+10 | N3: 3.6750325e+09 | O3: 5.4434825e+09 | P3: 5.0580172e+09 | Q3: =+N3+O3+P3 -> 1.4176532e+10 | R3: 5.6019277e+09 | S3: 5.6937983e+09 | T3: 6.1335519e+09 | U3: =+R3+S3+T3 -> 1.7429278e+10 | V3: =U3+Q3 -> 3.160581e+10 | W3: =V3+M3 -> 4.8593994e+10 | X3: 5.2269026e+10
C5: Volume : pcs | E5: Jan | F5: Feb | G5: Mar | H5: 1Q | I5: Apr | J5: May | K5: Jun | L5: 2Q | M5: 1H TTL | N5: Jul | O5: Aug | P5: Sep | Q5: 3Q | R5: Oct | S5: Nov | T5: Dec | U5: 4Q | V5: 2H TTL | W5: FY TTL | X5: FY TTL
C6: OB | D6: Q'ty | E6: 16091 | F6: 22633 | G6: 26329 | H6: =+E6+F6+G6 -> 65053 | I6: 29180 | J6: 31700 | K6: 41311 | L6: =+I6+J6+K6 -> 102191 | M6: =H6+L6 -> 167244 | N6: 41678 | O6: 50165 | P6: 48461 | Q6: =+N6+O6+P6 -> 140304 | R6: 51017 | S6: 48287 | T6: 52147 | U6: =+R6+S6+T6 -> 151451 | V6: =+Q6+U6 -> 291755 | W6: =V6+M6 -> 458999 | X6: 458999
C7: RF | D7: Q'ty | E7: 18205 | F7: 25326 | G7: 30594 | H7: =+E7+F7+G7 -> 74125 | I7: 30055 | J7: 32651 | K7: 38085 | L7: =+I7+J7+K7 -> 100791 | M7: =L7+H7 -> 174916 | N7: 42928 | O7: 51670 | P7: 49915 | Q7: =+N7+O7+P7 -> 144513 | R7: 51017 | S7: 49736 | T7: 53711 | U7: =+R7+S7+T7 -> 154464 | V7: =U7+Q7 -> 298977 | W7: =V7+M7 -> 473893 | X7: 473893 | Y7: =X7*11% -> 52128.23
C8: SL | D8: Q'ty | I8: 168.06901 | J8: 182.58354 | K8: 213.01188 | L8: =+I8+J8+K8 -> 563.66443 | M8: =L8+H8 -> 563.66443 | N8: 240.05416 | O8: 288.93701 | P8: 279.12243 | Q8: =+N8+O8+P8 -> 808.1136 | R8: 285.28573 | S8: 278.12023 | T8: 300.3528 | U8: =+R8+S8+T8 -> 863.75877 | V8: =U8+Q8 -> 1671.8724 | W8: =V8+M8 -> 2235.5368 | X8: 2235.5368
C9: Add | D9: Q'ty | K9: 1000 | L9: =+I9+J9+K9 -> 1000 | M9: =L9+H9 -> 1000 | N9: 2000 | O9: 2000 | P9: 2000 | Q9: =+N9+O9+P9 -> 6000 | R9: 2000 | S9: 3000 | T9: 3000 | U9: =+R9+S9+T9 -> 8000 | V9: =U9+Q9 -> 14000 | W9: =V9+M9 -> 15000 | X9: 15000
C10: ACT/Fcst | D10: Q'ty | E10: =E7+E8+E9 -> 18205 | F10: =F7+F8+F9 -> 25326 | G10: =G7+G8+G9 -> 30594 | H10: =+E10+F10+G10 -> 74125 | I10: 31580 | J10: 35455 | K10: 42119 | L10: =+I10+J10+K10 -> 109154 | M10: =L10+H10 -> 183279 | N10: 45168.054 | O10: 53958.937 | P10: 52194.122 | Q10: =+N10+O10+P10 -> 151321.11 | R10: 53302.286 | S10: 50014 | T10: 54012 | U10: =+R10+S10+T10 -> 157328.29 | V10: =U10+Q10 -> 308649.4 | W10: =V10+M10 -> 491928.4 | X10: 491129.4 | Y10: =X10-X6 -> 32130.399
D11: % vs RF | E11: =E10/E7 -> 1 | F11: =F10/F7 -> 1 | G11: =G10/G7 -> 1 | H11: =H10/H7 -> 1 | I11: =I10/I7 -> 1.0507403 | J11: =J10/J7 -> 1.0858779 | K11: =K10/K7 -> 1.105921 | L11: =L10/L7 -> 1.0829737 | ... W11: =W10/W7 -> 1.038058 | X11: 1.0363719
D12: % vs OB | E12: =E10/E6 -> 1.1313778 | F12: =F10/F6 -> 1.1189856 | G12: =G10/G6 -> 1.1619887 | H12: =H10/H6 -> 1.1394555 | I12: =I10/I6 -> 1.0822481 | J12: =J10/J6 -> 1.1184543 | K12: =K10/K6 -> 1.019559 | L12: =L10/L6 -> 1.0681371 | ... W12: =W10/W6 -> 1.0717418 | X12: 1.070001
D13: +/- vs OB | E13: =E10-E6 -> 2114 | F13: =F10-F6 -> 2693 | G13: =G10-G6 -> 4265 | H13: =H10-H6 -> 9072 | I13: =I10-I6 -> 2400 | J13: =J10-J6 -> 3755 | K13: =K10-K6 -> 808 | L13: =L10-L6 -> 6963 | ... Q13: =Q10-Q6 -> 11017.114 | S13: =S10-S6 -> 1727 | U13: =U10-U6 -> 5877.2857 | V13: =V10-V6 -> 16894.399 | W13: =W10-W6 -> 32929.399 | X13: 32129.537
D14: vs PY | E14: =E10/E2 -> 1.3411669 | F14: =F10/F2 -> 1.1084074 | G14: =G10/G2 -> 1.1628278 | H14: =H10/H2 -> 1.181595 | I14: =I10/I2 -> 1.2740036 | J14: =J10/J2 -> 1.3341988 | K14: =K10/K2 -> 1.13946 | L14: =L10/L2 -> 1.2358083 | ... W14: =W10/W2 -> 1.1264779 | X14: 1.1246463
C16: Net Amount : MKkrw | E16: Jan | F16: Feb | G16: Mar | H16: 1Q | I16: Apr | J16: May | K16: Jun | L16: 2Q | M16: 1H TTL | N16: Jul | O16: Aug | P16: Sep | Q16: 3Q | R16: Oct | S16: Nov | T16: Dec | U16: 4Q | V16: 2H TTL | W16: FY TTL | X16: FY TTL | AB16: 1H TTL
C17: OB | D17: Net AMT | E17: 1.8991156e+09 | F17: 2.6051572e+09 | G17: 3.0210575e+09 | H17: =+E17+F17+G17 -> 7.5253304e+09 | I17: 3.2949287e+09 | J17: 3.6081728e+09 | K17: 4.7887515e+09 | L17: =+I17+J17+K17 -> 1.1691853e+10 | M17: =L17+H17 -> 1.9217183e+10 | N17: 4.9422852e+09 | O17: 6.0111103e+09 | P17: 5.7474061e+09 | Q17: =+N17+O17+P17 -> 1.6700802e+10 | R17: 5.9351462e+09 | S17: 5.5417783e+09 | T17: 5.9576879e+09 | U17: =+R17+S17+T17 -> 1.7434612e+10 | V17: =U17+Q17 -> 3.4135414e+10 | W17: =V17+M17 -> 5.3352598e+10 | X17: 5.3352598e+10 | Z17: 3.6081728e+09 | AB17: 1.9217183e+10
C18: RF | D18: Net AMT | E18: 2.0677511e+09 | F18: 2.6505783e+09 | G18: 3.3390851e+09 | H18: =+E18+F18+G18 -> 8.0574145e+09 | I18: 3.2949287e+09 | J18: 3.6081728e+09 | K18: 4.2566674e+09 | L18: =+I18+J18+K18 -> 1.1159769e+10 | M18: =L18+H18 -> 1.9217183e+10 | N18: 4.9422852e+09 | O18: 6.0111103e+09 | P18: 5.7474061e+09 | Q18: =+N18+O18+P18 -> 1.6700802e+10 | R18: 5.9351462e+09 | S18: 5.5417783e+09 | T18: 5.9576879e+09 | U18: =+R18+S18+T18 -> 1.7434612e+10 | V18: =U18+Q18 -> 3.4135414e+10 | W18: =V18+M18 -> 5.3352598e+10 | X18: 5.3352598e+10 | Z18: 3.6081728e+09 | AB18: 1.9217183e+10
C19: SL | D19: Net AMT | H19: =+E19+F19+G19 -> 0 | I19: 30398674 | J19: 33288632 | K19: 39428254 | L19: =+I19+J19+K19 -> 1.0311556e+08 | M19: =L19+H19 -> 1.0311556e+08 | N19: 45597016 | O19: 55457886 | P19: 53024978 | Q19: =+N19+O19+P19 -> 1.5407988e+08 | R19: 54757049 | S19: 51127878 | T19: 54965017 | U19: =+R19+S19+T19 -> 1.6084994e+08 | V19: =U19+Q19 -> 3.1492982e+08 | W19: =V19+M19 -> 4.1804538e+08 | X19: 4.1804538e+08 | Z19: 33288632 | AB19: 1.0311556e+08
C20: Add | D20: Net AMT | H20: =+E20+F20+G20 -> 0 | K20: 44328809 | L20: =+I20+J20+K20 -> 44328809 | M20: =L20+H20 -> 44328809 | N20: 88657619 | O20: 88657619 | P20: 88657619 | Q20: =+N20+O20+P20 -> 2.6597286e+08 | R20: 88657619 | S20: 1.3298643e+08 | T20: 1.3298643e+08 | U20: =+R20+S20+T20 -> 3.5463047e+08 | V20: =U20+Q20 -> 6.2060333e+08 | W20: =V20+M20 -> 6.6493214e+08 | X20: 6.6493214e+08 | AB20: 44328809
C21: ACT/Fcst | D21: Net AMT | E21: =E18+E19+E20 -> 2.0677511e+09 | F21: =F18+F19+F20 -> 2.6505783e+09 | G21: =G18+G19+G20 -> 3.3390851e+09 | H21: =+E21+F21+G21 -> 8.0574145e+09 | I21: 3.3662293e+09 | J21: 3.7368023e+09 | K21: 4.7269959e+09 | L21: =+I21+J21+K21 -> 1.1830028e+10 | M21: =L21+H21 -> 1.9887442e+10 | N21: 5.0220284e+09 | O21: 6.1015418e+09 | P21: 5.8352005e+09 | Q21: =+N21+O21+P21 -> 1.6958771e+10 | R21: 6.024818e+09 | S21: 5.6275165e+09 | T21: 6.0475852e+09 | U21: =+R21+S21+T21 -> 1.769992e+10 | V21: =U21+Q21 -> 3.465869e+10 | W21: =V21+M21 -> 5.4546132e+10 | X21: 5.4546132e+10 | Y21: =X21-W21 -> 0 | Z21: 3.9187245e+09 | AA21: =Z21-J21 -> 1.8192214e+08 | AB21: 1.9887442e+10 | AC21: =AB21-M21 -> 0
D22: % vs RF | E22: =E21/E18 -> 1 | F22: =F21/F18 -> 1 | G22: =G21/G18 -> 1 | H22: =H21/H18 -> 1 | I22: =I21/I18 -> 1.0216395 | J22: =J21/J18 -> 1.0356495 | K22: =K21/K18 -> 1.1104922 | L22: =L21/L18 -> 1.0600603 | ... W22: =W21/W18 -> 1.0223707 | X22: 1.0223707 | Z22: 1.0860689 | AB22: 1.0348781
D23: % vs OB | E23: =E21/E17 -> 1.0887968 | F23: =F21/F17 -> 1.017435 | G23: =G21/G17 -> 1.1052703 | H23: =H21/H17 -> 1.0707057 | I23: =I21/I17 -> 1.0216395 | J23: =J21/J17 -> 1.0356495 | K23: =K21/K17 -> 0.98710404 | L23: =L21/L17 -> 1.011818 | ... W23: =W21/W17 -> 1.0223707 | X23: 1.0223707 | Y23: =Y21/6 -> 0 | Z23: 1.0860689 | AA23: =J21/Z21 -> 0.95357619 | AB23: 1.0348781
D24: +/- vs OB | E24: =E21-E17 -> 1.6863547e+08 | F24: =F21-F17 -> 45421021 | G24: =G21-G17 -> 3.1802757e+08 | H24: =H21-H17 -> 5.3208407e+08 | I24: =I21-I17 -> 71300599 | J24: =J21-J17 -> 1.286295e+08 | K24: =K21-K17 -> -61755530 | L24: =L21-L17 -> 1.3817457e+08 | ... W24: =W21-W17 -> 1.1935349e+09 | X24: 1.0829775e+09 | Z24: 3.1055164e+08 | AB24: 6.7025864e+08
D25: vs PY | E25: =E21/E3 -> 1.2566837 | F25: =F21/F3 -> 1.0737111 | G25: =G21/G3 -> 1.1927951 | H25: =H21/H3 -> 1.1654786 | I25: =I21/I3 -> 1.1890554 | J25: =J21/J3 -> 1.2904029 | K25: =K21/K3 -> 1.0871818 | L25: =L21/L3 -> 1.174221 | ... W25: =W21/W3 -> 1.1224871 | X25: 1.120212 | Z25: 1.3532247 | AB25: 1.1706632
C26: ASP | D26: OB | E26: =E17/E6 -> 118023.47 | F26: =F17/F6 -> 115104.37 | G26: =G17/G6 -> 114742.59 | H26: =H17/H6 -> 115679.99 | I26: =I17/I6 -> 112917.37 | J26: =J17/J6 -> 113822.49 | K26: =K17/K6 -> 115919.52 | L26: =L17/L6 -> 114411.77 | ... W26: =W17/W6 -> 116236.85 | X26: 116236.85 | Z26: 113822.49 | AB26: 114905.07
D27: ACT/FCST | E27: =E21/E10 -> 113581.5 | F27: =F21/F10 -> 104658.38 | G27: =G21/G10 -> 109141.83 | H27: =H21/H10 -> 108700.36 | I27: =I21/I10 -> 106593.71 | J27: =J21/J10 -> 105395.64 | K27: =K21/K10 -> 112229.54 | L27: =L21/L10 -> 108379.24 | ... W27: =W21/W10 -> 110882.26 | X27: 110837.74 | Z27: 113074.92 | AB27: 108509.12
C29: 1. May sales review
C30: - Qty : 111.8% vs 26OB | E30: ▶ Fully utilized early bird promotion, we have achieved Qty target
C31: - Amt :103.6% vs 26OB | E31: ▶ Although sales vol increased, the amount gap was caused by the application of old price.
C33: 2. Jun sales plan
C34: - Qty : 102% vs 26OB | E34: ▶ Plan to achieve 109% of volume to meet revenue target.
E35: ▶ Increase sales volume with early bird promotion(LVR, EP300, H/L)
C36: - Amt : 98.7% vs 26OB | E36: ▶ The price increase settles down in the market to secure the target ASP.
E37: ▶ Focus on selling high ASP products with various promotions(Potenza sport AS, Turanza EV, KOE)

Sheet Summary
C1: PCR - 2026 JUL PRODUCTION ORDER SHEET Summary
E2: ='PCR Order Sheet final'!T4 -> 4 | F2: ='PCR Order Sheet final'!U4 -> 931 | G2: ='PCR Order Sheet final'!V4 -> 6500 | H2: ='PCR Order Sheet final'!W4 -> 4387 | I2: ='PCR Order Sheet final'!X4 -> 3044 | J2: ='PCR Order Sheet final'!Y4 -> 15404 | K2: ='PCR Order Sheet final'!Z4 -> 9588 | L2: ='PCR Order Sheet final'!AA4 -> 8860 | M2: ='PCR Order Sheet final'!CO4 -> 32593 | N2: ='PCR Order Sheet final'!AC4 -> 13053 | O2: ='PCR Order Sheet final'!CB4 -> 28400 | P2: ='PCR Order Sheet final'!AO4 -> 29642 | Q2: ='PCR Order Sheet final'!CP4 -> 1846 | R2: ='PCR Order Sheet final'!BG4 -> 16430 | S2: ='PCR Order Sheet final'!BH4 -> 13532 | T2: ='PCR Order Sheet final'!BI4 -> 292
B3: No. | C3: Pttn | D3: Origin | E3: Sales | F3: Stock1 | G3: Ship01 | H3: Sales1 | I3: Stock2 | J3: Ship11 | K3: Sales2 | L3: Stock3 | M3: Ship12 | N3: Sales3 | O3: Stock4 | P3: ProdOrder | Q3: Ship13 | R3: Sales4 | S3: Sales5 | T3: Sales6 | W3: Mth | Y3: Pattern | Z3: Y24 OB | AA3: Portion
E4: 46170 | F4: 46170 | G4: =EDATE(F4,1) -> 46201 | H4: =EDATE(F4,1) -> 46201 | I4: =EDATE(F4,1) -> 46201 | J4: =EDATE(I4,1) -> 46231 | K4: =EDATE(I4,1) -> 46231 | L4: =EDATE(H4,1) -> 46231 | M4: =EDATE(K4,1) -> 46262 | N4: =EDATE(L4,1) -> 46262 | O4: =EDATE(K4,1) -> 46262 | P4: =EDATE(H4,1) -> 46231 | Q4: =EDATE(O4,1) -> 46293 | R4: =EDATE(O4,1) -> 46293 | S4: =EDATE(R4,1) -> 46323 | T4: =EDATE(S4,1) -> 46354 | W4: As of E/May | Y4: OE | Z4: 73962 | AA4: 0.19
B5: 1 | C5: RFT | D5: BSJ,BSEU,BATO | E5: 769 | F5: 2088 | G5: 123 | H5: 482 | I5: 1729 | J5: 465 | K5: 619 | L5: 1575 | M5: 925 | N5: 727 | O5: 1773 | P5: 392 | Q5: 769 | R5: 859 | S5: 660 | T5: 792 | W5: =IF(O5=0,0,IF(O5<=R5,O5/R5,IF(O5<R5+S5,1+(O5-R5)/S5,IF(O5<R5+S5+T5,2+(O5-R5-S5)/T5,IF(O5<R5+S5+T5+T5,3+((O5-R5-S5-T5)/(T5)),4))))) -> 2.3207071 | Y5: DRGU+ | Z5: 18303 | AA5: 0.05
B6: 2 | C6: Drive Guard | D6: BSJ | E6: 1722 | F6: 1183 | G6: 1272 | H6: 1742 | I6: 713 | J6: 1867 | K6: 729 | L6: 1851 | M6: 2066 | N6: 839 | O6: 3078 | P6: 2066 | Q6: 1991 | R6: 1560 | S6: 1706 | T6: 2060 | W6: =IF(O6=0,0,IF(O6<=R6,O6/R6,IF(O6<R6+S6,1+(O6-R6)/S6,IF(O6<R6+S6+T6,2+(O6-R6-S6)/T6,IF(O6<R6+S6+T6+T6,3+((O6-R6-S6-T6)/(T6)),4))))) -> 1.8898007 | Y6: T005A | Z6: 1508 | AA6: 0
B7: 3 | C7: OE-After | D7: BSJ, BSEU, BATO | E7: 2888 | F7: 10291 | G7: 5546 | H7: 4651 | I7: 11186 | J7: 5481 | K7: 4550 | L7: 12117 | M7: 5458 | N7: 5291 | O7: 12284 | P7: 4800 | Q7: 4362 | R7: 5828 | S7: 5221 | T7: 6056 | W7: =IF(O7=0,0,IF(O7<=R7,O7/R7,IF(O7<R7+S7,1+(O7-R7)/S7,IF(O7<R7+S7+T7,2+(O7-R7-S7)/T7,IF(O7<R7+S7+T7+T7,3+((O7-R7-S7-T7)/(T7)),4))))) -> 2.20393 | Y7: D400 | Z7: 16386 | AA7: 0.04
B8: 4 | C8: KOE | D8: BSFC, BTMV | E8: 44 | F8: 3250 | G8: 256 | H8: 400 | I8: 3106 | J8: 0 | K8: 300 | L8: 2806 | M8: 298 | N8: 300 | O8: 2804 | P8: 0 | Q8: 0 | R8: 440 | S8: 652 | T8: 1434 | W8: =IF(O8=0,0,IF(O8<=R8,O8/R8,IF(O8<R8+S8,1+(O8-R8)/S8,IF(O8<R8+S8+T8,2+(O8-R8-S8)/T8,IF(O8<R8+S8+T8+T8,3+((O8-R8-S8-T8)/(T8)),4))))) -> 3.1938633
B9: 5 | C9: Potenza sport AS | D9: BATO | E9: 144 | F9: 5745 | G9: 32 | H9: 1268 | I9: 4509 | J9: 1100 | K9: 1256 | L9: 4353 | M9: 0 | N9: 1222 | O9: 3131 | P9: 0 | Q9: 235 | R9: 1076 | S9: 875 | T9: 1057 | W9: =IF(O9=0,0,IF(O9<=R9,O9/R9,IF(O9<R9+S9,1+(O9-R9)/S9,IF(O9<R9+S9+T9,2+(O9-R9-S9)/T9,IF(O9<R9+S9+T9+T9,3+((O9-R9-S9-T9)/(T9)),4))))) -> 3.1163671 | Y9: EL64Z | Z9: 71148 | AA9: 0.19
B10: 6 | C10: Turanza EV | D10: BATO | E10: 48 | F10: 1238 | G10: 43 | H10: 359 | I10: 922 | J10: 1273 | K10: 466 | L10: 1729 | M10: 0 | N10: 537 | O10: 1192 | P10: 0 | Q10: 329 | R10: 459 | S10: 402 | T10: 416 | W10: =IF(O10=0,0,IF(O10<=R10,O10/R10,IF(O10<R10+S10,1+(O10-R10)/S10,IF(O10<R10+S10+T10,2+(O10-R10-S10)/T10,IF(O10<R10+S10+T10+T10,3+((O10-R10-S10-T10)/(T10)),4))))) -> 2.7956731 | Y10: EA04 | Z10: 39504 | AA10: 0.1
B11: 7 | C11: H/L | D11: BSJ | E11: 3400 | F11: 5687 | G11: 2633 | H11: 3154 | I11: 5166 | J11: 2875 | K11: 1220 | L11: 6821 | M11: 3498 | N11: 2110 | O11: 8209 | P11: 3288 | Q11: 4020 | R11: 2640 | S11: 4678 | T11: 5610 | W11: =IF(O11=0,0,IF(O11<=R11,O11/R11,IF(O11<R11+S11,1+(O11-R11)/S11,IF(O11<R11+S11+T11,2+(O11-R11-S11)/T11,IF(O11<R11+S11+T11+T11,3+((O11-R11-S11-T11)/(T11)),4))))) -> 2.1588235
B12: 8 | C12: Serenity Plus | D12: BTMV,TBSC,BSIN | E12: 3350 | F12: 8345 | H12: 5506 | I12: 15637 | J12: 2546 | K12: 5086 | L12: 13097 | M12: 9548 | N12: 4865 | O12: 17780 | P12: 1907 | Q12: 1907 | R12: 4822 | S12: 7360 | T12: 7316 | W12: =IF(O12=0,0,IF(O12<=R12,O12/R12,IF(O12<R12+S12,1+(O12-R12)/S12,IF(O12<R12+S12+T12,2+(O12-R12-S12)/T12,IF(O12<R12+S12+T12+T12,3+((O12-R12-S12-T12)/(T12)),4))))) -> 2.7651722 | X12: 4
B13: 9 | C13: RE005 | D13: TBSC | E13: 5134 | F13: 2550 | G13: 5120 | H13: 3898 | I13: 3772 | J13: 6362 | K13: 6029 | L13: 4105 | M13: 3523 | N13: 6373 | O13: 1255 | P13: 15479 | Q13: 15479 | R13: 5938 | S13: 5647 | T13: 5878 | W13: =IF(O13=0,0,IF(O13<=R13,O13/R13,IF(O13<R13+S13,1+(O13-R13)/S13,IF(O13<R13+S13+T13,2+(O13-R13-S13)/T13,IF(O13<R13+S13+T13+T13,3+((O13-R13-S13-T13)/(T13)),4))))) -> 0.21135062 | X13: 3 | Y13: EP300 | Z13: 28155 | AA13: 0.07
B14: 10 | C14: HL 001 | D14: TBSC,BSFC,BSJ | E14: 628 | F14: 2602 | G14: 159 | H14: 955 | I14: 1806 | J14: 402 | K14: 824 | L14: 1384 | M14: 941 | N14: 949 | O14: 1376 | P14: 1379 | Q14: 1379 | R14: 928 | S14: 1007 | T14: 883 | W14: =IF(O14=0,0,IF(O14<=R14,O14/R14,IF(O14<R14+S14,1+(O14-R14)/S14,IF(O14<R14+S14+T14,2+(O14-R14-S14)/T14,IF(O14<R14+S14+T14+T14,3+((O14-R14-S14-T14)/(T14)),4))))) -> 1.4448858 | Y14: HL001 | Z14: 6412 | AA14: 0.02
B15: 11 | C15: EP300 | D15: TBSC | E15: 1535 | F15: 4585 | G15: 800 | H15: 2045 | I15: 3340 | J15: 1128 | K15: 1367 | L15: 3101 | M15: 1645 | N15: 1329 | O15: 3417 | P15: 1134 | Q15: 1134 | R15: 1443 | S15: 1301 | T15: 1494 | W15: =IF(O15=0,0,IF(O15<=R15,O15/R15,IF(O15<R15+S15,1+(O15-R15)/S15,IF(O15<R15+S15+T15,2+(O15-R15-S15)/T15,IF(O15<R15+S15+T15+T15,3+((O15-R15-S15-T15)/(T15)),4))))) -> 2.4504685 | X15: Order confirmation | Y15: LE3 | Z15: 38000 | AA15: 0.1
B16: 12 | C16: LE3 | D16: BSJ | E16: 10213 | F16: 7799 | G16: 16033 | H16: 9138 | I16: 14694 | J16: 10715 | K16: 8901 | L16: 16508 | M16: 12984 | N16: 10964 | O16: 18528 | P16: 12984 | Q16: 11667 | R16: 9538 | S16: 9586 | T16: 12119 | U16: 6743 | V16: 7000 | W16: =IF(O16=0,0,IF(O16<=R16,O16/R16,IF(O16<R16+S16,1+(O16-R16)/S16,IF(O16<R16+S16+T16,2+(O16-R16-S16)/T16,IF(O16<R16+S16+T16+T16,3+((O16-R16-S16-T16)/(T16)),4))))) -> 1.937826 | X16: 2
B17: 13 | C17: FS A/S | D17: BSJ, BTMV | E17: 1578 | F17: 3106 | G17: 2619 | H17: 1940 | I17: 3785 | J17: 2132 | K17: 1550 | L17: 4367 | M17: 1733 | N17: 1518 | O17: 4582 | P17: 1997 | Q17: 1935 | R17: 2271 | S17: 2126 | T17: 2231 | W17: =IF(O17=0,0,IF(O17<=R17,O17/R17,IF(O17<R17+S17,1+(O17-R17)/S17,IF(O17<R17+S17+T17,2+(O17-R17-S17)/T17,IF(O17<R17+S17+T17+T17,3+((O17-R17-S17-T17)/(T17)),4))))) -> 2.0829225 | Y17: Weathergrip | Z17: 10263 | AA17: 0.03
B18: 15 | C18: R624/710 | D18: TBSC,BSIN,BSJ | E18: 3317 | F18: 6849 | G18: 364 | H18: 1433 | I18: 5780 | J18: 183 | K18: 2046 | L18: 3917 | M18: 4363 | N18: 3114 | O18: 5166 | P18: 3044 | Q18: 3044 | R18: 2747 | S18: 2943 | T18: 2859 | W18: =IF(O18=0,0,IF(O18<=R18,O18/R18,IF(O18<R18+S18,1+(O18-R18)/S18,IF(O18<R18+S18+T18,2+(O18-R18-S18)/T18,IF(O18<R18+S18+T18+T18,3+((O18-R18-S18-T18)/(T18)),4))))) -> 1.8219504 | Y18: Nextry | Z18: 0 | AA18: 0
B19: 14 | C19: Weather grip | D19: BSJ | E19: 534 | F19: 1141 | G19: 968 | H19: 594 | I19: 1515 | J19: 405 | K19: 563 | L19: 1357 | M19: 405 | N19: 574 | O19: 1188 | P19: 405 | Q19: 481 | R19: 457 | S19: 605 | T19: 645 | W19: =IF(O19=0,0,IF(O19<=R19,O19/R19,IF(O19<R19+S19,1+(O19-R19)/S19,IF(O19<R19+S19+T19,2+(O19-R19-S19)/T19,IF(O19<R19+S19+T19+T19,3+((O19-R19-S19-T19)/(T19)),4))))) -> 2.1953488 | Y19: Winter | Z19: 47000 | AA19: 0.12
B20: 16 | C20: Winter | D20: BSJ, BSEU | E20: 4 | F20: 931 | G20: 6500 | H20: 4387 | I20: 3044 | J20: 15404 | K20: 9588 | L20: 8860 | M20: 22445 | N20: 13053 | O20: 18252 | P20: 19494 | Q20: 908 | R20: 11012 | S20: 8148 | T20: 0 | W20: =IF(O20=0,0,IF(O20<=R20,O20/R20,IF(O20<R20+S20,1+(O20-R20)/S20,IF(O20<R20+S20+T20,2+(O20-R20-S20)/T20,IF(O20<R20+S20+T20+T20,3+((O20-R20-S20-T20)/(T20)),4))))) -> 1.8885616 | X20: 1 | Y20: Total | Z20: 379912
B21: 17 | C21: T005A, Alenza 001 RE71RS, S007 | D21: TBSC,BSIN,BSJ | E21: 80 | F21: 631 | G21: 0 | H21: 62 | I21: 569 | J21: 0 | K21: 70 | L21: 499 | M21: 2 | N21: 103 | O21: 398 | P21: 2 | Q21: 60 | R21: 209 | S21: 196 | T21: 60 | W21: =IF(O21=0,0,IF(O21<=R21,O21/R21,IF(O21<R21+S21,1+(O21-R21)/S21,IF(O21<R21+S21+T21,2+(O21-R21-S21)/T21,IF(O21<R21+S21+T21+T21,3+((O21-R21-S21-T21)/(T21)),4))))) -> 1.9642857
B22: Total | E22: =SUM(E5:E21) -> 35388 | F22: =SUM(F5:F21) -> 68021 | G22: =SUM(G5:G21) -> 42468 | H22: =SUM(H5:H21) -> 42014 | I22: =SUM(I5:I21) -> 81273 | J22: =SUM(J5:J21) -> 52338 | K22: =SUM(K5:K21) -> 45164 | L22: =SUM(L5:L21) -> 88447 | ... T22: =SUM(T5:T21) -> 50910 | W22: =IF(O22=0,0,IF(O22<=R22,O22/R22,IF(O22<R22+S22,1+(O22-R22)/S22,IF(O22<R22+S22+T22,2+(O22-R22-S22)/T22,IF(O22<R22+S22+T22+T22,3+((O22-R22-S22-T22)/(T22)),4))))) -> 1.9825466
C23: Summary
X27: 58295
X28: =P22 -> 68371
X29: =X28/X27 -> 1.172845
L83: s
C87: 23OB(Y230601)
C216: 23OB(Y231201)

Sheet PSR(G)_Optional_
A2: Ⅱ：個別層別 | D2: 製品在庫管理を行う上で適切な切り口をベースに、在庫見込みをご連絡願います。
D3: 切り口例毎の在庫管理フォーマット（Sample）を下記致しますので、貴方管理の
D4: 切り口に合わせて調整頂き、送付用フォーマットとして設定の上、返信願います。
D5: ※ 切り口例：OE／REP／EXP別、夏／冬別、卸／小売別、メインサイズ／レアサイズ別
D6: ※ 管理フォーマット（Sample）の切り口は必要に応じて変更頂いて構いません。
HU8: h | HV8: h | HW8: h | HX8: h | HY8: h | HZ8: h | IA8: h | IB8: i | IF8: u | IH8: u
IJ9: sales | IM9: in | IR9: IN | IS9: ='[11]PCR Order Sheet final'!V4/1000 -> 0 | IT9: ='[11]PCR Order Sheet final'!Z4/1000 -> 0 | IU9: ='[11]PCR Order Sheet final'!CM4/1000 -> 0
GJ10: 2018 | GV10: 2019 | HH10: 2020 | IJ10: incom | IM10: out | IX10: IN
P11: 単位：千本 | IX11: OUT
A12: Stock Month Forecast | HT12: Y2021 | IF12: Y2022 | IR12: Y2023 | JD12: Y2024
C13: Target month | E13: Target Month | F13: 40148 | H13: 40179 | J13: 40210 | L13: 40238 | N13: 40269 | P13: 40299 | R13: 40330 | T13: 40360 | V13: 40391 | X13: 40422 | Z13: 40452 | AB13: 40483 | AD13: 40513 | AF13: 11 - Jan | AH13: Feb | AJ13: Mar | AL13: Apr | AN13: May | AP13: Jun | AR13: Jul | AT13: Aug | AV13: Sep | AX13: Oct | AZ13: Nov | BB13: Dec | BD13: 40909 | BF13: Feb-12 | BH13: Mar-12 | BJ13: Apr | BL13: May | BN13: Jun | BP13: Jul | BR13: Aug | BT13: Sep | BV13: Oct | BX13: Nov | BZ13: Dec | CB13: Jan | CD13: FEB | CF13: MAR | CH13: Apr | CJ13: MAY | CL13: June | CN13: July | CP13: Aug | CR13: SEP | CT13: OCT | CV13: Nov | CX13: DEC | CZ13: JAN | DB13: FEB | DD13: Mar | DF13: Apr | DH13: May | DJ13: June | DL13: July | DN13: Aug | DP13: Sep | DR13: Oct | DT13: Nov | DV13: Dec | DX13: Jan | DZ13: Feb | EB13: Mar | ED13: Apr | EF13: May | EH13: Jun | EJ13: Jul | EL13: Aug | EN13: Sep | EP13: Oct | ER13: Nov | ET13: Dec | EV13: Jan | EX13: Feb | EZ13: Mar | FB13: Apr | FD13: May | FF13: Jun | FH13: Jul | FJ13: Aug | FL13: Sep | FN13: Oct | FP13: Nov | FR13: Dec | FT13: Jan | FV13: Feb | FX13: Mar | FZ13: Apr | GB13: May | GC13: Jun | GD13: Jul | GE13: Aug | GF13: Sep | GG13: Oct | GH13: Nov | GI13: Dec | GJ13: Jan | GK13: Feb | GL13: Mar | GM13: Apr | GN13: May | GO13: Jun | GP13: Jul | GQ13: Aug | GR13: Sep | GS13: Oct | GT13: Nov | GU13: Dec | GV13: Jan | GW13: Feb | GX13: Mar | GY13: Apr | GZ13: May | HA13: Jun | HB13: Jul | HC13: Aug | HD13: Sep | HE13: Oct | HF13: Nov | HG13: Dec | HH13: Jan | HI13: Feb | HJ13: Mar | HK13: Apr | HL13: May | HM13: Jun | HN13: Jul | HO13: Aug | HP13: Sep | HQ13: Oct | HR13: Nov | HS13: Dec | HT13: Jan | HU13: Feb | HV13: Mar | HW13: Apr | HX13: May | HY13: Jun | HZ13: Jul | IA13: Aug | IB13: Sep | IC13: Oct | ID13: Nov | IE13: Dec | IF13: Jan | IG13: Feb | IH13: Mar | II13: Apr | IJ13: May | IK13: Jun | IL13: Jul | IM13: Aug | IN13: Sep | IO13: Oct | IP13: Nov | IQ13: Dec | IR13: Jan | IS13: Feb | IT13: Mar | IU13: Apr | IV13: May | IW13: Jun | IX13: Jul | IY13: Aug | IZ13: Sep | JA13: Oct | JB13: Nov | JC13: Dec | JD13: Jan | JE13: Feb | JF13: Mar | JG13: Apr | JH13: May | JI13: Jun | JJ13: Jul | JK13: Aug | JL13: Sep | JM13: Oct | JN13: Nov | JO13: Dec
F14: RB | G14: FCST | H14: BGT | I14: FCST | J14: BGT | K14: FCST | L14: BGT | M14: FCST | N14: BGT | O14: FCST | P14: BGT | Q14: FCST | R14: BGT | S14: FCST | T14: BGT | U14: FCST | V14: BGT | W14: FCST | X14: BGT | Y14: FCST | Z14: BGT | AA14: FCST | AB14: BGT | AC14: FCST | AD14: BGT | AE14: FCST | AF14: OB | AG14: FCST | AH14: OB | AI14: FCST | AJ14: OB | AK14: FCST | AL14: OB | AM14: FCST | AN14: OB | AO14: FCST | AP14: OB | AQ14: FCST | AR14: OB | AS14: FCST | AT14: OB | AU14: FCST | AV14: OB | AW14: FCST | AX14: OB | AY14: FCST | AZ14: OB | BA14: FCST | BB14: OB | BC14: FCST | BD14: OB | BE14: FCST | BF14: OB | BG14: FCST | BH14: OB | BI14: FCST | BJ14: OB | BK14: FCST | BL14: RB | BM14: Act | BN14: RB | BO14: Act | BP14: RB | BQ14: Act | BR14: RB | BS14: Act | BT14: RB | BU14: Act | BV14: RB | BW14: Act | BX14: RB | BY14: ACT | BZ14: RB | CA14: ACT | CB14: RB | CC14: ACT | CD14: RB | CE14: ACT | CF14: RB | CG14: ACT | CH14: RB | CI14: ACT | CJ14: RB | CK14: ACT | CL14: RB | CM14: ACT | CN14: RB | CO14: ACT | CP14: RB | CQ14: ACT | CR14: RB | CS14: ACT | CT14: RB | CU14: ACT | CV14: RB | CW14: ACT | CX14: RB | CY14: ACT | CZ14: OB | DA14: ACT | DB14: OB | DC14: ACT | DD14: OB | DE14: ACT | DF14: OB | DG14: ACT | DH14: OB | DI14: ACT | DJ14: OB | DK14: ACT | DL14: RB | DM14: Act | DN14: RB | DO14: Act | DP14: RB | DQ14: Act | DR14: RB | DS14: Act | DT14: RB | DU14: Act | DV14: RB | DW14: Act | DX14: OB | DY14: Act | DZ14: OB | EA14: Act | EB14: OB | EC14: Act | ED14: OB | EE14: Act | EF14: OB | EG14: Act | EH14: OB | EI14: Act | EJ14: RB | EK14: Act | EL14: RB | EM14: Act | EN14: RB | EO14: Act | EP14: RB | EQ14: Act | ER14: RB | ES14: Act | ET14: RB | EU14: Act | EV14: OB | EW14: FCST | EX14: OB | EY14: FCST | EZ14: OB | FA14: FCST | FB14: OB | FC14: FCST | FD14: OB | FE14: FCST | FF14: OB | FG14: FCST | FH14: RB | FI14: Act | FJ14: RB | FK14: Act | FL14: RB | FM14: Act | FN14: RB | FO14: Act | FP14: RB | FQ14: Act | FR14: RB | FS14: Act | FT14: OB | FU14: Act | FV14: OB | FW14: Act | FX14: OB | FY14: FCST | FZ14: OB | GA14: Act | GB14: Act | GC14: Act | GD14: Act | GE14: Act | GF14: FCST | GG14: FCST | GH14: FCST | GI14: FCST | GJ14: FCST | GK14: FCST | GL14: FCST | GM14: ACT | GN14: ACT | GO14: ACT | GP14: ACT | GQ14: ACT | GR14: ACT | GS14: ACT | GT14: ACT | GU14: ACT | GV14: ACT | GW14: ACT | GX14: ACT | GY14: ACT | GZ14: ACT | HA14: ACT | HB14: ACT | HC14: ACT | HD14: ACT | HE14: ACT | HF14: ACT | HG14: ACT | HH14: ACT | HI14: ACT | HJ14: Act | HK14: Act | HL14: Act | HM14: Act | HN14: Act | HO14: Act | HP14: Act | HQ14: Act | HR14: Act | HS14: Act | HT14: Act | HU14: Act | HV14: Act | HW14: Act | HX14: Act | HY14: Act | HZ14: Act | IA14: Act | IB14: Act | IC14: Act | ID14: Act | IE14: Act | IF14: Act | IG14: Act | IH14: Act | II14: Act | IJ14: Act | IK14: Act | IL14: Act | IM14: Act | IN14: Act | IO14: Act | IP14: Act | IQ14: Act | IR14: Act | IS14: Act | IT14: Act | IU14: Act | IV14: Act | IW14: Act | IX14: Act | IY14: FCST | IZ14: FCST | JA14: Act | JB14: FCST | JC14: FCST | JD14: Act | JE14: Act | JF14: Act | JG14: Act | JH14: Act | JI14: Act | JJ14: Act | JK14: FCST | JL14: FCST | JM14: FCST | JN14: FCST | JO14: FCST
B15: RFT | C15: 3 | D15: In | F15: 0.2 | G15: 0.104 | H15: 0.192 | I15: 0.03 | J15: =H16 -> 0.133 | K15: 0.192 | L15: 0.25 | M15: 0.778 | N15: 0.35 | O15: 0.77 | P15: 0.25 | Q15: 0.272 | R15: 0.18 | S15: 0.863 | T15: 0.3 | U15: 0.148 | V15: 0.35 | W15: 0.093 | X15: 0.4 | Y15: 0.722 | Z15: =X16 -> 0.3 | AA15: 0.484 | AB15: 0.18 | AC15: 0.256 | AD15: 0.15 | AE15: 0.187 | AF15: 0.282 | AG15: 0.071 | AH15: 0.265 | AI15: 0.459 | AJ15: 0.385 | AK15: 0.472 | AL15: 0.484 | AM15: 0.859 | AN15: 0.564 | AO15: 0.397 | AP15: 0.63 | AQ15: 0.259 | AR15: 0.449 | AS15: 1.157 | AT15: 0.329 | AU15: 0.525 | AV15: 0.519 | AW15: 1.144 | AX15: 0.649 | AY15: 1.212 | AZ15: 0.773 | BA15: 0.124 | BB15: 0.672 | BC15: 0.008 | BD15: 0.268 | BE15: 0.04 | BF15: 0.336 | BG15: 0.663 | BH15: 0.438 | BI15: 0.657 | BJ15: 0.554 | BK15: 1.113 | BL15: 0.64 | BM15: 0.508 | BN15: 0.664 | BO15: 1.153 | BP15: 0.592 | BQ15: 0.278 | BR15: 0.876 | BS15: 0.665 | BT15: 0.95 | BU15: 0.744 | BV15: 1.021 | BW15: 0.768 | BX15: 0.9944 | BY15: 1.076 | BZ15: 1.0143 | CA15: 0.823 | CB15: 0.606 | CC15: 0.595 | CD15: =+CD16 -> 0.532 | CE15: 0.555 | CF15: 0.807 | CG15: 1.189 | CH15: 0.734 | CI15: 0.722 | CJ15: 0.879 | CK15: 0.507 | CL15: 0.985 | CM15: 0.73 | CN15: 0.845 | CO15: 1.471 | CP15: 0.987 | CQ15: 0.237 | CR15: 1.09 | CS15: 0.922 | CT15: 1.095 | CU15: 0.621 | CV15: 1.362 | CW15: 0.245 | CX15: 1.305 | CY15: 1.116 | CZ15: 0.693 | DA15: 0.44 | DB15: 0.686 | DC15: 0.102 | DD15: 0.952 | DE15: 0.837 | DF15: 1.035 | DG15: =[12]PCR!$J$218 -> 0.098 | DH15: 1.037 | DI15: =[13]PCR!$J$227 -> 1.238 | DJ15: 1.25 | DK15: 1.131 | DL15: 0.894 | DM15: 1.59 | DN15: 1.048 | DO15: 1.328 | DP15: 1.177 | DQ15: 0.722 | DR15: 1.283 | DS15: 1.662 | DT15: 1.505 | DU15: =[14]PCR!$J$284 -> 1.042 | DV15: 1.44 | DW15: =[15]PCR!$J$279 -> 3.088 | DX15: 0.676 | DY15: =[16]PCR!$J$247 -> 0 | DZ15: 0.694 | EA15: =[17]PCR!$J$239 -> 3.103 | EB15: 1.004 | EC15: =[18]PCR!$J$241 -> 1.281 | ED15: 1.049 | EE15: =[19]PCR!$J$241 -> 0.412 | EF15: 1.193 | EG15: =[20]PCR!$J$245 -> 1.814 | EH15: 1.408 | EI15: =[21]PCR!$J$261 -> 0.452 | EJ15: 1.05 | EK15: =[22]PCR!$J$269 -> 0.778 | EL15: 1.23 | EM15: =[23]PCR!$J$292 -> 1.561 | EN15: 1.439 | EO15: =[24]PCR!$J$313 -> 1.657 | EP15: 1.766 | EQ15: =[25]PCR!$J$318 -> 0.398 | ER15: 1.891 | ES15: =[26]PCR!$J$285 -> 0.906 | ET15: 1.9 | EU15: =[27]PCR!$J$269 -> 0.646 | EV15: 0.738 | EW15: =[28]PCR!$J$242 -> 0.778 | EX15: 0.903 | EY15: =[29]PCR!$J$247 -> #REF! | EZ15: 1.025 | FA15: =[30]PCR!$J$251 -> 2.446 | FB15: 1.759 | FC15: 5.463 | FD15: 2.587 | FE15: =[31]PCR!$J$242 -> 2.299 | FF15: 2.763 | FG15: =[32]PCR!$J$249 -> 3.113 | FH15: 2.1245953 | FI15: =[33]PCR!$J$260 -> 2.108 | FJ15: 2.144657 | FK15: =[34]PCR!$J$257 -> 1.976 | FL15: 2.0376141 | FM15: =[35]PCR!$J$270 -> 3.056 | FN15: 2.1261572 | FO15: =[36]PCR!$J$263 -> 1.847 | FP15: 2.681 | FQ15: =[37]PCR!$J$262 -> 2.863 | FR15: 2.717 | FS15: =[38]PCR!$J$247 -> 1.091 | FT15: 2.486 | FU15: =[39]PCR!$J$241 -> 3.039 | FV15: 2.764 | FW15: =[40]PCR!$J$235 -> 1.64 | FX15: 2.104 | FY15: =[41]PCR!$J$224 -> 4.025 | FZ15: 4.678 | GA15: =[42]PCR!$J$232 -> 4.615 | GB15: 2.325 | GC15: 3.698 | GD15: 2.326 | GE15: 2.606 | GF15: 4.327 | GG15: 2.745 | GH15: 4.761 | GI15: 2.963 | GJ15: 3.127 | GK15: 5.651 | GL15: 3.356 | GM15: 3.974 | GN15: 2.811 | GO15: 2.207 | GP15: 5.899 | GQ15: 2.793 | GR15: 2.093 | GS15: 2.981 | GT15: 1.73 | GU15: 0.823 | GV15: 1.316 | GW15: 2.625 | GX15: 4.32 | GY15: 4.183 | GZ15: 2.174 | HA15: 1.53 | HB15: 5.038 | HC15: 1.93 | HD15: 4.4 | HE15: 4.16 | HF15: 5.292 | HG15: 1.891 | HH15: =[43]PCR!$I$503 -> 1.973 | HI15: =[44]PCR!$I$503 -> 2.04 | HJ15: 2.839 | HK15: =[45]PCR!$I$503 -> 1.138 | HL15: 0.992 | HM15: 1.443 | HN15: 2.378 | HO15: 0.246 | HP15: 2.067 | HQ15: 3.327 | HR15: 2.694 | HS15: 3.079 | HT15: 0.783 | HU15: 3.576 | HV15: 3.044 | HW15: 1.742 | HX15: 1.968 | HY15: =[46]Cate!I503 -> 7.255 | HZ15: 0.619 | IA15: =[47]Cate!I503 -> 3.73 | IB15: =[48]Cate!I503 -> 1.067 | IC15: 0.526 | ID15: =[49]PCR!$I$503 -> 4.169 | IE15: 3.999 | IF15: 3.401 | IG15: 0.539 | IH15: 0.599 | II15: 1.59 | IJ15: 1.558 | IK15: 0.096 | IL15: 2.058 | IM15: 3.206 | IN15: 1.377 | IO15: 3.458 | IP15: 2.485 | IQ15: 1.281 | IR15: 2.538 | IS15: 0.493 | IT15: 1.737 | IU15: 2.405 | IV15: 0.86 | IW15: 4.151 | IX15: 3.646 | IY15: 2.075 | IZ15: 3.505 | JA15: 2.826 | JB15: 1.572 | JC15: 1.296 | JD15: 1.866 | JE15: 0.741 | JF15: 2.882 | JG15: 2.328 | JH15: 2.274
D16: Out | F16: 0.193 | G16: 0.329 | H16: 0.133 | I16: 0.088 | J16: 0.133 | K16: 0.203 | L16: 0.195 | M16: 0.551 | N16: 0.287 | O16: 0.481 | P16: 0.212 | Q16: 0.312 | R16: 0.325 | S16: 0.586 | T16: 0.25 | U16: 0.324 | V16: 0.15 | W16: 0.156 | X16: 0.3 | Y16: 0.316 | Z16: 0.37 | AA16: 0.296 | AB16: 0.4 | AC16: 0.463 | AD16: 0.315 | AE16: 0.504 | AF16: 0.282 | AG16: 0.257 | AH16: 0.265 | AI16: 0.167 | AJ16: 0.385 | AK16: 0.423 | AL16: 0.484 | AM16: 0.605 | AN16: 0.564 | AO16: 0.432 | AP16: 0.63 | AQ16: 0.668 | AR16: 0.449 | AS16: 0.359 | AT16: 0.329 | AU16: 0.627 | AV16: 0.519 | AW16: 0.456 | AX16: 0.649 | AY16: 0.486 | AZ16: 0.773 | BA16: 0.598 | BB16: 0.672 | BC16: 0.726 | BD16: 0.268 | BE16: 0.261 | BF16: 0.336 | BG16: 0.844 | BH16: 0.438 | BI16: 0.353 | BJ16: 0.554 | BK16: 0.572 | BL16: 0.64 | BM16: 0.492 | BN16: 0.664 | BO16: 0.999 | BP16: 0.592 | BQ16: 0.547 | BR16: 0.876 | BS16: 1.112 | BT16: 0.95 | BU16: 0.525 | BV16: 1.021 | BW16: 1.013 | BX16: =+BX15 -> 0.9944 | BY16: 1.03 | BZ16: =+BZ15 -> 1.0143 | CA16: 0.802 | CB16: 0.606 | CC16: 0.537 | CD16: 0.532 | CE16: 0.394 | CF16: 0.807 | CG16: 0.802 | CH16: 0.734 | CI16: 0.786 | CJ16: 0.879 | CK16: 0.49 | CL16: 0.985 | CM16: 1.026 | CN16: =+CN15 -> 0.845 | CO16: 0.746 | CP16: 0.987 | CQ16: 0.669 | CR16: 1.09 | CS16: 1.114 | CT16: 1.095 | CU16: 0.452 | CV16: 1.362 | CW16: 1.005 | CX16: 1.305 | CY16: 1.015 | CZ16: 0.693 | DA16: 0.499 | DB16: 0.686 | DC16: 0.446 | DD16: 0.952 | DE16: 0.535 | DF16: 1.035 | DG16: =[12]PCR!$J$219 -> 0.527 | DH16: 1.037 | DI16: =[13]PCR!$J$228 -> 1.004 | DJ16: 1.25 | DK16: 1.019 | DL16: =DL15 -> 0.894 | DM16: 0.722 | DN16: =DN15 -> 1.048 | DO16: 1.207 | DP16: =DP15 -> 1.177 | DQ16: 0.848 | DR16: =DR15 -> 1.283 | DS16: 1.334 | DT16: =DT15 -> 1.505 | DU16: =[14]PCR!$J$285 -> 1.821 | DV16: =DV15 -> 1.44 | DW16: =[15]PCR!$J$280 -> 2.021 | DX16: =DX15 -> 0.676 | DY16: =[16]PCR!$J$248 -> 0.491 | DZ16: =DZ15 -> 0.694 | EA16: =[17]PCR!$J$240 -> 0.456 | EB16: =EB15 -> 1.004 | EC16: =[18]PCR!$J$242 -> 1.162 | ED16: =ED15 -> 1.049 | EE16: =[19]PCR!$J$242 -> 1.161 | EF16: =EF15 -> 1.193 | EG16: =[20]PCR!$J$246 -> 0.728 | EH16: =EH15 -> 1.408 | EI16: =[21]PCR!$J$262 -> 0.409 | EJ16: =EJ15 -> 1.05 | EK16: =[22]PCR!$J$270 -> 1.116 | EL16: =EL15 -> 1.23 | EM16: =[23]PCR!$J$293 -> 3.263 | EN16: =EN15 -> 1.439 | EO16: =[24]PCR!$J$314 -> 1.05 | EP16: =EP15 -> 1.766 | EQ16: =[25]PCR!$J$319 -> 1.287 | ER16: =ER15 -> 1.891 | ES16: =[26]PCR!$J$286 -> 0.726 | ET16: =ET15 -> 1.9 | EU16: =[27]PCR!$J$270 -> 1.364 | EV16: =EV15 -> 0.738 | EW16: =[28]PCR!$J$243 -> 0.552 | EX16: =EX15 -> 0.903 | EY16: =[29]PCR!$J$248 -> #REF! | EZ16: =EZ15 -> 1.025 | FA16: =[30]PCR!$J$252 -> 1.178 | FB16: =FB15 -> 1.759 | FC16: 1.878 | FD16: =FD15 -> 2.587 | FE16: =[31]PCR!$J$243 -> 3.772 | FF16: =FF15 -> 2.763 | FG16: =[32]PCR!$J$250 -> 1.944 | FH16: 2.1245953 | FI16: =[33]PCR!$J$261 -> 2.727 | FJ16: 2.144657 | FK16: =[34]PCR!$J$258 -> 2.145 | FL16: 2.0376141 | FM16: =[35]PCR!$J$271 -> 2.556 | FN16: 2.1261572 | FO16: =[36]PCR!$J$264 -> 2.487 | FP16: 2.681 | FQ16: =[37]PCR!$J$263 -> 3.85 | FR16: 2.717 | FS16: =[38]PCR!$J$248 -> 2.613 | FT16: 1.067 | FU16: =[39]PCR!$J$242 -> 2.762 | FV16: 1.683 | FW16: =[40]PCR!$J$236 -> 1.079 | FX16: 1.873 | FY16: =[41]PCR!$J$225 -> 2.166 | FZ16: 2.473 | GA16: =[42]PCR!$J$233 -> 3.036 | GB16: 3.614 | GC16: 2.449 | GD16: 3.762 | GE16: 2.563 | GF16: 2.944 | GG16: 3.891 | GH16: 3.934 | GI16: 4.808 | GJ16: 2.383 | GK16: 2.25 | GL16: 3.658 | GM16: 3.876 | GN16: 2.827 | GO16: 3.211 | GP16: 2.739 | GQ16: 2.635 | GR16: 2.068 | GS16: 2.037 | GT16: 2.67 | GU16: 2.919 | GV16: 1.796 | GW16: 2.694 | GX16: 2.492 | GY16: 3.202 | GZ16: 3.778 | HA16: 3.802 | HB16: 2.493 | HC16: 1.49 | HD16: 3.71 | HE16: 5.09 | HF16: 5.74 | HG16: 3.684 | HH16: =[43]PCR!$I$504 -> 1.568 | HI16: =[44]PCR!$I$504 -> 1.191 | HJ16: 1.565 | HK16: =[45]PCR!$J$503 -> 1.389 | HL16: 2.005 | HM16: 2.226 | HN16: 2.996 | HO16: 1.721 | HP16: 3.08 | HQ16: 3.454 | HR16: 3.531 | HS16: 2.255 | HT16: 1.798 | HU16: 1.118 | HV16: 3.531 | HW16: 1.748 | HX16: 1.982 | HY16: =[46]Cate!J503 -> 6.423 | HZ16: 1.308 | IA16: =[47]Cate!J503 -> 1.941 | IB16: =[48]Cate!J503 -> 1.255 | IC16: 2.775 | ID16: =[49]PCR!$J$503 -> 4.698 | IE16: 3.881 | IF16: 2.674 | IG16: 0.648 | IH16: 1.1 | II16: 1.72 | IJ16: 1.488 | IK16: 2.081 | IL16: 0.79 | IM16: 1.56 | IN16: 1.789 | IO16: 3.843 | IP16: 1.595 | IQ16: 2.185 | IR16: 2.763 | IS16: 1.754 | IT16: 2.255 | IU16: 1.834 | IV16: 0.907 | IW16: 2.927 | IX16: 2.43 | IY16: 3.191 | IZ16: 2.638 | JA16: 3.038 | JB16: 2.394 | JC16: 3.219 | JD16: 1.448 | JE16: 1.498 | JF16: 1.291 | JG16: 2.712 | JH16: 2.72
D17: Inventory | F17: 0.19 | G17: 0.4916 | H17: =F17+H15-H16 -> 0.249 | I17: =G17+I15-I16 -> 0.4336 | J17: =H17+J15-J16 -> 0.249 | K17: =I17+K15-K16 -> 0.4226 | L17: =J17+L15-L16 -> 0.304 | M17: =K17+M15-M16 -> 0.6496 | N17: =L17+N15-N16 -> 0.367 | O17: =M17+O15-O16 -> 0.9386 | ... AK17: =AI17+AK15-AK16 -> 1.1616 | AL17: =N17*1.137 -> 0.417279 | AM17: =AK17+AM15-AM16 -> 1.4156 | AN17: =P17*1.137 -> 0.460485 | AO17: =AM17+AO15-AO16 -> 1.3806 | AP17: =R17*1.137 -> 0.29562 | AQ17: 0.98 | AR17: =T17*1.137 -> 0.35247 | AS17: =AQ17+AS15-AS16 -> 1.778 | AT17: =V17*1.137 -> 0.57987 | AU17: =AS17+AU15-AU16 -> 1.676 | AV17: =X17*1.137 -> 0.69357 | AW17: =AU17+AW15-AW16 -> 2.364 | AX17: =Z17*1.137 -> 0.61398 | AY17: =AW17+AY15-AY16 -> 3.09 | AZ17: 0.36384 | BA17: 2.616 | BB17: 0.176235 | BC17: 1.898 | BD17: 0.176235 | BE17: 1.677 | BF17: =BD17+BF15-BF16 -> 0.176235 | BG17: =BE17+BG15-BG16 -> 1.496 | BH17: =AJ17*1.137 -> 0.176235 | BI17: =BG17+BI15-BI16 -> 1.8 | BJ17: =AL17*1.137 -> 0.47444622 | BK17: =BI17+BK15-BK16 -> 2.341 | BL17: =AN17*1.137 -> 0.52357145 | BM17: =BK17+BM15-BM16 -> 2.357 | BN17: 0.664 | BO17: =BM17+BO15-BO16 -> 2.511 | BP17: 0.664 | BQ17: =BO17+BQ15-BQ16 -> 2.242 | BR17: 0.664 | BS17: =BQ17+BS15-BS16 -> 1.795 | BT17: 0.664 | BU17: =BS17+BU15-BU16 -> 2.014 | BV17: 0.664 | BW17: =BU17+BW15-BW16 -> 1.769 | BX17: 0.664 | BY17: =BW17+BY15-BY16 -> 1.815 | BZ17: 0.664 | CA17: =BY17+CA15-CA16 -> 1.836 | CB17: 0.664 | CC17: =CA17+CC15-CC16 -> 1.894 | CD17: 0.664 | CE17: =CC17+CE15-CE16 -> 2.055 | CF17: 0.664 | CG17: =CE17+CG15-CG16 -> 2.442 | CH17: 0.664 | CI17: =CG17+CI15-CI16 -> 2.378 | CJ17: 0.664 | CK17: =CI17+CK15-CK16 -> 2.395 | CL17: 0.664 | CM17: =CK17+CM15-CM16 -> 2.099 | CN17: 0.664 | CO17: =CM17+CO15-CO16 -> 2.824 | CP17: 0.664 | CQ17: =CO17+CQ15-CQ16 -> 2.392 | CR17: 0.664 | CS17: =CQ17+CS15-CS16 -> 2.2 | CT17: 0.664 | CU17: =CS17+CU15-CU16 -> 2.369 | CV17: 0.664 | CW17: =CU17+CW15-CW16 -> 1.609 | CX17: 0.664 | CY17: 1.809 | CZ17: =CX17+CZ15-CZ16 -> 0.664 | DA17: =CY17+DA15-DA16 -> 1.75 | DB17: =CZ17+DB15-DB16 -> 0.664 | DC17: =DA17+DC15-DC16 -> 1.406 | DD17: =DB17+DD15-DD16 -> 0.664 | DE17: =DC17+DE15-DE16 -> 1.708 | DF17: =DD17+DF15-DF16 -> 0.664 | DG17: =DE17+DG15-DG16 -> 1.279 | DH17: 0.664 | DI17: =DG17+DI15-DI16 -> 1.513 | DJ17: 0.664 | DK17: =DI17+DK15-DK16 -> 1.625 | DL17: 0.664 | DM17: =DK17+DM15-DM16 -> 2.493 | DN17: 0.664 | DO17: =DM17+DO15-DO16 -> 2.614 | DP17: 0.664 | DQ17: =DO17+DQ15-DQ16 -> 2.488 | DR17: 0.664 | DS17: =DQ17+DS15-DS16 -> 2.816 | DT17: 0.664 | DU17: =DS17+DU15-DU16 -> 2.037 | DV17: 0.664 | DW17: =DU17+DW15-DW16 -> 3.104 | DX17: 0.664 | DY17: =DW17+DY15-DY16 -> 2.613 | DZ17: 0.664 | EA17: =DY17+EA15-EA16 -> 5.26 | EB17: 0.664 | EC17: =EA17+EC15-EC16 -> 5.379 | ED17: 0.664 | EE17: =EC17+EE15-EE16 -> 4.63 | EF17: 0.664 | EG17: =EE17+EG15-EG16 -> 5.716 | EH17: 0.664 | EI17: =EG17+EI15-EI16 -> 5.759 | EJ17: 0.664 | EK17: =EI17+EK15-EK16 -> 5.421 | EL17: 0.664 | EM17: =EK17+EM15-EM16 -> 3.719 | EN17: 0.664 | EO17: 4.162 | EP17: 0.664 | EQ17: =EO17+EQ15-EQ16 -> 3.273 | ER17: 0.664 | ES17: =EQ17+ES15-ES16 -> 3.453 | ET17: 0.664 | EU17: =ES17+EU15-EU16 -> 2.735 | EV17: 0.664 | EW17: =EU17+EW15-EW16 -> 2.961 | EX17: 0.664 | EY17: =EW17+EY15-EY16 -> #REF! | EZ17: 0.664 | FA17: =EY17+FA15-FA16 -> #REF! | FB17: 0.664 | FC17: =FA17+FC15-FC16 -> #REF! | FD17: 0.664 | FE17: 6.016 | FF17: 0.664 | FG17: =FE17+FG15-FG16 -> 7.185 | FH17: 0.664 | FI17: =FG17+FI15-FI16 -> 6.566 | FJ17: 0.664 | FK17: =FI17+FK15-FK16 -> 6.397 | FL17: 0.664 | FM17: =FK17+FM15-FM16 -> 6.897 | FN17: 0.664 | FO17: =FM17+FO15-FO16 -> 6.257 | FP17: 0.664 | FQ17: =FO17+FQ15-FQ16 -> 5.27 | FR17: 3.614 | FS17: =FQ17+FS15-FS16 -> 3.748 | FT17: =FR17+FT15-FT16 -> 5.033 | FU17: =FS17+FU15-FU16 -> 4.025 | FV17: =FT17+FV15-FV16 -> 6.114 | FW17: =FU17+FW15-FW16 -> 4.586 | FX17: =FV17+FX15-FX16 -> 6.345 | FY17: =FW17+FY15-FY16 -> 6.445 | FZ17: 8.957 | GA17: 8.252 | GB17: =GA17+GB15-GB16 -> 6.963 | GC17: =GB17+GC15-GC16 -> 8.212 | GD17: 6.791 | GE17: 6.847 | GF17: =GE17+GF15-GF16 -> 8.23 | GG17: =GF17+GG15-GG16 -> 7.084 | GH17: 7.956 | GI17: =GH17+GI15-GI16 -> 6.111 | GJ17: =GI17+GJ15-GJ16 -> 6.855 | GK17: 10.29 | GL17: =GK17+GL15-GL16 -> 9.988 | GM17: =GL17+GM15-GM16 -> 10.086 | GN17: =GM17+GN15-GN16 -> 10.07 | GO17: =GN17+GO15-GO16 -> 9.066 | GP17: =GO17+GP15-GP16 -> 12.226 | GQ17: =GP17+GQ15-GQ16 -> 12.384 | GR17: =GQ17+GR15-GR16 -> 12.409 | GS17: =GR17+GS15-GS16 -> 13.353 | ... HU17: =HT17+HU15-HU16 -> 7.883 | HV17: 7.359 | HW17: =HV17+HW15-HW16 -> 7.353 | HX17: =HW17+HX15-HX16 -> 7.339 | HY17: =HX17+HY15-HY16 -> 8.171 | HZ17: =HY17+HZ15-HZ16 -> 7.482 | IA17: =HZ17+IA15-IA16 -> 9.271 | IB17: =IA17+IB15-IB16 -> 9.083 | IC17: =IB17+IC15-IC16 -> 6.834 | ID17: =IC17+ID15-ID16 -> 6.305 | ... IL17: =IK17+IL15-IL16 -> 5.763 | IM17: 7.405 | IN17: =IM17+IN15-IN16 -> 6.993 | IO17: =IN17+IO15-IO16 -> 6.608 | IP17: =IO17+IP15-IP16 -> 7.498 | IQ17: =IP17+IQ15-IQ16 -> 6.594 | IR17: =IQ17+IR15-IR16 -> 6.369 | IS17: 5.168 | IT17: =IS17+IT15-IT16 -> 4.65 | IU17: =IT17+IU15-IU16 -> 5.221 | IV17: =IU17+IV15-IV16 -> 5.174 | IW17: =IV17+IW15-IW16 -> 6.398 | IX17: =IW17+IX15-IX16 -> 7.614 | IY17: =IX17+IY15-IY16 -> 6.498 | IZ17: =IY17+IZ15-IZ16 -> 7.365 | JA17: =IZ17+JA15-JA16 -> 7.153 | ... JO17: =JN17+JO15-JO16 -> 4.83
D18: month | E18: 1.9 | F18: 0.75949367 | G18: 3.3518182 | H18: =IF(H17<=J16,H17/J16,IF(H17<=J16+L16,1+(H17-J16)/L16,IF(H17<=J16+L16+N16,2+(H17-J16-L16)/N16,H17*3/(J16+L16+N16)))) -> 1.5948718 | I18: =IF(I17<=K16,I17/K16,IF(I17<=K16+M16,1+(I17-K16)/M16,IF(I17<=K16+M16+O16,2+(I17-K16-M16)/O16,I17*3/(K16+M16+O16)))) -> 1.4185118 | J18: =IF(J17<=L16,J17/L16,IF(J17<=L16+N16,1+(J17-L16)/N16,IF(J17<=L16+N16+P16,2+(J17-L16-N16)/P16,J17*3/(L16+N16+P16)))) -> 1.1881533 | K18: =IF(K17<=M16,K17/M16,IF(K17<=M16+O16,1+(K17-M16)/O16,IF(K17<=M16+O16+Q16,2+(K17-M16-O16)/Q16,K17*3/(M16+O16+Q16)))) -> 0.76696915 | L18: =IF(L17<=N16,L17/N16,IF(L17<=N16+P16,1+(L17-N16)/P16,IF(L17<=N16+P16+R16,2+(L17-N16-P16)/R16,L17*3/(N16+P16+R16)))) -> 1.0801887 | M18: =IF(M17<=O16,M17/O16,IF(M17<=O16+Q16,1+(M17-O16)/Q16,IF(M17<=O16+Q16+S16,2+(M17-O16-Q16)/S16,M17*3/(O16+Q16+S16)))) -> 1.5403846 | N18: =IF(N17<=P16,N17/P16,IF(N17<=P16+R16,1+(N17-P16)/R16,IF(N17<=P16+R16+T16,2+(N17-P16-R16)/T16,N17*3/(P16+R16+T16)))) -> 1.4769231 | O18: =IF(O17<=Q16,O17/Q16,IF(O17<=Q16+S16,1+(O17-Q16)/S16,IF(O17<=Q16+S16+U16,2+(O17-Q16-S16)/U16,O17*3/(Q16+S16+U16)))) -> 2.1253086 | ... AK18: =IF(AK17<=AM16,AK17/AM16,IF(AK17<=AM16+AO16,1+(AK17-AM16)/AO16,IF(AK17<=AM16+AO16+AQ16,2+(AK17-AM16-AO16)/AQ16,AK17*3/(AM16+AO16+AQ16)))) -> 2.1865269 | AL18: =N18*1.137 -> 1.6792615 | AM18: =IF(AM17<=AO16,AM17/AO16,IF(AM17<=AO16+AQ16,1+(AM17-AO16)/AQ16,IF(AM17<=AO16+AQ16+AS16,2+(AM17-AO16-AQ16)/AS16,AM17*3/(AO16+AQ16+AS16)))) -> 2.8791086 | AN18: =P18*1.137 -> 1.50084 | AO18: =IF(AO17<=AQ16,AO17/AQ16,IF(AO17<=AQ16+AS16,1+(AO17-AQ16)/AS16,IF(AO17<=AQ16+AS16+AU16,2+(AO17-AQ16-AS16)/AU16,AO17*3/(AQ16+AS16+AU16)))) -> 2.5639553 | AP18: =R18*1.137 -> 1.2128 | AQ18: =IF(AQ17<=AS16,AQ17/AS16,IF(AQ17<=AS16+AU16,1+(AQ17-AS16)/AU16,IF(AQ17<=AS16+AU16+AW16,2+(AQ17-AS16-AU16)/AW16,AQ17*3/(AS16+AU16+AW16)))) -> 1.9904306 | AR18: =T18*1.137 -> 1.7434 | AS18: =IF(AS17<=AU16,AS17/AU16,IF(AS17<=AU16+AW16,1+(AS17-AU16)/AW16,IF(AS17<=AU16+AW16+AY16,2+(AS17-AU16-AW16)/AY16,AS17*3/(AU16+AW16+AY16)))) -> 3.3996176 | AT18: =V18*1.137 -> 1.7823243 | AU18: =IF(AU17<=AW16,AU17/AW16,IF(AU17<=AW16+AY16,1+(AU17-AW16)/AY16,IF(AU17<=AW16+AY16+BA16,2+(AU17-AW16-AY16)/BA16,AU17*3/(AW16+AY16+BA16)))) -> 3.2649351 | AV18: =X18*1.137 -> 1.8192 | AW18: =IF(AW17<=AY16,AW17/AY16,IF(AW17<=AY16+BA16,1+(AW17-AY16)/BA16,IF(AW17<=AY16+BA16+BC16,2+(AW17-AY16-BA16)/BC16,AW17*3/(AY16+BA16+BC16)))) -> 3.918232 | AX18: =Z18*1.137 -> 1.6423333 | AY18: =IF(AY17<=BA16,AY17/BA16,IF(AY17<=BA16+BC16,1+(AY17-BA16)/BC16,IF(AY17<=BA16+BC16+BE16,2+(AY17-BA16-BC16)/BE16,AY17*3/(BA16+BC16+BE16)))) -> 5.8485804 | AZ18: 1.1571596 | BA18: 4.2861824 | BB18: 0.62494681 | BC18: 3.9053498 | BD18: 0.66503774 | BE18: 2.8391608 | BF18: =AH18*1.137 -> 0.45775325 | BG18: =IF(BG17<=BI16,BG17/BI16,IF(BG17<=BI16+BK16,1+(BG17-BI16)/BK16,IF(BG17<=BI16+BK16+BM16,2+(BG17-BI16-BK16)/BM16,BG17*3/(BI16+BK16+BM16)))) -> 3.1672548 | BH18: =AJ18*1.137 -> 0.3641219 | BI18: =IF(BI17<=BK16,BI17/BK16,IF(BI17<=BK16+BM16,1+(BI17-BK16)/BM16,IF(BI17<=BK16+BM16+BO16,2+(BI17-BK16-BM16)/BO16,BI17*3/(BK16+BM16+BO16)))) -> 2.7367367 | BJ18: =AL18*1.137 -> 1.9093204 | BK18: =IF(BK17<=BM16,BK17/BM16,IF(BK17<=BM16+BO16,1+(BK17-BM16)/BO16,IF(BK17<=BM16+BO16+BQ16,2+(BK17-BM16-BO16)/BQ16,BK17*3/(BM16+BO16+BQ16)))) -> 3.4460255 | BL18: =AN18*1.137 -> 1.7064551 | BM18: =IF(BM17<=BO16,BM17/BO16,IF(BM17<=BO16+BQ16,1+(BM17-BO16)/BQ16,IF(BM17<=BO16+BQ16+BS16,2+(BM17-BO16-BQ16)/BS16,BM17*3/(BO16+BQ16+BS16)))) -> 2.7293165 | BN18: =AP18*1.137 -> 1.3789536 | BO18: =IF(BO17<=BQ16,BO17/BQ16,IF(BO17<=BQ16+BS16,1+(BO17-BQ16)/BS16,IF(BO17<=BQ16+BS16+BU16,2+(BO17-BQ16-BS16)/BU16,BO17*3/(BQ16+BS16+BU16)))) -> 3.4491758 | BP18: =AR18*1.137 -> 1.9822458 | BQ18: =IF(BQ17<=BS16,BQ17/BS16,IF(BQ17<=BS16+BU16,1+(BQ17-BS16)/BU16,IF(BQ17<=BS16+BU16+BW16,2+(BQ17-BS16-BU16)/BW16,BQ17*3/(BS16+BU16+BW16)))) -> 2.5972359 | BR18: =AT18*1.137 -> 2.0265028 | BS18: =IF(BS17<=BU16,BS17/BU16,IF(BS17<=BU16+BW16,1+(BS17-BU16)/BW16,IF(BS17<=BU16+BW16+BY16,2+(BS17-BU16-BW16)/BY16,BS17*3/(BU16+BW16+BY16)))) -> 2.2495146 | BT18: =AV18*1.137 -> 2.0684304 | BU18: =IF(BU17<=BW16,BU17/BW16,IF(BU17<=BW16+BY16,1+(BU17-BW16)/BY16,IF(BU17<=BW16+BY16+CA16,2+(BU17-BW16-BY16)/CA16,BU17*3/(BW16+BY16+CA16)))) -> 1.9718447 | BV18: =IF(BV17<=BX16,BV17/BX16,IF(BV17<=BX16+BZ16,1+(BV17-BX16)/BZ16,IF(BV17<=BX16+BZ16+CB16,2+(BV17-BX16-BZ16)/CB16,BV17*3/(BX16+BZ16+CB16)))) -> 0.66773934 | BW18: =IF(BW17<=BY16,BW17/BY16,IF(BW17<=BY16+CA16,1+(BW17-BY16)/CA16,IF(BW17<=BY16+CA16+CC16,2+(BW17-BY16-CA16)/CC16,BW17*3/(BY16+CA16+CC16)))) -> 1.9214464 | BX18: =IF(BX17<=BZ16,BX17/BZ16,IF(BX17<=BZ16+CB16,1+(BX17-BZ16)/CB16,IF(BX17<=BZ16+CB16+CD16,2+(BX17-BZ16-CB16)/CD16,BX17*3/(BZ16+CB16+CD16)))) -> 0.65463867 | BY18: =IF(BY17<=CA16,BY17/CA16,IF(BY17<=CA16+CC16,1+(BY17-CA16)/CC16,IF(BY17<=CA16+CC16+CE16,2+(BY17-CA16-CC16)/CE16,BY17*3/(CA16+CC16+CE16)))) -> 3.1419504 | BZ18: =IF(BZ17<=CB16,BZ17/CB16,IF(BZ17<=CB16+CD16,1+(BZ17-CB16)/CD16,IF(BZ17<=CB16+CD16+CF16,2+(BZ17-CB16-CD16)/CF16,BZ17*3/(CB16+CD16+CF16)))) -> 1.1090226 | CA18: =IF(CA17<=CC16,CA17/CC16,IF(CA17<=CC16+CE16,1+(CA17-CC16)/CE16,IF(CA17<=CC16+CE16+CG16,2+(CA17-CC16-CE16)/CG16,CA17*3/(CC16+CE16+CG16)))) -> 3.1783035 | CB18: =IF(CB17<=CD16,CB17/CD16,IF(CB17<=CD16+CF16,1+(CB17-CD16)/CF16,IF(CB17<=CD16+CF16+CH16,2+(CB17-CD16-CF16)/CH16,CB17*3/(CD16+CF16+CH16)))) -> 1.1635688 | ... CG18: =IF(CG17<=CI16,CG17/CI16,IF(CG17<=CI16+CK16,1+(CG17-CI16)/CK16,IF(CG17<=CI16+CK16+CM16,2+(CG17-CI16-CK16)/CM16,CG17*3/(CI16+CK16+CM16)))) -> 3.18245 | CH18: =BJ18*1.137 -> 2.1708973 | CI18: =IF(CI17<=CK16,CI17/CK16,IF(CI17<=CK16+CM16,1+(CI17-CK16)/CM16,IF(CI17<=CK16+CM16+CO16,2+(CI17-CK16-CM16)/CO16,CI17*3/(CK16+CM16+CO16)))) -> 3.1538462 | CJ18: =BL18*1.137 -> 1.9402394 | CK18: =IF(CK17<=CM16,CK17/CM16,IF(CK17<=CM16+CO16,1+(CK17-CM16)/CO16,IF(CK17<=CM16+CO16+CQ16,2+(CK17-CM16-CO16)/CQ16,CK17*3/(CM16+CO16+CQ16)))) -> 2.9312407 | CL18: =BN18*1.137 -> 1.5678702 | CM18: =IF(CM17<=CO16,CM17/CO16,IF(CM17<=CO16+CQ16,1+(CM17-CO16)/CQ16,IF(CM17<=CO16+CQ16+CS16,2+(CM17-CO16-CQ16)/CS16,CM17*3/(CO16+CQ16+CS16)))) -> 2.6140036 | CN18: =BP18*1.137 -> 2.2538135 | CO18: =IF(CO17<=CQ16,CO17/CQ16,IF(CO17<=CQ16+CS16,1+(CO17-CQ16)/CS16,IF(CO17<=CQ16+CS16+CU16,2+(CO17-CQ16-CS16)/CU16,CO17*3/(CQ16+CS16+CU16)))) -> 3.790604 | CP18: =BR18*1.137 -> 2.3041336 | CQ18: =IF(CQ17<=CS16,CQ17/CS16,IF(CQ17<=CS16+CU16,1+(CQ17-CS16)/CU16,IF(CQ17<=CS16+CU16+CW16,2+(CQ17-CS16-CU16)/CW16,CQ17*3/(CS16+CU16+CW16)))) -> 2.8218905 | CR18: =BT18*1.137 -> 2.3518054 | CS18: =IF(CS17<=CU16,CS17/CU16,IF(CS17<=CU16+CW16,1+(CS17-CU16)/CW16,IF(CS17<=CU16+CW16+CY16,2+(CS17-CU16-CW16)/CY16,CS17*3/(CU16+CW16+CY16)))) -> 2.7320197 | CT18: =BV18*1.137 -> 0.75921963 | CU18: =IF(CU17<=CW16,CU17/CW16,IF(CU17<=CW16+CY16,1+(CU17-CW16)/CY16,IF(CU17<=CW16+CY16+DA16,2+(CU17-CW16-CY16)/DA16,CU17*3/(CW16+CY16+DA16)))) -> 2.6993988 | CV18: =BX18*1.137 -> 0.74432416 | CW18: =IF(CW17<=CY16,CW17/CY16,IF(CW17<=CY16+DA16,1+(CW17-CY16)/DA16,IF(CW17<=CY16+DA16+DC16,2+(CW17-CY16-DA16)/DC16,CW17*3/(CY16+DA16+DC16)))) -> 2.2130045 | CX18: =BZ18*1.137 -> 1.2609586 | CY18: =IF(CY17<=DA16,CY17/DA16,IF(CY17<=DA16+DC16,1+(CY17-DA16)/DC16,IF(CY17<=DA16+DC16+DE16,2+(CY17-DA16-DC16)/DE16,CY17*3/(DA16+DC16+DE16)))) -> 3.6668919 | CZ18: =CB18*1.137 -> 1.3229777 | DA18: =IF(DA17<=DC16,DA17/DC16,IF(DA17<=DC16+DE16,1+(DA17-DC16)/DE16,IF(DA17<=DC16+DE16+DG16,2+(DA17-DC16-DE16)/DG16,DA17*3/(DC16+DE16+DG16)))) -> 3.4814324 | DB18: =CD18*1.137 -> 0.93552416 | DC18: =IF(DC17<=DE16,DC17/DE16,IF(DC17<=DE16+DG16,1+(DC17-DE16)/DG16,IF(DC17<=DE16+DG16+DI16,2+(DC17-DE16-DG16)/DI16,DC17*3/(DE16+DG16+DI16)))) -> 2.3426295 | DD18: =CF18*1.137 -> 1.0285668 | DE18: =IF(DE17<=DG16,DE17/DG16,IF(DE17<=DG16+DI16,1+(DE17-DG16)/DI16,IF(DE17<=DG16+DI16+DK16,2+(DE17-DG16-DI16)/DK16,DE17*3/(DG16+DI16+DK16)))) -> 2.1736997 | DF18: =CF18*1.137 -> 1.0285668 | DG18: =IF(DG17<=DI16,DG17/DI16,IF(DG17<=DI16+DK16,1+(DG17-DI16)/DK16,IF(DG17<=DI16+DK16+DM16,2+(DG17-DI16-DK16)/DM16,DG17*3/(DI16+DK16+DM16)))) -> 1.2698724 | DH18: =CH18*1.137 -> 2.4683102 | DI18: =IF(DI17<=DK16,DI17/DK16,IF(DI17<=DK16+DM16,1+(DI17-DK16)/DM16,IF(DI17<=DK16+DM16+DO16,2+(DI17-DK16-DM16)/DO16,DI17*3/(DK16+DM16+DO16)))) -> 1.6842105 | DJ18: 1.5 | DK18: =IF(DK17<=DM16,DK17/DM16,IF(DK17<=DM16+DO16,1+(DK17-DM16)/DO16,IF(DK17<=DM16+DO16+DQ16,2+(DK17-DM16-DO16)/DQ16,DK17*3/(DM16+DO16+DQ16)))) -> 1.7481359 | DL18: 1.5 | DM18: =IF(DM17<=DO16,DM17/DO16,IF(DM17<=DO16+DQ16,1+(DM17-DO16)/DQ16,IF(DM17<=DO16+DQ16+DS16,2+(DM17-DO16-DQ16)/DS16,DM17*3/(DO16+DQ16+DS16)))) -> 2.3283358 | DN18: 1.5 | DO18: =IF(DO17<=DQ16,DO17/DQ16,IF(DO17<=DQ16+DS16,1+(DO17-DQ16)/DS16,IF(DO17<=DQ16+DS16+DU16,2+(DO17-DQ16-DS16)/DU16,DO17*3/(DQ16+DS16+DU16)))) -> 2.2372323 | DP18: 1.5 | DQ18: =IF(DQ17<=DS16,DQ17/DS16,IF(DQ17<=DS16+DU16,1+(DQ17-DS16)/DU16,IF(DQ17<=DS16+DU16+DW16,2+(DQ17-DS16-DU16)/DW16,DQ17*3/(DS16+DU16+DW16)))) -> 1.6337177 | DR18: 1.5 | DS18: =IF(DS17<=DU16,DS17/DU16,IF(DS17<=DU16+DW16,1+(DS17-DU16)/DW16,IF(DS17<=DU16+DW16+DY16,2+(DS17-DU16-DW16)/DY16,DS17*3/(DU16+DW16+DY16)))) -> 1.4923305 | DT18: 1.5 | DU18: =IF(DU17<=DW16,DU17/DW16,IF(DU17<=DW16+DY16,1+(DU17-DW16)/DY16,IF(DU17<=DW16+DY16+EA16,2+(DU17-DW16-DY16)/EA16,DU17*3/(DW16+DY16+EA16)))) -> 1.0325866 | DV18: 1.5 | DW18: =IF(DW17<=DY16,DW17/DY16,IF(DW17<=DY16+EA16,1+(DW17-DY16)/EA16,IF(DW17<=DY16+EA16+EC16,2+(DW17-DY16-EA16)/EC16,DW17*3/(DY16+EA16+EC16)))) -> 4.4153627 | DX18: 1.5 | DY18: =IF(DY17<=EA16,DY17/EA16,IF(DY17<=EA16+EC16,1+(DY17-EA16)/EC16,IF(DY17<=EA16+EC16+EE16,2+(DY17-EA16-EC16)/EE16,DY17*3/(EA16+EC16+EE16)))) -> 2.8570198 | DZ18: 1.5 | EA18: =IF(EA17<=EC16,EA17/EC16,IF(EA17<=EC16+EE16,1+(EA17-EC16)/EE16,IF(EA17<=EC16+EE16+EG16,2+(EA17-EC16-EE16)/EG16,EA17*3/(EC16+EE16+EG16)))) -> 5.1720747 | EB18: 1.5 | EC18: =IF(EC17<=EE16,EC17/EE16,IF(EC17<=EE16+EG16,1+(EC17-EE16)/EG16,IF(EC17<=EE16+EG16+EI16,2+(EC17-EE16-EG16)/EI16,EC17*3/(EE16+EG16+EI16)))) -> 7.0221932 | ED18: 1.5 | EE18: =IF(EE17<=EG16,EE17/EG16,IF(EE17<=EG16+EI16,1+(EE17-EG16)/EI16,IF(EE17<=EG16+EI16+EK16,2+(EE17-EG16-EI16)/EK16,EE17*3/(EG16+EI16+EK16)))) -> 6.1651132 | EF18: 1.5 | EG18: =IF(EG17<=EI16,EG17/EI16,IF(EG17<=EI16+EK16,1+(EG17-EI16)/EK16,IF(EG17<=EI16+EK16+EM16,2+(EG17-EI16-EK16)/EM16,EG17*3/(EI16+EK16+EM16)))) -> 3.5814536 | EH18: 1.5 | EI18: =IF(EI17<=EK16,EI17/EK16,IF(EI17<=EK16+EM16,1+(EI17-EK16)/EM16,IF(EI17<=EK16+EM16+EO16,2+(EI17-EK16-EM16)/EO16,EI17*3/(EK16+EM16+EO16)))) -> 3.182354 | EJ18: 2.5 | EK18: =IF(EK17<=EM16,EK17/EM16,IF(EK17<=EM16+EO16,1+(EK17-EM16)/EO16,IF(EK17<=EM16+EO16+EQ16,2+(EK17-EM16-EO16)/EQ16,EK17*3/(EM16+EO16+EQ16)))) -> 2.8609169 | EL18: 2.5 | EM18: =IF(EM17<=EO16,EM17/EO16,IF(EM17<=EO16+EQ16,1+(EM17-EO16)/EQ16,IF(EM17<=EO16+EQ16+ES16,2+(EM17-EO16-EQ16)/ES16,EM17*3/(EO16+EQ16+ES16)))) -> 3.6425073 | EN18: 2.5 | EO18: =IF(EO17<=EQ16,EO17/EQ16,IF(EO17<=EQ16+ES16,1+(EO17-EQ16)/ES16,IF(EO17<=EQ16+ES16+EU16,2+(EO17-EQ16-ES16)/EU16,EO17*3/(EQ16+ES16+EU16)))) -> 3.6973645 | EP18: 2.5 | EQ18: =IF(EQ17<=ES16,EQ17/ES16,IF(EQ17<=ES16+EU16,1+(EQ17-ES16)/EU16,IF(EQ17<=ES16+EU16+EW16,2+(EQ17-ES16-EU16)/EW16,EQ17*3/(ES16+EU16+EW16)))) -> 3.7165026 | ER18: 2.5 | ES18: =IF(ES17<=EU16,ES17/EU16,IF(ES17<=EU16+EW16,1+(ES17-EU16)/EW16,IF(ES17<=EU16+EW16+EY16,2+(ES17-EU16-EW16)/EY16,ES17*3/(EU16+EW16+EY16)))) -> #REF! | ET18: 2.5 | EU18: =IF(EU17<=EW16,EU17/EW16,IF(EU17<=EW16+EY16,1+(EU17-EW16)/EY16,IF(EU17<=EW16+EY16+FA16,2+(EU17-EW16-EY16)/FA16,EU17*3/(EW16+EY16+FA16)))) -> #REF! | EV18: 2.5 | EW18: =IF(EW17<=EY16,EW17/EY16,IF(EW17<=EY16+FA16,1+(EW17-EY16)/FA16,IF(EW17<=EY16+FA16+FC16,2+(EW17-EY16-FA16)/FC16,EW17*3/(EY16+FA16+FC16)))) -> #REF! | EX18: 2.5 | EY18: =IF(EY17<=FA16,EY17/FA16,IF(EY17<=FA16+FC16,1+(EY17-FA16)/FC16,IF(EY17<=FA16+FC16+FE16,2+(EY17-FA16-FC16)/FE16,EY17*3/(FA16+FC16+FE16)))) -> #REF! | EZ18: 2.5 | FA18: =IF(FA17<=FC16,FA17/FC16,IF(FA17<=FC16+FE16,1+(FA17-FC16)/FE16,IF(FA17<=FC16+FE16+FG16,2+(FA17-FC16-FE16)/FG16,FA17*3/(FC16+FE16+FG16)))) -> #REF! | FB18: 2.5 | FC18: =IF(FC17<=FE16,FC17/FE16,IF(FC17<=FE16+FG16,1+(FC17-FE16)/FG16,IF(FC17<=FE16+FG16+FI16,2+(FC17-FE16-FG16)/FI16,FC17*3/(FE16+FG16+FI16)))) -> #REF! | FD18: 2 | FE18: =IF(FE17<=FG16,FE17/FG16,IF(FE17<=FG16+FI16,1+(FE17-FG16)/FI16,IF(FE17<=FG16+FI16+FK16,2+(FE17-FG16-FI16)/FK16,FE17*3/(FG16+FI16+FK16)))) -> 2.6270396 | FF18: 2 | FG18: =IF(FG17<=FI16,FG17/FI16,IF(FG17<=FI16+FK16,1+(FG17-FI16)/FK16,IF(FG17<=FI16+FK16+FM16,2+(FG17-FI16-FK16)/FM16,FG17*3/(FI16+FK16+FM16)))) -> 2.9049296 | FH18: 2 | FI18: =IF(FI17<=FK16,FI17/FK16,IF(FI17<=FK16+FM16,1+(FI17-FK16)/FM16,IF(FI17<=FK16+FM16+FO16,2+(FI17-FK16-FM16)/FO16,FI17*3/(FK16+FM16+FO16)))) -> 2.7498995 | FJ18: 2 | FK18: =IF(FK17<=FM16,FK17/FM16,IF(FK17<=FM16+FO16,1+(FK17-FM16)/FO16,IF(FK17<=FM16+FO16+FQ16,2+(FK17-FM16-FO16)/FQ16,FK17*3/(FM16+FO16+FQ16)))) -> 2.3516883 | FL18: 2 | FM18: =IF(FM17<=FO16,FM17/FO16,IF(FM17<=FO16+FQ16,1+(FM17-FO16)/FQ16,IF(FM17<=FO16+FQ16+FS16,2+(FM17-FO16-FQ16)/FS16,FM17*3/(FO16+FQ16+FS16)))) -> 2.2143131 | FN18: 2 | FO18: =IF(FO17<=FQ16,FO17/FQ16,IF(FO17<=FQ16+FS16,1+(FO17-FQ16)/FS16,IF(FO17<=FQ16+FS16+FU16,2+(FO17-FQ16-FS16)/FU16,FO17*3/(FQ16+FS16+FU16)))) -> 1.9211634 | FP18: 2 | FQ18: =IF(FQ17<=FS16,FQ17/FS16,IF(FQ17<=FS16+FU16,1+(FQ17-FS16)/FU16,IF(FQ17<=FS16+FU16+FW16,2+(FQ17-FS16-FU16)/FW16,FQ17*3/(FS16+FU16+FW16)))) -> 1.9619841 | FR18: 2 | FS18: =IF(FS17<=FU16,FS17/FU16,IF(FS17<=FU16+FW16,1+(FS17-FU16)/FW16,IF(FS17<=FU16+FW16+FY16,2+(FS17-FU16-FW16)/FY16,FS17*3/(FU16+FW16+FY16)))) -> 1.9138091 | FT18: =IF(FT17<=FV16,FT17/FV16,IF(FT17<=FV16+FX16,1+(FT17-FV16)/FX16,IF(FT17<=FV16+FX16+FZ16,2+(FT17-FV16-FX16)/FZ16,FT17*3/(FV16+FX16+FZ16)))) -> 2.5972503 | FU18: =IF(FU17<=FW16,FU17/FW16,IF(FU17<=FW16+FY16,1+(FU17-FW16)/FY16,IF(FU17<=FW16+FY16+GA16,2+(FU17-FW16-FY16)/GA16,FU17*3/(FW16+FY16+GA16)))) -> 2.256917 | FV18: =IF(FV17<=FX16,FV17/FX16,IF(FV17<=FX16+FZ16,1+(FV17-FX16)/FZ16,IF(FV17<=FX16+FZ16+#REF!,2+(FV17-FX16-FZ16)/#REF!,FV17*3/(FX16+FZ16+#REF!)))) -> #REF! | FW18: =IF(FW17<=FY16,FW17/FY16,IF(FW17<=FY16+GA16,1+(FW17-FY16)/GA16,IF(FW17<=FY16+GA16+GB16,2+(FW17-FY16-GA16)/GB16,FW17*3/(FY16+GA16+GB16)))) -> 1.7971014 | FX18: =IF(FX17<=FZ16,FX17/FZ16,IF(FX17<=FZ16+#REF!,1+(FX17-FZ16)/#REF!,IF(FX17<=FZ16+#REF!+#REF!,2+(FX17-FZ16-#REF!)/#REF!,FX17*3/(FZ16+#REF!+#REF!)))) -> #REF! | FY18: =IF(FY17<=GA16,FY17/GA16,IF(FY17<=GA16+GB16,1+(FY17-GA16)/GB16,IF(FY17<=GA16+GB16+GC16,2+(FY17-GA16-GB16)/GC16,FY17*3/(GA16+GB16+GC16)))) -> 1.9432761 | FZ18: =IF(FZ17<=#REF!,FZ17/#REF!,IF(FZ17<=#REF!+#REF!,1+(FZ17-#REF!)/#REF!,IF(FZ17<=#REF!+#REF!+#REF!,2+(FZ17-#REF!-#REF!)/#REF!,FZ17*3/(#REF!+#REF!+#REF!)))) -> #REF! | GA18: =IF(GA17<=GB16,GA17/GB16,IF(GA17<=GB16+GC16,1+(GA17-GB16)/GC16,IF(GA17<=GB16+GC16+GD16,2+(GA17-GB16-GC16)/GD16,GA17*3/(GB16+GC16+GD16)))) -> 2.5818713 | GB18: =IF(GB17<=GC16,GB17/GC16,IF(GB17<=GC16+GD16,1+(GB17-GC16)/GD16,IF(GB17<=GC16+GD16+GE16,2+(GB17-GC16-GD16)/GE16,GB17*3/(GC16+GD16+GE16)))) -> 2.2934062 | GC18: =IF(GC17<=GD16,GC17/GD16,IF(GC17<=GD16+GE16,1+(GC17-GD16)/GE16,IF(GC17<=GD16+GE16+GF16,2+(GC17-GD16-GE16)/GF16,GC17*3/(GD16+GE16+GF16)))) -> 2.6409647 | GD18: =IF(GD17<=GE16,GD17/GE16,IF(GD17<=GE16+GF16,1+(GD17-GE16)/GF16,IF(GD17<=GE16+GF16+GG16,2+(GD17-GE16-GF16)/GG16,GD17*3/(GE16+GF16+GG16)))) -> 2.3299923 | GE18: =IF(GE17<=GF16,GE17/GF16,IF(GE17<=GF16+GG16,1+(GE17-GF16)/GG16,IF(GE17<=GF16+GG16+GH16,2+(GE17-GF16-GG16)/GH16,GE17*3/(GF16+GG16+GH16)))) -> 2.0030503 | GF18: =IF(GF17<=GG16,GF17/GG16,IF(GF17<=GG16+GH16,1+(GF17-GG16)/GH16,IF(GF17<=GG16+GH16+GI16,2+(GF17-GG16-GH16)/GI16,GF17*3/(GG16+GH16+GI16)))) -> 2.0842346 | GG18: =IF(GG17<=GH16,GG17/GH16,IF(GG17<=GH16+GI16,1+(GG17-GH16)/GI16,IF(GG17<=GH16+GI16+GJ16,2+(GG17-GH16-GI16)/GJ16,GG17*3/(GH16+GI16+GJ16)))) -> 1.6551581 | GH18: =IF(GH17<=GI16,GH17/GI16,IF(GH17<=GI16+GJ16,1+(GH17-GI16)/GJ16,IF(GH17<=GI16+GJ16+GK16,2+(GH17-GI16-GJ16)/GK16,GH17*3/(GI16+GJ16+GK16)))) -> 2.34 | ... JO18: =IF(JO17<=JP16,JO17/JP16,IF(JO17<=JP16+JQ16,1+(JO17-JP16)/JQ16,IF(JO17<=JP16+JQ16+JR16,2+(JO17-JP16-JQ16)/JR16,JO17*3/(JP16+JQ16+JR16)))) -> #DIV/0!
B19: UHP | C19: 2.5 | D19: In | F19: 2.1 | G19: 0.554 | H19: 1.706 | I19: 0.44 | J19: =H20 -> 1.2 | K19: 1.013 | L19: 3.5 | M19: 2.304 | N19: 3.5 | O19: 5.189 | P19: 3.8 | Q19: 2.81 | R19: 2.6 | S19: 7.5 | T19: 3 | U19: 2.928 | V19: 4 | W19: 2.894 | X19: 4.8 | Y19: 1.793 | Z19: 4 | AA19: 2.299 | AB19: 1.7 | AC19: 1.512 | AD19: 1.2 | AE19: 0.645 | AF19: 1.791 | AG19: 0.644 | AH19: 1.66 | AI19: 1.516 | AJ19: 2.602 | AK19: 2.489 | AL19: 3.387 | AM19: 4.413 | AN19: 4.015 | AO19: 3.153 | AP19: 4.538 | AQ19: 3.491 | AR19: 2.168 | AS19: 3.953 | AT19: 3.159 | AU19: 4.029 | AV19: 4.684 | AW19: 9.474 | AX19: 4.6 | AY19: 5.142 | AZ19: 4.842 | BA19: 5.416 | BB19: 4.697 | BC19: 0.613 | BD19: 2.71 | BE19: 0.172 | BF19: 2.78 | BG19: 2.204 | BH19: 3.746 | BI19: 3.15 | BJ19: 4.414 | BK19: 5.181 | BL19: 4.846 | BM19: 4.24 | BN19: 5.24 | BO19: 5.548 | BP19: 4.073 | BQ19: 8.189 | BR19: 4.515 | BS19: 3.726 | BT19: 4.943 | BU19: 4.264 | BV19: 5.913 | BW19: 7.695 | BX19: 6.966 | BY19: 4.543 | BZ19: 6.229 | CA19: 2.55 | CB19: 3.635 | CC19: 3.657 | CD19: =+CD20 -> 3.19 | CE19: 3.064 | CF19: 4.84 | CG19: 3.829 | CH19: 4.411 | CI19: 4.451 | CJ19: 5.272 | CK19: 2.472 | CL19: 5.908 | CM19: 3.496 | CN19: =+CN20 -> 4.9407154 | CO19: 5.589 | CP19: 5.7931729 | CQ19: 3.268 | CR19: 6.3655767 | CS19: 5.552 | CT19: 7.304 | CU19: 9.104 | CV19: 8.791547 | CW19: 3.932 | CX19: 7.6383022 | CY19: 5.883 | CZ19: 3.983 | DA19: 2.692 | DB19: 3.95 | DC19: 2.314 | DD19: 5.5292 | DE19: 2.658 | DF19: 5.4875436 | DG19: =[12]PCR!$J$419 -> 3.567 | DH19: 5.7584094 | DI19: =[13]PCR!$J$431 -> 4.948 | DJ19: 7.555 | DK19: 8.047 | DL19: =5.687 -> 5.687 | DM19: 5.948 | DN19: 6.666 | DO19: 4.139 | DP19: 7.488 | DQ19: 15.611 | DR19: 8.161 | DS19: 14.821 | DT19: 9.574 | DU19: =[14]PCR!$J$517 -> 2.005 | DV19: 9.162 | DW19: =[15]PCR!$J$514 -> 7.297 | DX19: 4.225 | DY19: =[16]PCR!$J$460 -> 3.741 | DZ19: 4.354 | EA19: =[17]PCR!$J$456 -> 2.687 | EB19: 6.338 | EC19: =[18]PCR!$J$452 -> 2.505 | ED19: 6.582 | EE19: =[19]PCR!$J$449 -> 2.075 | EF19: 7.514 | EG19: =[20]PCR!$J$452 -> 5.92 | EH19: 8.947 | EI19: =[21]PCR!$J$479 -> 6.41 | EJ19: 5.662 | EK19: =[22]PCR!$J$493 -> 6.619 | EL19: 6.555 | EM19: =[23]PCR!$J$521 -> 5.966 | EN19: 8.606 | EO19: =[24]PCR!$J$562 -> 12.603 | EP19: 11.55 | EQ19: =[25]PCR!$J$570 -> 6.737 | ER19: 12.741 | ES19: =[26]PCR!$J$491 -> 5.234 | ET19: 11.175 | EU19: =[27]PCR!$J$474 -> 2.924 | EV19: 2.959 | EW19: =[28]PCR!$J$432 -> 0.929 | EX19: 3.531 | EY19: =[29]PCR!$J$459 -> #REF! | EZ19: 4.77 | FA19: =[30]PCR!$J$474 -> 10.95 | FB19: 6.653 | FC19: 8.18 | FD19: 7.323 | FE19: =[31]PCR!$J$437 -> 5.58 | FF19: 8.381 | FG19: =[32]PCR!$J$451 -> 9.868 | FH19: 7.8040944 | FI19: =[33]PCR!$J$469 -> 10.432 | FJ19: 7.8372676 | FK19: =[34]PCR!$J$466 -> 8.597 | FL19: 9.6264213 | FM19: =[35]PCR!$J$485 -> 13.176 | FN19: 12.172904 | FO19: =[36]PCR!$J$478 -> 16.26 | FP19: 12.545 | FQ19: =[37]PCR!$J$473 -> 10.646 | FR19: 11.919 | FS19: =[38]PCR!$J$452 -> 4.749 | FT19: 3.836 | FU19: =[39]PCR!$J$436 -> 3.099 | FV19: 4.534 | FW19: =[40]PCR!$J$429 -> 8.328 | FX19: 9.957 | FY19: =[41]PCR!$J$415 -> 6.637 | FZ19: 8.784 | GA19: =[42]PCR!$J$407 -> 7.98 | GB19: 7.179 | GC19: 10.623 | GD19: 9.991 | GE19: 11.892 | GF19: 15.49 | GG19: 12.266 | GH19: 9.265 | GI19: 9.46 | GJ19: 6.393 | GK19: 4.503 | GL19: 13.335 | GM19: 12.954 | GN19: 14.638 | GO19: 17.829 | GP19: 13.558 | GQ19: 13.741 | GR19: 11.763 | GS19: 16.208 | GT19: 6.244 | GU19: 8.515 | GV19: 4.865 | GW19: 10.691 | GX19: 9.671 | GY19: 30.269 | GZ19: 10.477 | HA19: 7.071 | HB19: 35.523 | HC19: 21.662 | HD19: 25.184 | HE19: 17.611 | HF19: 17.112 | HG19: 7.212 | HH19: =[43]PCR!$I$772 -> 7.668 | HI19: =[44]PCR!$I$772 -> 9.417 | HJ19: 17.311 | HK19: =[45]PCR!$I$775 -> 15.326 | HL19: 13.691 | HM19: 11.908 | HN19: 16.11 | HO19: 23.796 | HP19: 15.274 | HQ19: 24.145 | HR19: 24.969 | HS19: 20.151 | HT19: 4.115 | HU19: 9.698 | HV19: 11.951 | HW19: 22.249 | HX19: 20.459 | HY19: =[46]Cate!I818 -> 15.691 | HZ19: 25.302 | IA19: =[47]Cate!I818 -> 22.42 | IB19: =[48]Cate!I818 -> 22.801 | IC19: 16.017 | ID19: =[49]PCR!$I$818 -> 27.287 | IE19: 29.687 | IF19: 11.842 | IG19: 1.786 | IH19: 7.423 | II19: 15.323 | IJ19: 14.28 | IK19: 25.975 | IL19: 24.91 | IM19: 39.612 | IN19: 20.492 | IO19: 12.862 | IP19: 16.915 | IQ19: 8.577 | IR19: 11.265 | IS19: 2.468 | IT19: 6.49 | IU19: 8.233 | IV19: 9.291 | IW19: 18.158 | IX19: 20.161 | IY19: 10.454 | IZ19: 14.947 | JA19: 14.756 | JB19: 8.155 | JC19: 3.369 | JD19: 8.665 | JE19: 4.056 | JF19: 7.472 | JG19: 20.387 | JH19: 12.017
D20: Out | F20: 2.1737501 | G20: 2.638 | H20: 1.2 | I20: 1.671 | J20: 1 | K20: 1.668 | L20: 2.5 | M20: 2.566 | N20: 4 | O20: 2.794 | P20: 3.5 | Q20: 2.355 | R20: 3.531 | S20: 3.06 | T20: 3.53 | U20: 1.887 | V20: 2.454 | W20: 2.52 | X20: 3.04 | Y20: 2.682 | Z20: 4.53 | AA20: 3.628 | AB20: 4.83 | AC20: 3.348 | AD20: 3.54 | AE20: 3.722 | AF20: 1.791 | AG20: 1.447 | AH20: 1.66 | AI20: 1.912 | AJ20: 2.602 | AK20: 2.732 | AL20: 3.387 | AM20: 2.582 | AN20: 4.015 | AO20: 2.686 | AP20: 4.538 | AQ20: 3.532 | AR20: 2.168 | AS20: 2.737 | AT20: 3.159 | AU20: 3.639 | AV20: 4.684 | AW20: 3.603 | AX20: 4.6 | AY20: 5.213 | AZ20: 4.842 | BA20: 5.939 | BB20: 4.697 | BC20: 4.305 | BD20: 2.71 | BE20: 2.479 | BF20: 2.78 | BG20: 3.148 | BH20: 3.746 | BI20: 3.591 | BJ20: 4.414 | BK20: 3.565 | BL20: 4.846 | BM20: 3.547 | BN20: 5.24 | BO20: 5.436 | BP20: 4.073 | BQ20: 4.55 | BR20: 4.515 | BS20: 4.335 | BT20: 4.943 | BU20: 3.962 | BV20: =+BV19 -> 5.913 | BW20: 5.512 | BX20: =+BX19 -> 6.966 | BY20: 7.009 | BZ20: =+BZ19 -> 6.229 | CA20: 6.103 | CB20: =+CB19 -> 3.635 | CC20: 3.534 | CD20: 3.19 | CE20: 3.014 | CF20: 4.84 | CG20: 4.114 | CH20: 4.411 | CI20: 3.772 | CJ20: 5.272 | CK20: 4.899 | CL20: 5.908 | CM20: 4.578 | CN20: 4.9407154 | CO20: 3.852 | CP20: 5.7931729 | CQ20: 3.764 | CR20: 6.3655767 | CS20: 4.191 | CT20: =+CT19 -> 7.304 | CU20: 5.939 | CV20: =+CV19 -> 8.791547 | CW20: 6.366 | CX20: 7.6383022 | CY20: 6.994 | CZ20: 3.983 | DA20: 2.413 | DB20: 3.95 | DC20: 3.242 | DD20: 5.5292 | DE20: 3.383 | DF20: 5.4875436 | DG20: =[12]PCR!$J$420 -> 4.885 | DH20: 5.7584094 | DI20: =[13]PCR!$J$432 -> 4.57 | DJ20: 7.555 | DK20: 6.652 | DL20: =DL19 -> 5.687 | DM20: 4.58 | DN20: =DN19 -> 6.666 | DO20: 4.327 | DP20: =DP19 -> 7.488 | DQ20: 7.484 | DR20: =DR19 -> 8.161 | DS20: 8.375 | DT20: =DT19 -> 9.574 | DU20: =[14]PCR!$J$518 -> 4.923 | DV20: =DV19 -> 9.162 | DW20: =[15]PCR!$J$515 -> 7.028 | DX20: =DX19 -> 4.225 | DY20: =[16]PCR!$J$461 -> 2.422 | DZ20: =DZ19 -> 4.354 | EA20: =[17]PCR!$J$457 -> 6.937 | EB20: =EB19 -> 6.338 | EC20: =[18]PCR!$J$453 -> 4.262 | ED20: =ED19 -> 6.582 | EE20: =[19]PCR!$J$450 -> 4.151 | EF20: =EF19 -> 7.514 | EG20: =[20]PCR!$J$453 -> 4.765 | EH20: =EH19 -> 8.947 | EI20: =[21]PCR!$J$480 -> 6.214 | EJ20: =EJ19 -> 5.662 | EK20: =[22]PCR!$J$494 -> 4.759 | EL20: =EL19 -> 6.555 | EM20: =[23]PCR!$J$522 -> 4.195 | EN20: =EN19 -> 8.606 | EO20: =[24]PCR!$J$563 -> 4.446 | EP20: =EP19 -> 11.55 | EQ20: =[25]PCR!$J$571 -> 11.689 | ER20: =ER19 -> 12.741 | ES20: =[26]PCR!$J$492 -> 10.325 | ET20: =ET19 -> 11.175 | EU20: =[27]PCR!$J$475 -> 8.462 | EV20: =EV19 -> 2.959 | EW20: =[28]PCR!$J$433 -> 2.349 | EX20: =EX19 -> 3.531 | EY20: =[29]PCR!$J$460 -> #REF! | EZ20: =EZ19 -> 4.77 | FA20: =[30]PCR!$J$475 -> 7.151 | FB20: =FB19 -> 6.653 | FC20: 8.807 | FD20: =FD19 -> 7.323 | FE20: =[31]PCR!$J$438 -> 6.858 | FF20: =FF19 -> 8.381 | FG20: =[32]PCR!$J$452 -> 8.507 | FH20: 7.8040944 | FI20: =[33]PCR!$J$470 -> 8.493 | FJ20: 7.8372676 | FK20: =[34]PCR!$J$467 -> 7.127 | FL20: 9.6264213 | FM20: =[35]PCR!$J$486 -> 7.914 | FN20: 12.172904 | FO20: =[36]PCR!$J$479 -> 13.552 | FP20: 12.545 | FQ20: =[37]PCR!$J$474 -> 12.838 | FR20: 11.919 | FS20: =[38]PCR!$J$453 -> 10.729 | FT20: 2.995 | FU20: =[39]PCR!$J$437 -> 4.36 | FV20: 3.319 | FW20: =[40]PCR!$J$430 -> 5.987 | FX20: 6.86 | FY20: =[41]PCR!$J$416 -> 11.3 | FZ20: 7.903 | GA20: =[42]PCR!$J$408 -> 6.329 | GB20: 5.841 | GC20: 10.629 | GD20: 7.15 | GE20: 7.419 | GF20: 11.429 | GG20: 14.33 | GH20: 13.157 | GI20: 14.708 | GJ20: 5.972 | GK20: 7.458 | GL20: 9.623 | GM20: 11.495 | GN20: 10.765 | GO20: 11.917 | GP20: 10.588 | GQ20: 10.6 | GR20: 14.053 | GS20: 18.529 | GT20: 13.122 | GU20: 14.328 | GV20: 5.685 | GW20: 5.526 | GX20: 10.113 | GY20: 19.204 | GZ20: 12.826 | HA20: 16.455 | HB20: 14.275 | HC20: 14.891 | HD20: 21.202 | HE20: 20.175 | HF20: 18.843 | HG20: 22.488 | HH20: =[43]PCR!$I$773 -> 5.457 | HI20: =[44]PCR!$I$773 -> 4.044 | HJ20: 5.172 | HK20: =[45]PCR!$J$775 -> 12.767 | HL20: 14.984 | HM20: 19.607 | HN20: 19.46 | HO20: 23.151 | HP20: 24.719 | HQ20: 29.447 | HR20: 24.192 | HS20: 17.488 | HT20: 8.445 | HU20: 8.271 | HV20: 13.799 | HW20: 21.196 | HX20: 19.315 | HY20: =[46]Cate!J818 -> 22.206 | HZ20: 14.204 | IA20: =[47]Cate!J818 -> 16.172 | IB20: =[48]Cate!J818 -> 18.692 | IC20: 19.221 | ID20: =[49]PCR!$J$818 -> 21.141 | IE20: 29.228 | IF20: 9.178 | IG20: 10.228 | IH20: 17.566 | II20: 13.77 | IJ20: 14.167 | IK20: 23.262 | IL20: 16.174 | IM20: 16.934 | IN20: 10.7 | IO20: 9.979 | IP20: 15.537 | IQ20: 24.228 | IR20: 4.811 | IS20: 6.866 | IT20: 14.77 | IU20: 11.579 | IV20: 12.611 | IW20: 11.541 | IX20: 11.758 | IY20: 13.879 | IZ20: 11.712 | JA20: 16.866 | JB20: 20.298 | JC20: 28.702 | JD20: 7.697 | JE20: 7.008 | JF20: 11.401 | JG20: 11.704 | JH20: 12.536
D21: Inventory | F21: 3.0048499 | G21: 6.955 | H21: =F21+H19-H20 -> 3.5108499 | I21: =G21+I19-I20 -> 5.724 | J21: =H21+J19-J20 -> 3.7108499 | K21: =I21+K19-K20 -> 5.069 | L21: =J21+L19-L20 -> 4.7108499 | M21: =K21+M19-M20 -> 4.807 | N21: =L21+N19-N20 -> 4.2108499 | O21: =M21+O19-O20 -> 7.202 | ... AK21: =AI21+AK19-AK20 -> 4.939 | AL21: =N21*1.137 -> 4.7877364 | AM21: =AK21+AM19-AM20 -> 6.77 | AN21: =P21*1.137 -> 5.1288364 | AO21: =AM21+AO19-AO20 -> 7.237 | AP21: =R21*1.137 -> 4.0702894 | AQ21: 7.505 | AR21: =T21*1.137 -> 3.4676794 | AS21: =AQ21+AS19-AS20 -> 8.721 | AT21: =V21*1.137 -> 5.2254814 | AU21: =AS21+AU19-AU20 -> 9.111 | AV21: =X21*1.137 -> 7.2266014 | AW21: =AU21+AW19-AW20 -> 14.982 | AX21: =Z21*1.137 -> 6.6239914 | AY21: =AW21+AY19-AY20 -> 14.911 | AZ21: 3.0651814 | BA21: 14.388 | BB21: 0.40460136 | BC21: 10.696 | BD21: 0.40460136 | BE21: 8.389 | BF21: =BD21+BF19-BF20 -> 0.40460136 | BG21: 7.245 | BH21: =AJ21*1.137 -> 0.40460136 | BI21: =BG21+BI19-BI20 -> 6.804 | BJ21: =AL21*1.137 -> 5.4436562 | BK21: =BI21+BK19-BK20 -> 8.42 | BL21: =AN21*1.137 -> 5.8314869 | BM21: =BK21+BM19-BM20 -> 9.113 | BN21: =AP21*1.137 -> 4.627919 | BO21: =BM21+BO19-BO20 -> 9.225 | BP21: =AR21*1.137 -> 3.9427514 | BQ21: =BO21+BQ19-BQ20 -> 12.864 | BR21: =AT21*1.137 -> 5.9413723 | BS21: =BQ21+BS19-BS20 -> 12.255 | BT21: =AV21*1.137 -> 8.2166457 | BU21: =BS21+BU19-BU20 -> 12.557 | BV21: =AX21*1.137 -> 7.5314782 | BW21: =BU21+BW19-BW20 -> 14.74 | BX21: =AZ21*1.137 -> 3.4851112 | BY21: =BW21+BY19-BY20 -> 12.274 | BZ21: =BB21*1.137 -> 0.46003175 | CA21: =BY21+CA19-CA20 -> 8.721 | CB21: =BD21*1.137 -> 0.46003175 | CC21: =CA21+CC19-CC20 -> 8.844 | CD21: =BF21*1.137 -> 0.46003175 | CE21: =CC21+CE19-CE20 -> 8.894 | CF21: =BH21*1.137 -> 0.46003175 | CG21: =CE21+CG19-CG20 -> 8.609 | CH21: =BJ21*1.137 -> 6.1894371 | CI21: =CG21+CI19-CI20 -> 9.288 | CJ21: =BL21*1.137 -> 6.6304007 | CK21: =CI21+CK19-CK20 -> 6.861 | CL21: =BN21*1.137 -> 5.2619439 | CM21: =CK21+CM19-CM20 -> 5.779 | CN21: =BP21*1.137 -> 4.4829084 | CO21: =CM21+CO19-CO20 -> 7.516 | CP21: =BR21*1.137 -> 6.7553403 | CQ21: =CO21+CQ19-CQ20 -> 7.02 | CR21: =BT21*1.137 -> 9.3423262 | CS21: =CQ21+CS19-CS20 -> 8.381 | CT21: =BV21*1.137 -> 8.5632907 | CU21: =CS21+CU19-CU20 -> 11.546 | CV21: =BX21*1.137 -> 3.9625714 | CW21: =CU21+CW19-CW20 -> 9.112 | CX21: =BZ21*1.137 -> 0.5230561 | CY21: 7.523 | CZ21: =CB21*1.137 -> 0.5230561 | DA21: =CY21+DA19-DA20 -> 7.802 | DB21: =CD21*1.137 -> 0.5230561 | DC21: =DA21+DC19-DC20 -> 6.874 | DD21: =CF21*1.137 -> 0.5230561 | DE21: =DC21+DE19-DE20 -> 6.149 | DF21: =CF21*1.137 -> 0.5230561 | DG21: =DE21+DG19-DG20 -> 4.831 | DH21: =CH21*1.137 -> 7.03739 | DI21: =DG21+DI19-DI20 -> 5.209 | DJ21: =CH21*1.137 -> 7.03739 | DK21: =DI21+DK19-DK20 -> 6.604 | DL21: =CJ21*1.137 -> 7.5387655 | DM21: =DK21+DM19-DM20 -> 7.972 | DN21: =CL21*1.137 -> 5.9828302 | DO21: =DM21+DO19-DO20 -> 7.784 | DP21: =CN21*1.137 -> 5.0970668 | DQ21: =DO21+DQ19-DQ20 -> 15.911 | DR21: =CP21*1.137 -> 7.6808219 | DS21: =DQ21+DS19-DS20 -> 22.357 | DT21: =CR21*1.137 -> 10.622225 | DU21: =DS21+DU19-DU20 -> 19.439 | DV21: =CT21*1.137 -> 9.7364615 | DW21: =DU21+DW19-DW20 -> 19.708 | DX21: =CV21*1.137 -> 4.5054437 | DY21: =DW21+DY19-DY20 -> 21.027 | DZ21: =CX21*1.137 -> 0.59471478 | EA21: =DY21+EA19-EA20 -> 16.777 | EB21: =CZ21*1.137 -> 0.59471478 | EC21: =EA21+EC19-EC20 -> 15.02 | ED21: =DB21*1.137 -> 0.59471478 | EE21: =EC21+EE19-EE20 -> 12.944 | EF21: =DD21*1.137 -> 0.59471478 | EG21: =EE21+EG19-EG20 -> 14.099 | EH21: =DF21*1.137 -> 0.59471478 | EI21: =EG21+EI19-EI20 -> 14.295 | EJ21: =DH21*1.137 -> 8.0015125 | EK21: =EI21+EK19-EK20 -> 16.155 | EL21: =DJ21*1.137 -> 8.0015125 | EM21: =EK21+EM19-EM20 -> 17.926 | EN21: =DL21*1.137 -> 8.5715764 | EO21: 26.18 | EP21: =DN21*1.137 -> 6.802478 | EQ21: =EO21+EQ19-EQ20 -> 21.228 | ER21: =DP21*1.137 -> 5.795365 | ES21: =EQ21+ES19-ES20 -> 16.137 | ET21: =DR21*1.137 -> 8.7330945 | EU21: =ES21+EU19-EU20 -> 10.599 | EV21: =DT21*1.137 -> 12.07747 | EW21: =EU21+EW19-EW20 -> 9.179 | EX21: =DV21*1.137 -> 11.070357 | EY21: =EW21+EY19-EY20 -> #REF! | EZ21: =DX21*1.137 -> 5.1226895 | FA21: =EY21+FA19-FA20 -> #REF! | FB21: =DZ21*1.137 -> 0.67619071 | FC21: =FA21+FC19-FC20 -> #REF! | FD21: =EB21*1.137 -> 0.67619071 | FE21: 12.837 | FF21: =ED21*1.137 -> 0.67619071 | FG21: =FE21+FG19-FG20 -> 14.198 | FH21: =EF21*1.137 -> 0.67619071 | FI21: =FG21+FI19-FI20 -> 16.137 | FJ21: =EH21*1.137 -> 0.67619071 | FK21: =FI21+FK19-FK20 -> 17.607 | FL21: =EJ21*1.137 -> 9.0977197 | FM21: =FK21+FM19-FM20 -> 22.869 | FN21: =EL21*1.137 -> 9.0977197 | FO21: =FM21+FO19-FO20 -> 25.577 | FP21: =EN21*1.137 -> 9.7458824 | FQ21: =FO21+FQ19-FQ20 -> 23.385 | FR21: 13.027 | FS21: =FQ21+FS19-FS20 -> 17.405 | FT21: =FR21+FT19-FT20 -> 13.868 | FU21: =FS21+FU19-FU20 -> 16.144 | FV21: =FT21+FV19-FV20 -> 15.083 | FW21: =FU21+FW19-FW20 -> 18.485 | FX21: =FV21+FX19-FX20 -> 18.18 | FY21: =FW21+FY19-FY20 -> 13.822 | FZ21: 14.276 | GA21: 15.256 | GB21: =GA21+GB19-GB20 -> 16.594 | GC21: =GB21+GC19-GC20 -> 16.588 | GD21: 19.414 | GE21: 23.874 | GF21: =GE21+GF19-GF20 -> 27.935 | GG21: =GF21+GG19-GG20 -> 25.871 | GH21: 21.934 | GI21: =GH21+GI19-GI20 -> 16.686 | GJ21: =GI21+GJ19-GJ20 -> 17.107 | GK21: 14.118 | GL21: =GK21+GL19-GL20 -> 17.83 | GM21: =GL21+GM19-GM20 -> 19.289 | GN21: =GM21+GN19-GN20 -> 23.162 | GO21: =GN21+GO19-GO20 -> 29.074 | GP21: =GO21+GP19-GP20 -> 32.044 | GQ21: =GP21+GQ19-GQ20 -> 35.185 | GR21: =GQ21+GR19-GR20 -> 32.895 | GS21: 30.454 | GT21: =GS21+GT19-GT20 -> 23.576 | GU21: =GT21+GU19-GU20 -> 17.763 | GV21: =GU21+GV19-GV20 -> 16.943 | GW21: =GV21+GW19-GW20 -> 22.108 | GX21: =GW21+GX19-GX20 -> 21.666 | GY21: =GX21+GY19-GY20 -> 32.731 | GZ21: =GY21+GZ19-GZ20 -> 30.382 | HA21: =GZ21+HA19-HA20 -> 20.998 | HB21: 42.242 | HC21: 44.157 | HD21: =HC21+HD19-HD20 -> 48.139 | HE21: =HD21+HE19-HE20 -> 45.575 | HF21: =HE21+HF19-HF20 -> 43.844 | HG21: =HF21+HG19-HG20 -> 28.568 | HH21: =HG21+HH19-HH20 -> 30.779 | HI21: =HH21+HI19-HI20 -> 36.152 | HJ21: =HI21+HJ19-HJ20 -> 48.291 | HK21: =HJ21+HK19-HK20 -> 50.85 | ... HU21: =HT21+HU19-HU20 -> 24.943 | HV21: 23.095 | HW21: =HV21+HW19-HW20 -> 24.148 | HX21: =HW21+HX19-HX20 -> 25.292 | HY21: =HX21+HY19-HY20 -> 18.777 | HZ21: =HY21+HZ19-HZ20 -> 29.875 | IA21: =HZ21+IA19-IA20 -> 36.123 | IB21: =IA21+IB19-IB20 -> 40.232 | IC21: =IB21+IC19-IC20 -> 37.028 | ID21: =IC21+ID19-ID20 -> 43.174 | ... IL21: =IK21+IL19-IL20 -> 40.827 | IM21: 63.509 | IN21: =IM21+IN19-IN20 -> 73.301 | IO21: =IN21+IO19-IO20 -> 76.184 | IP21: =IO21+IP19-IP20 -> 77.562 | IQ21: =IP21+IQ19-IQ20 -> 61.911 | IR21: =IQ21+IR19-IR20 -> 68.365 | IS21: 63.907 | IT21: =IS21+IT19-IT20 -> 55.627 | IU21: =IT21+IU19-IU20 -> 52.281 | IV21: =IU21+IV19-IV20 -> 48.961 | IW21: =IV21+IW19-IW20 -> 55.578 | IX21: =IW21+IX19-IX20 -> 63.981 | IY21: =IX21+IY19-IY20 -> 60.556 | IZ21: =IY21+IZ19-IZ20 -> 63.791 | JA21: =IZ21+JA19-JA20 -> 61.681 | ... JO21: =JN21+JO19-JO20 -> 26.456
D22: month | E22: 1.9 | F22: 1.1439675 | G22: 4.4393617 | H22: =IF(H21<=J20,H21/J20,IF(H21<=J20+L20,1+(H21-J20)/L20,IF(H21<=J20+L20+N20,2+(H21-J20-L20)/N20,H21*3/(J20+L20+N20)))) -> 2.0027125 | I22: =IF(I21<=K20,I21/K20,IF(I21<=K20+M20,1+(I21-K20)/M20,IF(I21<=K20+M20+O20,2+(I21-K20-M20)/O20,I21*3/(K20+M20+O20)))) -> 2.5332856 | J22: =IF(J21<=L20,J21/L20,IF(J21<=L20+N20,1+(J21-L20)/N20,IF(J21<=L20+N20+P20,2+(J21-L20-N20)/P20,J21*3/(L20+N20+P20)))) -> 1.3027125 | K22: =IF(K21<=M20,K21/M20,IF(K21<=M20+O20,1+(K21-M20)/O20,IF(K21<=M20+O20+Q20,2+(K21-M20-O20)/Q20,K21*3/(M20+O20+Q20)))) -> 1.8958482 | L22: =IF(L21<=N20,L21/N20,IF(L21<=N20+P20,1+(L21-N20)/P20,IF(L21<=N20+P20+R20,2+(L21-N20-P20)/R20,L21*3/(N20+P20+R20)))) -> 1.2031 | M22: =IF(M21<=O20,M21/O20,IF(M21<=O20+Q20,1+(M21-O20)/Q20,IF(M21<=O20+Q20+S20,2+(M21-O20-Q20)/S20,M21*3/(O20+Q20+S20)))) -> 1.8547771 | N22: =IF(N21<=P20,N21/P20,IF(N21<=P20+R20,1+(N21-P20)/R20,IF(N21<=P20+R20+T20,2+(N21-P20-R20)/T20,N21*3/(P20+R20+T20)))) -> 1.2013169 | O22: =IF(O21<=Q20,O21/Q20,IF(O21<=Q20+S20,1+(O21-Q20)/S20,IF(O21<=Q20+S20+U20,2+(O21-Q20-S20)/U20,O21*3/(Q20+S20+U20)))) -> 2.9470058 | ... CI22: =IF(CI21<=CK20,CI21/CK20,IF(CI21<=CK20+CM20,1+(CI21-CK20)/CM20,IF(CI21<=CK20+CM20+CO20,2+(CI21-CK20-CM20)/CO20,CI21*3/(CK20+CM20+CO20)))) -> 1.9587156 | CJ22: =IF(CJ21<=CL20,CJ21/CL20,IF(CJ21<=CL20+CN20,1+(CJ21-CL20)/CN20,IF(CJ21<=CL20+CN20+#REF!,2+(CJ21-CL20-CN20)/#REF!,CJ21*3/(CL20+CN20+#REF!)))) -> 1.1462138 | CK22: =IF(CK21<=CM20,CK21/CM20,IF(CK21<=CM20+CO20,1+(CK21-CM20)/CO20,IF(CK21<=CM20+CO20+CQ20,2+(CK21-CM20-CO20)/CQ20,CK21*3/(CM20+CO20+CQ20)))) -> 1.5926791 | CL22: =IF(CL21<=CN20,CL21/CN20,IF(CL21<=CN20+#REF!,1+(CL21-CN20)/#REF!,IF(CL21<=CN20+#REF!+#REF!,2+(CL21-CN20-#REF!)/#REF!,CL21*3/(CN20+#REF!+#REF!)))) -> #REF! | CM22: =IF(CM21<=CO20,CM21/CO20,IF(CM21<=CO20+CQ20,1+(CM21-CO20)/CQ20,IF(CM21<=CO20+CQ20+CS20,2+(CM21-CO20-CQ20)/CS20,CM21*3/(CO20+CQ20+CS20)))) -> 1.5119554 | CN22: =BP22*1.137 -> 0.99289222 | CO22: =IF(CO21<=CQ20,CO21/CQ20,IF(CO21<=CQ20+CS20,1+(CO21-CQ20)/CS20,IF(CO21<=CQ20+CS20+CU20,2+(CO21-CQ20-CS20)/CU20,CO21*3/(CQ20+CS20+CU20)))) -> 1.8952517 | CP22: =BR22*1.137 -> 1.3289752 | CQ22: =IF(CQ21<=CS20,CQ21/CS20,IF(CQ21<=CS20+CU20,1+(CQ21-CS20)/CU20,IF(CQ21<=CS20+CU20+CW20,2+(CQ21-CS20-CU20)/CW20,CQ21*3/(CS20+CU20+CW20)))) -> 1.4763428 | CR22: =BT22*1.137 -> 1.5130042 | CS22: =IF(CS21<=CU20,CS21/CU20,IF(CS21<=CU20+CW20,1+(CS21-CU20)/CW20,IF(CS21<=CU20+CW20+CY20,2+(CS21-CU20-CW20)/CY20,CS21*3/(CU20+CW20+CY20)))) -> 1.3836004 | CT22: =BV22*1.137 -> 1.2402186 | CU22: =IF(CU21<=CW20,CU21/CW20,IF(CU21<=CW20+CY20,1+(CU21-CW20)/CY20,IF(CU21<=CW20+CY20+DA20,2+(CU21-CW20-CY20)/DA20,CU21*3/(CW20+CY20+DA20)))) -> 1.7406348 | CV22: =BX22*1.137 -> 0.63614889 | CW22: =IF(CW21<=CY20,CW21/CY20,IF(CW21<=CY20+DA20,1+(CW21-CY20)/DA20,IF(CW21<=CY20+DA20+DC20,2+(CW21-CY20-DA20)/DC20,CW21*3/(CY20+DA20+DC20)))) -> 1.8777455 | CX22: =BZ22*1.137 -> 0.14389439 | CY22: =IF(CY21<=DA20,CY21/DA20,IF(CY21<=DA20+DC20,1+(CY21-DA20)/DC20,IF(CY21<=DA20+DC20+DE20,2+(CY21-DA20-DC20)/DE20,CY21*3/(DA20+DC20+DE20)))) -> 2.5521726 | CZ22: =CB22*1.137 -> 0.16396743 | DA22: =IF(DA21<=DC20,DA21/DC20,IF(DA21<=DC20+DE20,1+(DA21-DC20)/DE20,IF(DA21<=DC20+DE20+DG20,2+(DA21-DC20-DE20)/DG20,DA21*3/(DC20+DE20+DG20)))) -> 2.2409417 | DB22: =CD22*1.137 -> 0.10806944 | DC22: =IF(DC21<=DE20,DC21/DE20,IF(DC21<=DE20+DG20,1+(DC21-DE20)/DG20,IF(DC21<=DE20+DG20+DI20,2+(DC21-DE20-DG20)/DI20,DC21*3/(DE20+DG20+DI20)))) -> 1.7146366 | DD22: =CF22*1.137 -> 0.11857994 | DE22: =IF(DE21<=DG20,DE21/DG20,IF(DE21<=DG20+DI20,1+(DE21-DG20)/DI20,IF(DE21<=DG20+DI20+DK20,2+(DE21-DG20-DI20)/DK20,DE21*3/(DG20+DI20+DK20)))) -> 1.2765864 | DF22: =CF22*1.137 -> 0.11857994 | DG22: =IF(DG21<=DI20,DG21/DI20,IF(DG21<=DI20+DK20,1+(DG21-DI20)/DK20,IF(DG21<=DI20+DK20+DM20,2+(DG21-DI20-DK20)/DM20,DG21*3/(DI20+DK20+DM20)))) -> 1.0392363 | DH22: =CH22*1.137 -> 1.3135616 | DI22: =IF(DI21<=DK20,DI21/DK20,IF(DI21<=DK20+DM20,1+(DI21-DK20)/DM20,IF(DI21<=DK20+DM20+DO20,2+(DI21-DK20-DM20)/DO20,DI21*3/(DK20+DM20+DO20)))) -> 0.78307276 | DJ22: 1.5 | DK22: =IF(DK21<=DM20,DK21/DM20,IF(DK21<=DM20+DO20,1+(DK21-DM20)/DO20,IF(DK21<=DM20+DO20+DQ20,2+(DK21-DM20-DO20)/DQ20,DK21*3/(DM20+DO20+DQ20)))) -> 1.4677606 | DL22: 1.5 | DM22: =IF(DM21<=DO20,DM21/DO20,IF(DM21<=DO20+DQ20,1+(DM21-DO20)/DQ20,IF(DM21<=DO20+DQ20+DS20,2+(DM21-DO20-DQ20)/DS20,DM21*3/(DO20+DQ20+DS20)))) -> 1.487039 | DN22: 1.5 | DO22: =IF(DO21<=DQ20,DO21/DQ20,IF(DO21<=DQ20+DS20,1+(DO21-DQ20)/DS20,IF(DO21<=DQ20+DS20+DU20,2+(DO21-DQ20-DS20)/DU20,DO21*3/(DQ20+DS20+DU20)))) -> 1.0358209 | DP22: 1.5 | DQ22: =IF(DQ21<=DS20,DQ21/DS20,IF(DQ21<=DS20+DU20,1+(DQ21-DS20)/DU20,IF(DQ21<=DS20+DU20+DW20,2+(DQ21-DS20-DU20)/DW20,DQ21*3/(DS20+DU20+DW20)))) -> 2.3717985 | DR22: 1.5 | DS22: =IF(DS21<=DU20,DS21/DU20,IF(DS21<=DU20+DW20,1+(DS21-DU20)/DW20,IF(DS21<=DU20+DW20+DY20,2+(DS21-DU20-DW20)/DY20,DS21*3/(DU20+DW20+DY20)))) -> 4.6664579 | DT22: 1.5 | DU22: =IF(DU21<=DW20,DU21/DW20,IF(DU21<=DW20+DY20,1+(DU21-DW20)/DY20,IF(DU21<=DW20+DY20+EA20,2+(DU21-DW20-DY20)/EA20,DU21*3/(DW20+DY20+EA20)))) -> 3.5587356 | DV22: 1.5 | DW22: =IF(DW21<=DY20,DW21/DY20,IF(DW21<=DY20+EA20,1+(DW21-DY20)/EA20,IF(DW21<=DY20+EA20+EC20,2+(DW21-DY20-EA20)/EC20,DW21*3/(DY20+EA20+EC20)))) -> 4.3406505 | DX22: 1.5 | DY22: =IF(DY21<=EA20,DY21/EA20,IF(DY21<=EA20+EC20,1+(DY21-EA20)/EC20,IF(DY21<=EA20+EC20+EE20,2+(DY21-EA20-EC20)/EE20,DY21*3/(EA20+EC20+EE20)))) -> 4.1095114 | DZ22: 1.5 | EA22: =IF(EA21<=EC20,EA21/EC20,IF(EA21<=EC20+EE20,1+(EA21-EC20)/EE20,IF(EA21<=EC20+EE20+EG20,2+(EA21-EC20-EE20)/EG20,EA21*3/(EC20+EE20+EG20)))) -> 3.8193201 | EB22: 1.5 | EC22: =IF(EC21<=EE20,EC21/EE20,IF(EC21<=EE20+EG20,1+(EC21-EE20)/EG20,IF(EC21<=EE20+EG20+EI20,2+(EC21-EE20-EG20)/EI20,EC21*3/(EE20+EG20+EI20)))) -> 2.982298 | ED22: 1.5 | EE22: =IF(EE21<=EG20,EE21/EG20,IF(EE21<=EG20+EI20,1+(EE21-EG20)/EI20,IF(EE21<=EG20+EI20+EK20,2+(EE21-EG20-EI20)/EK20,EE21*3/(EG20+EI20+EK20)))) -> 2.4129019 | EF22: 1.5 | EG22: =IF(EG21<=EI20,EG21/EI20,IF(EG21<=EI20+EK20,1+(EG21-EI20)/EK20,IF(EG21<=EI20+EK20+EM20,2+(EG21-EI20-EK20)/EM20,EG21*3/(EI20+EK20+EM20)))) -> 2.7451728 | EH22: 1.5 | EI22: =IF(EI21<=EK20,EI21/EK20,IF(EI21<=EK20+EM20,1+(EI21-EK20)/EM20,IF(EI21<=EK20+EM20+EO20,2+(EI21-EK20-EM20)/EO20,EI21*3/(EK20+EM20+EO20)))) -> 3.2003731 | EJ22: 2.5 | EK22: =IF(EK21<=EM20,EK21/EM20,IF(EK21<=EM20+EO20,1+(EK21-EM20)/EO20,IF(EK21<=EM20+EO20+EQ20,2+(EK21-EM20-EO20)/EQ20,EK21*3/(EM20+EO20+EQ20)))) -> 2.6428266 | EL22: 2.5 | EM22: =IF(EM21<=EO20,EM21/EO20,IF(EM21<=EO20+EQ20,1+(EM21-EO20)/EQ20,IF(EM21<=EO20+EQ20+ES20,2+(EM21-EO20-EQ20)/ES20,EM21*3/(EO20+EQ20+ES20)))) -> 2.1734625 | EN22: 2.5 | EO22: =IF(EO21<=EQ20,EO21/EQ20,IF(EO21<=EQ20+ES20,1+(EO21-EQ20)/ES20,IF(EO21<=EQ20+ES20+EU20,2+(EO21-EQ20-ES20)/EU20,EO21*3/(EQ20+ES20+EU20)))) -> 2.4923186 | EP22: 2.5 | EQ22: =IF(EQ21<=ES20,EQ21/ES20,IF(EQ21<=ES20+EU20,1+(EQ21-ES20)/EU20,IF(EQ21<=ES20+EU20+EW20,2+(EQ21-ES20-EU20)/EW20,EQ21*3/(ES20+EU20+EW20)))) -> 3.0130583 | ER22: 2.5 | ES22: =IF(ES21<=EU20,ES21/EU20,IF(ES21<=EU20+EW20,1+(ES21-EU20)/EW20,IF(ES21<=EU20+EW20+EY20,2+(ES21-EU20-EW20)/EY20,ES21*3/(EU20+EW20+EY20)))) -> #REF! | ET22: 2.5 | EU22: =IF(EU21<=EW20,EU21/EW20,IF(EU21<=EW20+EY20,1+(EU21-EW20)/EY20,IF(EU21<=EW20+EY20+FA20,2+(EU21-EW20-EY20)/FA20,EU21*3/(EW20+EY20+FA20)))) -> #REF! | EV22: 2.5 | EW22: =IF(EW21<=EY20,EW21/EY20,IF(EW21<=EY20+FA20,1+(EW21-EY20)/FA20,IF(EW21<=EY20+FA20+FC20,2+(EW21-EY20-FA20)/FC20,EW21*3/(EY20+FA20+FC20)))) -> #REF! | EX22: 2.5 | EY22: =IF(EY21<=FA20,EY21/FA20,IF(EY21<=FA20+FC20,1+(EY21-FA20)/FC20,IF(EY21<=FA20+FC20+FE20,2+(EY21-FA20-FC20)/FE20,EY21*3/(FA20+FC20+FE20)))) -> #REF! | EZ22: 2.5 | FA22: =IF(FA21<=FC20,FA21/FC20,IF(FA21<=FC20+FE20,1+(FA21-FC20)/FE20,IF(FA21<=FC20+FE20+FG20,2+(FA21-FC20-FE20)/FG20,FA21*3/(FC20+FE20+FG20)))) -> #REF! | FB22: 2.5 | FC22: =IF(FC21<=FE20,FC21/FE20,IF(FC21<=FE20+FG20,1+(FC21-FE20)/FG20,IF(FC21<=FE20+FG20+FI20,2+(FC21-FE20-FG20)/FI20,FC21*3/(FE20+FG20+FI20)))) -> #REF! | FD22: 2 | FE22: =IF(FE21<=FG20,FE21/FG20,IF(FE21<=FG20+FI20,1+(FE21-FG20)/FI20,IF(FE21<=FG20+FI20+FK20,2+(FE21-FG20-FI20)/FK20,FE21*3/(FG20+FI20+FK20)))) -> 1.5098316 | FF22: 2 | FG22: =IF(FG21<=FI20,FG21/FI20,IF(FG21<=FI20+FK20,1+(FG21-FI20)/FK20,IF(FG21<=FI20+FK20+FM20,2+(FG21-FI20-FK20)/FM20,FG21*3/(FI20+FK20+FM20)))) -> 1.8004771 | FH22: 2 | FI22: =IF(FI21<=FK20,FI21/FK20,IF(FI21<=FK20+FM20,1+(FI21-FK20)/FM20,IF(FI21<=FK20+FM20+FO20,2+(FI21-FK20-FM20)/FO20,FI21*3/(FK20+FM20+FO20)))) -> 2.0808737 | FJ22: 2 | FK22: =IF(FK21<=FM20,FK21/FM20,IF(FK21<=FM20+FO20,1+(FK21-FM20)/FO20,IF(FK21<=FM20+FO20+FQ20,2+(FK21-FM20-FO20)/FQ20,FK21*3/(FM20+FO20+FQ20)))) -> 1.715245 | FL22: 2 | FM22: =IF(FM21<=FO20,FM21/FO20,IF(FM21<=FO20+FQ20,1+(FM21-FO20)/FQ20,IF(FM21<=FO20+FQ20+FS20,2+(FM21-FO20-FQ20)/FS20,FM21*3/(FO20+FQ20+FS20)))) -> 1.7257361 | FN22: 2 | FO22: =IF(FO21<=FQ20,FO21/FQ20,IF(FO21<=FQ20+FS20,1+(FO21-FQ20)/FS20,IF(FO21<=FQ20+FS20+FU20,2+(FO21-FQ20-FS20)/FU20,FO21*3/(FQ20+FS20+FU20)))) -> 2.4610092 | FP22: 2 | FQ22: =IF(FQ21<=FS20,FQ21/FS20,IF(FQ21<=FS20+FU20,1+(FQ21-FS20)/FU20,IF(FQ21<=FS20+FU20+FW20,2+(FQ21-FS20-FU20)/FW20,FQ21*3/(FS20+FU20+FW20)))) -> 3.3286677 | FR22: 2 | FS22: =IF(FS21<=FU20,FS21/FU20,IF(FS21<=FU20+FW20,1+(FS21-FU20)/FW20,IF(FS21<=FU20+FW20+FY20,2+(FS21-FU20-FW20)/FY20,FS21*3/(FU20+FW20+FY20)))) -> 2.6246018 | FT22: =IF(FT21<=FV20,FT21/FV20,IF(FT21<=FV20+FX20,1+(FT21-FV20)/FX20,IF(FT21<=FV20+FX20+FZ20,2+(FT21-FV20-FX20)/FZ20,FT21*3/(FV20+FX20+FZ20)))) -> 2.4667848 | FU22: =IF(FU21<=FW20,FU21/FW20,IF(FU21<=FW20+FY20,1+(FU21-FW20)/FY20,IF(FU21<=FW20+FY20+GA20,2+(FU21-FW20-FY20)/GA20,FU21*3/(FW20+FY20+GA20)))) -> 1.8988496 | FV22: =IF(FV21<=FX20,FV21/FX20,IF(FV21<=FX20+FZ20,1+(FV21-FX20)/FZ20,IF(FV21<=FX20+FZ20+#REF!,2+(FV21-FX20-FZ20)/#REF!,FV21*3/(FX20+FZ20+#REF!)))) -> #REF! | FW22: =IF(FW21<=FY20,FW21/FY20,IF(FW21<=FY20+GA20,1+(FW21-FY20)/GA20,IF(FW21<=FY20+GA20+GB20,2+(FW21-FY20-GA20)/GB20,FW21*3/(FY20+GA20+GB20)))) -> 2.1465502 | FX22: =IF(FX21<=FZ20,FX21/FZ20,IF(FX21<=FZ20+#REF!,1+(FX21-FZ20)/#REF!,IF(FX21<=FZ20+#REF!+#REF!,2+(FX21-FZ20-#REF!)/#REF!,FX21*3/(FZ20+#REF!+#REF!)))) -> #REF! | FY22: =IF(FY21<=GA20,FY21/GA20,IF(FY21<=GA20+GB20,1+(FY21-GA20)/GB20,IF(FY21<=GA20+GB20+GC20,2+(FY21-GA20-GB20)/GC20,FY21*3/(GA20+GB20+GC20)))) -> 2.1554238 | FZ22: =IF(FZ21<=#REF!,FZ21/#REF!,IF(FZ21<=#REF!+#REF!,1+(FZ21-#REF!)/#REF!,IF(FZ21<=#REF!+#REF!+#REF!,2+(FZ21-#REF!-#REF!)/#REF!,FZ21*3/(#REF!+#REF!+#REF!)))) -> #REF! | GA22: =IF(GA21<=GB20,GA21/GB20,IF(GA21<=GB20+GC20,1+(GA21-GB20)/GC20,IF(GA21<=GB20+GC20+GD20,2+(GA21-GB20-GC20)/GD20,GA21*3/(GB20+GC20+GD20)))) -> 1.8857842 | GB22: =IF(GB21<=GC20,GB21/GC20,IF(GB21<=GC20+GD20,1+(GB21-GC20)/GD20,IF(GB21<=GC20+GD20+GE20,2+(GB21-GC20-GD20)/GE20,GB21*3/(GC20+GD20+GE20)))) -> 1.8342657 | GC22: =IF(GC21<=GD20,GC21/GD20,IF(GC21<=GD20+GE20,1+(GC21-GD20)/GE20,IF(GC21<=GD20+GE20+GF20,2+(GC21-GD20-GE20)/GF20,GC21*3/(GD20+GE20+GF20)))) -> 2.1766559 | GD22: =IF(GD21<=GE20,GD21/GE20,IF(GD21<=GE20+GF20,1+(GD21-GE20)/GF20,IF(GD21<=GE20+GF20+GG20,2+(GD21-GE20-GF20)/GG20,GD21*3/(GE20+GF20+GG20)))) -> 2.0394976 | GE22: =IF(GE21<=GF20,GE21/GF20,IF(GE21<=GF20+GG20,1+(GE21-GF20)/GG20,IF(GE21<=GF20+GG20+GH20,2+(GE21-GF20-GG20)/GH20,GE21*3/(GF20+GG20+GH20)))) -> 1.8684578 | GF22: =IF(GF21<=GG20,GF21/GG20,IF(GF21<=GG20+GH20,1+(GF21-GG20)/GH20,IF(GF21<=GG20+GH20+GI20,2+(GF21-GG20-GH20)/GI20,GF21*3/(GG20+GH20+GI20)))) -> 2.0304596 | GG22: =IF(GG21<=GH20,GG21/GH20,IF(GG21<=GH20+GI20,1+(GG21-GH20)/GI20,IF(GG21<=GH20+GI20+GJ20,2+(GG21-GH20-GI20)/GJ20,GG21*3/(GH20+GI20+GJ20)))) -> 1.8644275 | GH22: =IF(GH21<=GI20,GH21/GI20,IF(GH21<=GI20+GJ20,1+(GH21-GI20)/GJ20,IF(GH21<=GI20+GJ20+GK20,2+(GH21-GI20-GJ20)/GK20,GH21*3/(GI20+GJ20+GK20)))) -> 2.1681416 | ... JO22: =IF(JO21<=JP20,JO21/JP20,IF(JO21<=JP20+JQ20,1+(JO21-JP20)/JQ20,IF(JO21<=JP20+JQ20+JR20,2+(JO21-JP20-JQ20)/JR20,JO21*3/(JP20+JQ20+JR20)))) -> #DIV/0!
B23: 4X4(L) | C23: 2.5 | D23: In | F23: 0.208 | G23: 0.077 | H23: 0.106 | I23: 0.106 | J23: =H24 -> 0.12 | K23: 0.225 | L23: 0.4 | M23: 0.329 | N23: 0.45 | O23: 0.602 | P23: 0.4 | Q23: 0.374 | R23: 0.3 | S23: 2.476 | T23: 0.35 | U23: 0.568 | V23: 0.4 | W23: 0.639 | X23: 0.6 | Y23: 1.317 | Z23: 0.5 | AA23: 0.216 | AB23: 0.25 | AC23: 0.241 | AD23: 0.4 | AE23: 0.38 | AF23: 0.32 | AG23: 0.069 | AH23: 0.301 | AI23: 0.415 | AJ23: 0.436 | AK23: 0.727 | AL23: 0.549 | AM23: 0.679 | AN23: 0.639 | AO23: 0.739 | AP23: 0.714 | AQ23: 0.458 | AR23: 0.364 | AS23: 0.17 | AT23: 0.48 | AU23: 0.603 | AV23: 0.454 | AW23: 0.84 | AX23: 0.642 | AY23: 0.907 | AZ23: 0.736 | BA23: 0.733 | BB23: 1.165 | BC23: 0.307 | BD23: 0.394 | BE23: 0.139 | BF23: 0.372 | BG23: 0.294 | BH23: 0.798 | BI23: 0.13 | BJ23: 0.59 | BK23: 1.824 | BL23: 0.65 | BM23: 0.468 | BN23: 0.696 | BO23: 0.988 | BP23: 0.67 | BQ23: 0.744 | BR23: 0.802 | BS23: 1.219 | BT23: 0.966 | BU23: 1.548 | BV23: 1.1 | BW23: 1.888 | BX23: 1.4 | BY23: 1.37 | BZ23: 1.127 | CA23: 0.771 | CB23: 0.68 | CC23: 0.273 | CD23: =+CD24 -> 0.596 | CE23: 0.688 | CF23: 0.905 | CG23: 0.72 | CH23: 0.825 | CI23: 0.602 | CJ23: 0.986 | CK23: 0.938 | CL23: 1.105 | CM23: 0.351 | CN23: 0.96428388 | CO23: 0.676 | CP23: 1.1236446 | CQ23: 1.898 | CR23: 1.2780342 | CS23: 1.603 | CT23: 1.9887878 | CU23: 1.304 | CV23: 2.2673419 | CW23: 1.134 | CX23: 1.6417563 | CY23: 0.87 | CZ23: 0.684 | DA23: 1.664 | DB23: 0.678 | DC23: 1.497 | DD23: 0.945 | DE23: 1.708 | DF23: 0.894 | DG23: =[12]PCR!$J$55 -> 1.98 | DH23: 0.919 | DI23: =[13]PCR!$J$56 -> 2.237 | DJ23: 1.229 | DK23: 0.843 | DL23: =1.014 -> 1.014 | DM23: 1.102 | DN23: 1.188 | DO23: 0.673 | DP23: 1.335 | DQ23: 1.309 | DR23: 1.454 | DS23: 2.423 | DT23: 1.706 | DU23: =[14]PCR!$J$69 -> 0.261 | DV23: 1.633 | DW23: =[15]PCR!$J$66 -> 0.806 | DX23: 0.763 | DY23: =[16]PCR!$J$61 -> 0.476 | DZ23: 0.779 | EA23: =[17]PCR!$J$58 -> 0.494 | EB23: 1.136 | EC23: =[18]PCR!$J$61 -> 0.855 | ED23: 1.182 | EE23: =[19]PCR!$J$59 -> 0.768 | EF23: 1.354 | EG23: =[20]PCR!$J$62 -> 1.619 | EH23: 1.603 | EI23: =[21]PCR!$J$66 -> 1.301 | EJ23: 1.005 | EK23: =[22]PCR!$J$65 -> 1.272 | EL23: 1.174 | EM23: =[23]PCR!$J$78 -> 2.607 | EN23: 1.652 | EO23: =[24]PCR!$J$94 -> 2.019 | EP23: 2.191 | EQ23: =[25]PCR!$J$98 -> 1.413 | ER23: 2.423 | ES23: =[26]PCR!$J$90 -> 1.149 | ET23: 2.202 | EU23: =[27]PCR!$J$86 -> 1.384 | EV23: 0.868 | EW23: =[28]PCR!$J$78 -> 0.181 | EX23: 1.053 | EY23: =[29]PCR!$J$76 -> #REF! | EZ23: 1.2 | FA23: =[30]PCR!$J$74 -> 0.399 | FB23: 1.2 | FC23: 1.355 | FD23: 1.342 | FE23: =[31]PCR!$J$73 -> 1.211 | FF23: 1.596 | FG23: =[32]PCR!$J$74 -> 0.837 | FH23: 1.197 | FI23: =[33]PCR!$J$78 -> 2.842 | FJ23: 1.232 | FK23: =[34]PCR!$J$78 -> 1.573 | FL23: 1.4955215 | FM23: =[35]PCR!$J$86 -> 2.527 | FN23: 1.9432195 | FO23: =[36]PCR!$J$85 -> 3.092 | FP23: 1.96 | FQ23: =[37]PCR!$J$86 -> 2.956 | FR23: 1.756 | FS23: =[38]PCR!$J$79 -> 0.309 | FT23: 0.519 | FU23: =[39]PCR!$J$77 -> 0.87 | FV23: 1.319 | FW23: =[40]PCR!$J$73 -> 1.144 | FX23: 1.496 | FY23: =[41]PCR!$J$75 -> 1.504 | FZ23: 1.558 | GA23: =[42]PCR!$J$73 -> 1.431 | GB23: 0.912 | GC23: 2.932 | GD23: 2.705 | GE23: 3.169 | GF23: 1.98 | GG23: 1.901 | GH23: 3.188 | GI23: 1.016 | GJ23: 2.74 | GK23: 1.182 | GL23: 1.502 | GM23: 4.451 | GN23: 3.652 | GO23: 2.689 | GP23: 7.03 | GQ23: 4.435 | GR23: 3.703 | GS23: 3.832 | GT23: 4.091 | GU23: 1.211 | GV23: 3.241 | GW23: 3.496 | GX23: 3.848 | GY23: 4.451 | GZ23: 2.014 | HA23: 1.727 | HB23: 3.111 | HC23: 1.605 | HD23: 9.237 | HE23: 4.721 | HF23: 2.005 | HG23: 0.692 | HH23: =[43]PCR!$I$169 -> 1.283 | HI23: =[44]PCR!$I$169 -> 0.88 | HJ23: 3.743 | HK23: =[45]PCR!$I$169 -> 3.978 | HL23: =[50]PCR!$I$169 -> 6.755 | HM23: 3.371 | HN23: 2.837 | HO23: 2.563 | HP23: 4.836 | HQ23: 3.455 | HR23: 2.498 | HS23: 1.787 | HT23: 0.805 | HU23: 3.052 | HV23: 4.689 | HW23: 3.348 | HX23: 6.306 | HY23: =[46]Cate!I169 -> 6.476 | HZ23: 10.118 | IA23: =[47]Cate!I169 -> 8.991 | IB23: 6.6 | IC23: 4.487 | ID23: =[49]PCR!$I$169 -> 0.821 | IE23: 1.411 | IF23: 0.774 | IG23: 1.441 | IH23: =[51]PCR!$I$169 -> 1.5 | II23: 8.123 | IJ23: 5.836 | IK23: 8.025 | IL23: 4.075 | IM23: 20.996 | IN23: 10.709 | IO23: 3.643 | IP23: 3.219 | IQ23: 0.365 | IR23: 3.979 | IS23: 3.806 | IT23: 1.433 | IU23: 2.611 | IV23: 1.92 | IW23: 11.085 | IX23: 10.43 | IY23: 11.992 | IZ23: 8.449 | JA23: 11.285 | JB23: 5.862 | JC23: 2.382 | JD23: 1.769 | JE23: 4.493 | JF23: 6.023 | JG23: 8.523 | JH23: 6.697
D24: Out | F24: 0.211 | G24: 0.314 | H24: 0.12 | I24: 0.123 | J24: 0.1 | K24: 0.275 | L24: 0.3 | M24: 0.342 | N24: 0.3 | O24: 0.252 | P24: 0.547 | Q24: 0.321 | R24: 0.4 | S24: 0.61 | T24: 0.35 | U24: 0.559 | V24: 0.239 | W24: 0.337 | X24: 0.4 | Y24: 0.884 | Z24: 0.5 | AA24: 0.519 | AB24: 0.55 | AC24: 0.81 | AD24: 0.4 | AE24: 1.133 | AF24: 0.32 | AG24: 0.403 | AH24: 0.301 | AI24: 0.253 | AJ24: 0.436 | AK24: 0.524 | AL24: 0.549 | AM24: 0.43 | AN24: 0.639 | AO24: 0.973 | AP24: 0.714 | AQ24: 0.472 | AR24: 0.364 | AS24: 0.513 | AT24: 0.48 | AU24: 0.571 | AV24: 0.454 | AW24: 0.485 | AX24: 0.642 | AY24: 0.604 | AZ24: 0.736 | BA24: 0.79 | BB24: 1.165 | BC24: 0.708 | BD24: 0.394 | BE24: 0.497 | BF24: 0.372 | BG24: 0.713 | BH24: 0.798 | BI24: 0.347 | BJ24: 0.59 | BK24: 0.642 | BL24: 0.65 | BM24: 1.527 | BN24: 0.696 | BO24: 0.953 | BP24: 0.67 | BQ24: 0.569 | BR24: 0.802 | BS24: 0.856 | BT24: 0.966 | BU24: 1.133 | BV24: =+BV23 -> 1.1 | BW24: 1.144 | BX24: =+BX23 -> 1.4 | BY24: 1.811 | BZ24: =+BZ23 -> 1.127 | CA24: 1.211 | CB24: =+CB23 -> 0.68 | CC24: 0.812 | CD24: 0.596 | CE24: 0.612 | CF24: 0.905 | CG24: 0.411 | CH24: 0.825 | CI24: 0.229 | CJ24: 0.986 | CK24: 0.843 | CL24: 1.105 | CM24: 0.999 | CN24: =+CN23 -> 0.96428388 | CO24: 0.668 | CP24: 1.1236446 | CQ24: 0.736 | CR24: 1.2780342 | CS24: 1.409 | CT24: =+CT23 -> 1.9887878 | CU24: 1.053 | CV24: =+CV23 -> 2.2673419 | CW24: 1.443 | CX24: =+CX23 -> 1.6417563 | CY24: 1.75 | CZ24: 0.684 | DA24: 1.598 | DB24: 0.678 | DC24: 0.842 | DD24: 0.945 | DE24: 1.106 | DF24: 0.894 | DG24: =[12]PCR!$J$56 -> 1.642 | DH24: 0.919 | DI24: =[13]PCR!$J$57 -> 1.254 | DJ24: 1.229 | DK24: 2.044 | DL24: =DL23 -> 1.014 | DM24: 1.008 | DN24: =DN23 -> 1.188 | DO24: 1.038 | DP24: =DP23 -> 1.335 | DQ24: 0.843 | DR24: =DR23 -> 1.454 | DS24: 0.621 | DT24: =DT23 -> 1.706 | DU24: =[14]PCR!$J$70 -> 1.435 | DV24: =DV23 -> 1.633 | DW24: =[15]PCR!$J$67 -> 1.426 | DX24: =DX23 -> 0.763 | DY24: =[16]PCR!$J$62 -> 0.928 | DZ24: =DZ23 -> 0.779 | EA24: =[17]PCR!$J$59 -> 0.449 | EB24: =EB23 -> 1.136 | EC24: =[18]PCR!$J$62 -> 0.715 | ED24: =ED23 -> 1.182 | EE24: =[19]PCR!$J$60 -> 0.747 | EF24: =EF23 -> 1.354 | EG24: =[20]PCR!$J$63 -> 1.021 | EH24: =EH23 -> 1.603 | EI24: =[21]PCR!$J$67 -> 0.742 | EJ24: =EJ23 -> 1.005 | EK24: =[22]PCR!$J$66 -> 1.401 | EL24: =EL23 -> 1.174 | EM24: =[23]PCR!$J$79 -> 1.675 | EN24: =EN23 -> 1.652 | EO24: =[24]PCR!$J$95 -> 1.343 | EP24: =EP23 -> 2.191 | EQ24: =[25]PCR!$J$99 -> 1.435 | ER24: =ER23 -> 2.423 | ES24: =[26]PCR!$J$91 -> 1.626 | ET24: =ET23 -> 2.202 | EU24: =[27]PCR!$J$87 -> 1.882 | EV24: =EV23 -> 0.868 | EW24: =[28]PCR!$J$79 -> 0.724 | EX24: =EX23 -> 1.053 | EY24: =[29]PCR!$J$77 -> #REF! | EZ24: =EZ23 -> 1.2 | FA24: =[30]PCR!$J$75 -> 0.535 | FB24: =FB23 -> 1.2 | FC24: 0.888 | FD24: =FD23 -> 1.342 | FE24: =[31]PCR!$J$74 -> 0.992 | FF24: =FF23 -> 1.596 | FG24: =[32]PCR!$J$75 -> 1.03 | FH24: 1.197 | FI24: =[33]PCR!$J$79 -> 1.76 | FJ24: 1.232 | FK24: =[34]PCR!$J$79 -> 1.997 | FL24: 1.4955215 | FM24: =[35]PCR!$J$87 -> 1.59 | FN24: 1.9432195 | FO24: =[36]PCR!$J$86 -> 2.719 | FP24: 1.96 | FQ24: =[37]PCR!$J$87 -> 3.018 | FR24: 1.756 | FS24: =[38]PCR!$J$80 -> 2.273 | FT24: 1.206 | FU24: =[39]PCR!$J$78 -> 1.022 | FV24: 0.94 | FW24: =[40]PCR!$J$74 -> 0.833 | FX24: 1.199 | FY24: =[41]PCR!$J$76 -> 1.567 | FZ24: 1.607 | GA24: =[42]PCR!$J$74 -> 1.492 | GB24: 1.286 | GC24: 1.402 | GD24: 2.14 | GE24: 2.024 | GF24: 3.809 | GG24: 3.164 | GH24: 3.9 | GI24: 2.113 | GJ24: 2.461 | GK24: 1.82 | GL24: 1.139 | GM24: 2.863 | GN24: 2.649 | GO24: 2.128 | GP24: 3.397 | GQ24: 3.032 | GR24: 4.367 | GS24: 6.027 | GT24: 5.34 | GU24: 3.835 | GV24: 2.721 | GW24: 2.263 | GX24: 2.49 | GY24: 2.054 | GZ24: 2.411 | HA24: 2.824 | HB24: 1.349 | HC24: 1.322 | HD24: 4.106 | HE24: 5.512 | HF24: 7.706 | HG24: 3.908 | HH24: =[43]PCR!$I$170 -> 2.023 | HI24: =[44]PCR!$I$170 -> 1.296 | HJ24: 1.334 | HK24: =[45]PCR!$J$169 -> 1.454 | HL24: =[50]PCR!$I$170 -> 2.787 | HM24: 4.108 | HN24: 3.12 | HO24: 2.792 | HP24: 5.356 | HQ24: 10.11 | HR24: 4.804 | HS24: 2.412 | HT24: 1.706 | HU24: 1.749 | HV24: 3.335 | HW24: 3.92 | HX24: 3.772 | HY24: =[46]Cate!J169 -> 3.805 | HZ24: 6.189 | IA24: =[47]Cate!J169 -> 6.732 | IB24: 6.556 | IC24: 11.619 | ID24: =[49]PCR!$J$169 -> 2.349 | IE24: 5.711 | IF24: 1.067 | IG24: 1.225 | IH24: =[51]PCR!$J$169 -> 1.116 | II24: 3.269 | IJ24: 7.888 | IK24: 5.393 | IL24: 2.664 | IM24: 10.901 | IN24: 12.541 | IO24: 7.714 | IP24: 3.753 | IQ24: 4.938 | IR24: 2.206 | IS24: 3.438 | IT24: 3.941 | IU24: 5.294 | IV24: 2.047 | IW24: 11.23 | IX24: 5.422 | IY24: 7.601 | IZ24: 9.667 | JA24: 8.617 | JB24: 8.005 | JC24: 8.558 | JD24: 1.833 | JE24: 3.971 | JF24: 7.353 | JG24: 6.705 | JH24: 5.205
D25: Inventory | F25: 0.017 | G25: 0.508 | H25: =F25+H23-H24 -> 0.003 | I25: =G25+I23-I24 -> 0.491 | J25: =H25+J23-J24 -> 0.023 | K25: =I25+K23-K24 -> 0.441 | L25: =J25+L23-L24 -> 0.123 | M25: =K25+M23-M24 -> 0.428 | N25: =L25+N23-N24 -> 0.273 | O25: =M25+O23-O24 -> 0.778 | ... AK25: =AI25+AK23-AK24 -> 1.847 | AL25: =N25*1.137 -> 0.310401 | AM25: =AK25+AM23-AM24 -> 2.096 | AN25: =P25*1.137 -> 0.143262 | AO25: =AM25+AO23-AO24 -> 1.862 | AP25: =R25*1.137 -> 0.029562 | AQ25: 1.866 | AR25: =T25*1.137 -> 0.029562 | AS25: =AQ25+AS23-AS24 -> 1.523 | AT25: =V25*1.137 -> 0.212619 | AU25: =AS25+AU23-AU24 -> 1.555 | AV25: =X25*1.137 -> 0.440019 | AW25: =AU25+AW23-AW24 -> 1.91 | AX25: =Z25*1.137 -> 0.440019 | AY25: =AW25+AY23-AY24 -> 2.213 | AZ25: 0.098919 | BA25: 2.156 | BB25: 0.098919 | BC25: 1.755 | BD25: 0.098919 | BE25: 1.397 | BF25: =BD25+BF23-BF24 -> 0.098919 | BG25: 1.159 | BH25: =AJ25*1.137 -> 0.098919 | BI25: =BG25+BI23-BI24 -> 0.942 | BJ25: =AL25*1.137 -> 0.35292594 | BK25: =BI25+BK23-BK24 -> 2.124 | BL25: =AN25*1.137 -> 0.16288889 | BM25: =BK25+BM23-BM24 -> 1.065 | BN25: =AP25*1.137 -> 0.033611994 | BO25: =BM25+BO23-BO24 -> 1.1 | BP25: =AR25*1.137 -> 0.033611994 | BQ25: =BO25+BQ23-BQ24 -> 1.275 | BR25: =AT25*1.137 -> 0.2417478 | BS25: =BQ25+BS23-BS24 -> 1.638 | BT25: =AV25*1.137 -> 0.5003016 | BU25: =BS25+BU23-BU24 -> 2.053 | BV25: =AX25*1.137 -> 0.5003016 | BW25: =BU25+BW23-BW24 -> 2.797 | BX25: =AZ25*1.137 -> 0.1124709 | BY25: =BW25+BY23-BY24 -> 2.356 | BZ25: =BB25*1.137 -> 0.1124709 | CA25: =BY25+CA23-CA24 -> 1.916 | CB25: =BD25*1.137 -> 0.1124709 | CC25: =CA25+CC23-CC24 -> 1.377 | CD25: =BF25*1.137 -> 0.1124709 | CE25: =CC25+CE23-CE24 -> 1.453 | CF25: =BH25*1.137 -> 0.1124709 | CG25: =CE25+CG23-CG24 -> 1.762 | CH25: =BJ25*1.137 -> 0.40127679 | CI25: =CG25+CI23-CI24 -> 2.135 | CJ25: 0.879 | CK25: =CI25+CK23-CK24 -> 2.23 | CL25: 0.879 | CM25: =CK25+CM23-CM24 -> 1.582 | CN25: 0.879 | CO25: =CM25+CO23-CO24 -> 1.59 | CP25: 0.879 | CQ25: =CO25+CQ23-CQ24 -> 2.752 | CR25: 0.879 | CS25: =CQ25+CS23-CS24 -> 2.946 | CT25: 1.3837878 | CU25: =CS25+CU23-CU24 -> 3.197 | CV25: 0.879 | CW25: =CU25+CW23-CW24 -> 2.888 | CX25: 0.879 | CY25: 2.024 | CZ25: 0.879 | DA25: =CY25+DA23-DA24 -> 2.09 | DB25: 0.879 | DC25: =DA25+DC23-DC24 -> 2.745 | DD25: 0.879 | DE25: =DC25+DE23-DE24 -> 3.347 | DF25: 0.879 | DG25: =DE25+DG23-DG24 -> 3.685 | DH25: 0.879 | DI25: =DG25+DI23-DI24 -> 4.668 | DJ25: 0.879 | DK25: =DI25+DK23-DK24 -> 3.467 | DL25: 0.879 | DM25: =DK25+DM23-DM24 -> 3.561 | DN25: 0.879 | DO25: =DM25+DO23-DO24 -> 3.196 | DP25: 0.879 | DQ25: =DO25+DQ23-DQ24 -> 3.662 | DR25: 0.879 | DS25: =DQ25+DS23-DS24 -> 5.464 | DT25: 0.879 | DU25: =DS25+DU23-DU24 -> 4.29 | DV25: 0.879 | DW25: =DU25+DW23-DW24 -> 3.67 | DX25: 0.879 | DY25: =DW25+DY23-DY24 -> 3.218 | DZ25: 0.879 | EA25: =DY25+EA23-EA24 -> 3.263 | EB25: 0.879 | EC25: =EA25+EC23-EC24 -> 3.403 | ED25: 0.879 | EE25: =EC25+EE23-EE24 -> 3.424 | EF25: 0.879 | EG25: =EE25+EG23-EG24 -> 4.022 | EH25: 0.879 | EI25: =EG25+EI23-EI24 -> 4.581 | EJ25: 0.879 | EK25: =EI25+EK23-EK24 -> 4.452 | EL25: 0.879 | EM25: =EK25+EM23-EM24 -> 5.384 | EN25: 0.879 | EO25: 6.117 | EP25: 0.879 | EQ25: =EO25+EQ23-EQ24 -> 6.095 | ER25: 0.879 | ES25: =EQ25+ES23-ES24 -> 5.618 | ET25: 0.879 | EU25: =ES25+EU23-EU24 -> 5.12 | EV25: 0.879 | EW25: =EU25+EW23-EW24 -> 4.577 | EX25: 0.879 | EY25: =EW25+EY23-EY24 -> #REF! | EZ25: 0.879 | FA25: =EY25+FA23-FA24 -> #REF! | FB25: 0.879 | FC25: =FA25+FC23-FC24 -> #REF! | FD25: 0.879 | FE25: 5.133 | FF25: 0.879 | FG25: =FE25+FG23-FG24 -> 4.94 | FH25: 0.879 | FI25: =FG25+FI23-FI24 -> 6.022 | FJ25: 0.879 | FK25: =FI25+FK23-FK24 -> 5.598 | FL25: 0.879 | FM25: =FK25+FM23-FM24 -> 6.535 | FN25: 0.879 | FO25: =FM25+FO23-FO24 -> 6.908 | FP25: 0.879 | FQ25: =FO25+FQ23-FQ24 -> 6.846 | FR25: 4.346 | FS25: =FQ25+FS23-FS24 -> 4.882 | FT25: =FR25+FT23-FT24 -> 3.659 | FU25: =FS25+FU23-FU24 -> 4.73 | FV25: =FT25+FV23-FV24 -> 4.038 | FW25: =FU25+FW23-FW24 -> 5.041 | FX25: =FV25+FX23-FX24 -> 4.335 | FY25: =FW25+FY23-FY24 -> 4.978 | FZ25: 5.048 | GA25: 4.905 | GB25: =GA25+GB23-GB24 -> 4.531 | GC25: =GB25+GC23-GC24 -> 6.061 | GD25: =GC25+GD23-GD24 -> 6.626 | GE25: =GD25+GE23-GE24 -> 7.771 | GF25: =GE25+GF23-GF24 -> 5.942 | GG25: =GF25+GG23-GG24 -> 4.679 | GH25: =GG25+GH23-GH24 -> 3.967 | GI25: =GH25+GI23-GI24 -> 2.87 | ... GR25: =GQ25+GR23-GR24 -> 10.398 | GS25: 8.323 | GT25: =GS25+GT23-GT24 -> 7.074 | GU25: =GT25+GU23-GU24 -> 4.45 | GV25: =GU25+GV23-GV24 -> 4.97 | GW25: =GV25+GW23-GW24 -> 6.203 | GX25: =GW25+GX23-GX24 -> 7.561 | GY25: =GX25+GY23-GY24 -> 9.958 | GZ25: =GY25+GZ23-GZ24 -> 9.561 | HA25: =GZ25+HA23-HA24 -> 8.464 | HB25: =HA25+HB23-HB24 -> 10.226 | HC25: 15.087 | HD25: =HC25+HD23-HD24 -> 20.218 | HE25: =HD25+HE23-HE24 -> 19.427 | HF25: =HE25+HF23-HF24 -> 13.726 | HG25: =HF25+HG23-HG24 -> 10.51 | HH25: =HG25+HH23-HH24 -> 9.77 | HI25: =HH25+HI23-HI24 -> 9.354 | HJ25: =HI25+HJ23-HJ24 -> 11.763 | HK25: =HJ25+HK23-HK24 -> 14.287 | ... HU25: =HT25+HU23-HU24 -> 7.302 | HV25: 8.693 | HW25: =HV25+HW23-HW24 -> 8.121 | HX25: =HW25+HX23-HX24 -> 10.655 | HY25: =HX25+HY23-HY24 -> 13.326 | HZ25: =HY25+HZ23-HZ24 -> 17.255 | IA25: =HZ25+IA23-IA24 -> 19.514 | IB25: =IA25+IB23-IB24 -> 19.558 | IC25: =IB25+IC23-IC24 -> 12.426 | ID25: =IC25+ID23-ID24 -> 10.898 | ... IL25: =IK25+IL23-IL24 -> 13.75 | IM25: 23.845 | IN25: =IM25+IN23-IN24 -> 22.013 | IO25: =IN25+IO23-IO24 -> 17.942 | IP25: =IO25+IP23-IP24 -> 17.408 | IQ25: =IP25+IQ23-IQ24 -> 12.835 | IR25: =IQ25+IR23-IR24 -> 14.608 | IS25: =IR25+IS23-IS24 -> 14.976 | IT25: =IS25+IT23-IT24 -> 12.468 | IU25: =IT25+IU23-IU24 -> 9.785 | ... JO25: =JN25+JO23-JO24 -> 14.481
D26: month | E26: 1.9 | F26: 0.050049068 | G26: 2.9607407 | H26: =IF(H25<=J24,H25/J24,IF(H25<=J24+L24,1+(H25-J24)/L24,IF(H25<=J24+L24+N24,2+(H25-J24-L24)/N24,H25*3/(J24+L24+N24)))) -> 0.03 | I26: =IF(I25<=K24,I25/K24,IF(I25<=K24+M24,1+(I25-K24)/M24,IF(I25<=K24+M24+O24,2+(I25-K24-M24)/O24,I25*3/(K24+M24+O24)))) -> 1.6315789 | J26: =IF(J25<=L24,J25/L24,IF(J25<=L24+N24,1+(J25-L24)/N24,IF(J25<=L24+N24+P24,2+(J25-L24-N24)/P24,J25*3/(L24+N24+P24)))) -> 0.076666667 | K26: =IF(K25<=M24,K25/M24,IF(K25<=M24+O24,1+(K25-M24)/O24,IF(K25<=M24+O24+Q24,2+(K25-M24-O24)/Q24,K25*3/(M24+O24+Q24)))) -> 1.3928571 | L26: =IF(L25<=N24,L25/N24,IF(L25<=N24+P24,1+(L25-N24)/P24,IF(L25<=N24+P24+R24,2+(L25-N24-P24)/R24,L25*3/(N24+P24+R24)))) -> 0.41 | M26: =IF(M25<=O24,M25/O24,IF(M25<=O24+Q24,1+(M25-O24)/Q24,IF(M25<=O24+Q24+S24,2+(M25-O24-Q24)/S24,M25*3/(O24+Q24+S24)))) -> 1.5482866 | N26: =IF(N25<=P24,N25/P24,IF(N25<=P24+R24,1+(N25-P24)/R24,IF(N25<=P24+R24+T24,2+(N25-P24-R24)/T24,N25*3/(P24+R24+T24)))) -> 0.49908592 | O26: =IF(O25<=Q24,O25/Q24,IF(O25<=Q24+S24,1+(O25-Q24)/S24,IF(O25<=Q24+S24+U24,2+(O25-Q24-S24)/U24,O25*3/(Q24+S24+U24)))) -> 1.7491803 | ... CI26: =IF(CI25<=CK24,CI25/CK24,IF(CI25<=CK24+CM24,1+(CI25-CK24)/CM24,IF(CI25<=CK24+CM24+CO24,2+(CI25-CK24-CM24)/CO24,CI25*3/(CK24+CM24+CO24)))) -> 2.4386228 | CJ26: =IF(CJ25<=CL24,CJ25/CL24,IF(CJ25<=CL24+CN24,1+(CJ25-CL24)/CN24,IF(CJ25<=CL24+CN24+#REF!,2+(CJ25-CL24-CN24)/#REF!,CJ25*3/(CL24+CN24+#REF!)))) -> 0.79547511 | CK26: =IF(CK25<=CM24,CK25/CM24,IF(CK25<=CM24+CO24,1+(CK25-CM24)/CO24,IF(CK25<=CM24+CO24+CQ24,2+(CK25-CM24-CO24)/CQ24,CK25*3/(CM24+CO24+CQ24)))) -> 2.7649457 | CL26: =IF(CL25<=CN24,CL25/CN24,IF(CL25<=CN24+CP24,1+(CL25-CN24)/CP24,IF(CL25<=CN24+CP24+#REF!,2+(CL25-CN24-CP24)/#REF!,CL25*3/(CN24+CP24+#REF!)))) -> 0.91155729 | CM26: =IF(CM25<=CO24,CM25/CO24,IF(CM25<=CO24+CQ24,1+(CM25-CO24)/CQ24,IF(CM25<=CO24+CQ24+CS24,2+(CM25-CO24-CQ24)/CS24,CM25*3/(CO24+CQ24+CS24)))) -> 2.1263307 | CN26: =IF(CN25<=CP24,CN25/CP24,IF(CN25<=CP24+CR24,1+(CN25-CP24)/CR24,IF(CN25<=CP24+CR24+#REF!,2+(CN25-CP24-CR24)/#REF!,CN25*3/(CP24+CR24+#REF!)))) -> 0.78227579 | CO26: =IF(CO25<=CQ24,CO25/CQ24,IF(CO25<=CQ24+CS24,1+(CO25-CQ24)/CS24,IF(CO25<=CQ24+CS24+CU24,2+(CO25-CQ24-CS24)/CU24,CO25*3/(CQ24+CS24+CU24)))) -> 1.6061036 | CP26: =IF(CP25<=CR24,CP25/CR24,IF(CP25<=CR24+CT24,1+(CP25-CR24)/CT24,IF(CP25<=CR24+CT24+#REF!,2+(CP25-CR24-CT24)/#REF!,CP25*3/(CR24+CT24+#REF!)))) -> 0.68777502 | CQ26: =IF(CQ25<=CS24,CQ25/CS24,IF(CQ25<=CS24+CU24,1+(CQ25-CS24)/CU24,IF(CQ25<=CS24+CU24+CW24,2+(CQ25-CS24-CU24)/CW24,CQ25*3/(CS24+CU24+CW24)))) -> 2.2009702 | CR26: =IF(CR25<=CT24,CR25/CT24,IF(CR25<=CT24+CV24,1+(CR25-CT24)/CV24,IF(CR25<=CT24+CV24+#REF!,2+(CR25-CT24-CV24)/#REF!,CR25*3/(CT24+CV24+#REF!)))) -> 0.44197778 | CS26: =IF(CS25<=CU24,CS25/CU24,IF(CS25<=CU24+CW24,1+(CS25-CU24)/CW24,IF(CS25<=CU24+CW24+CY24,2+(CS25-CU24-CW24)/CY24,CS25*3/(CU24+CW24+CY24)))) -> 2.2571429 | CT26: =BV26*1.137 -> 0.40631637 | CU26: =IF(CU25<=CW24,CU25/CW24,IF(CU25<=CW24+CY24,1+(CU25-CW24)/CY24,IF(CU25<=CW24+CY24+DA24,2+(CU25-CW24-CY24)/DA24,CU25*3/(CW24+CY24+DA24)))) -> 2.0025031 | CV26: =BX26*1.137 -> 0.11346887 | CW26: =IF(CW25<=CY24,CW25/CY24,IF(CW25<=CY24+DA24,1+(CW25-CY24)/DA24,IF(CW25<=CY24+DA24+DC24,2+(CW25-CY24-DA24)/DC24,CW25*3/(CY24+DA24+DC24)))) -> 1.7121402 | CX26: =BZ26*1.137 -> 0.18805797 | CY26: =IF(CY25<=DA24,CY25/DA24,IF(CY25<=DA24+DC24,1+(CY25-DA24)/DC24,IF(CY25<=DA24+DC24+DE24,2+(CY25-DA24-DC24)/DE24,CY25*3/(DA24+DC24+DE24)))) -> 1.5059382 | CZ26: =CB26*1.137 -> 0.21456278 | DA26: =IF(DA25<=DC24,DA25/DC24,IF(DA25<=DC24+DE24,1+(DA25-DC24)/DE24,IF(DA25<=DC24+DE24+DG24,2+(DA25-DC24-DE24)/DG24,DA25*3/(DC24+DE24+DG24)))) -> 2.0864799 | DB26: =CD26*1.137 -> 0.14130322 | DC26: =IF(DC25<=DE24,DC25/DE24,IF(DC25<=DE24+DG24,1+(DC25-DE24)/DG24,IF(DC25<=DE24+DG24+DI24,2+(DC25-DE24-DG24)/DI24,DC25*3/(DE24+DG24+DI24)))) -> 1.998173 | DD26: =CF26*1.137 -> 0.15500535 | DE26: =IF(DE25<=DG24,DE25/DG24,IF(DE25<=DG24+DI24,1+(DE25-DG24)/DI24,IF(DE25<=DG24+DI24+DK24,2+(DE25-DG24-DI24)/DK24,DE25*3/(DG24+DI24+DK24)))) -> 2.2206458 | DF26: =CH26*1.137 -> 0.46272993 | DG26: =IF(DG25<=DI24,DG25/DI24,IF(DG25<=DI24+DK24,1+(DG25-DI24)/DK24,IF(DG25<=DI24+DK24+DM24,2+(DG25-DI24-DK24)/DM24,DG25*3/(DI24+DK24+DM24)))) -> 2.3839286 | DH26: =CJ26*1.137 -> 0.9044552 | DI26: =IF(DI25<=DK24,DI25/DK24,IF(DI25<=DK24+DM24,1+(DI25-DK24)/DM24,IF(DI25<=DK24+DM24+DO24,2+(DI25-DK24-DM24)/DO24,DI25*3/(DK24+DM24+DO24)))) -> 3.4239609 | DJ26: 1.5 | DK26: =IF(DK25<=DM24,DK25/DM24,IF(DK25<=DM24+DO24,1+(DK25-DM24)/DO24,IF(DK25<=DM24+DO24+DQ24,2+(DK25-DM24-DO24)/DQ24,DK25*3/(DM24+DO24+DQ24)))) -> 3.6002077 | DL26: 1.5 | DM26: =IF(DM25<=DO24,DM25/DO24,IF(DM25<=DO24+DQ24,1+(DM25-DO24)/DQ24,IF(DM25<=DO24+DQ24+DS24,2+(DM25-DO24-DQ24)/DS24,DM25*3/(DO24+DQ24+DS24)))) -> 4.2697842 | DN26: 1.5 | DO26: =IF(DO25<=DQ24,DO25/DQ24,IF(DO25<=DQ24+DS24,1+(DO25-DQ24)/DS24,IF(DO25<=DQ24+DS24+DU24,2+(DO25-DQ24-DS24)/DU24,DO25*3/(DQ24+DS24+DU24)))) -> 3.3073474 | DP26: 1.5 | DQ26: =IF(DQ25<=DS24,DQ25/DS24,IF(DQ25<=DS24+DU24,1+(DQ25-DS24)/DU24,IF(DQ25<=DS24+DU24+DW24,2+(DQ25-DS24-DU24)/DW24,DQ25*3/(DS24+DU24+DW24)))) -> 3.1550833 | DR26: 1.5 | DS26: =IF(DS25<=DU24,DS25/DU24,IF(DS25<=DU24+DW24,1+(DS25-DU24)/DW24,IF(DS25<=DU24+DW24+DY24,2+(DS25-DU24-DW24)/DY24,DS25*3/(DU24+DW24+DY24)))) -> 4.3262074 | DT26: 1.5 | DU26: =IF(DU25<=DW24,DU25/DW24,IF(DU25<=DW24+DY24,1+(DU25-DW24)/DY24,IF(DU25<=DW24+DY24+EA24,2+(DU25-DW24-DY24)/EA24,DU25*3/(DW24+DY24+EA24)))) -> 4.5915091 | DV26: 1.5 | DW26: =IF(DW25<=DY24,DW25/DY24,IF(DW25<=DY24+EA24,1+(DW25-DY24)/EA24,IF(DW25<=DY24+EA24+EC24,2+(DW25-DY24-EA24)/EC24,DW25*3/(DY24+EA24+EC24)))) -> 5.2629063 | DX26: 1.5 | DY26: =IF(DY25<=EA24,DY25/EA24,IF(DY25<=EA24+EC24,1+(DY25-EA24)/EC24,IF(DY25<=EA24+EC24+EE24,2+(DY25-EA24-EC24)/EE24,DY25*3/(EA24+EC24+EE24)))) -> 5.0518053 | DZ26: 1.5 | EA26: =IF(EA25<=EC24,EA25/EC24,IF(EA25<=EC24+EE24,1+(EA25-EC24)/EE24,IF(EA25<=EC24+EE24+EG24,2+(EA25-EC24-EE24)/EG24,EA25*3/(EC24+EE24+EG24)))) -> 3.9424084 | EB26: 1.5 | EC26: =IF(EC25<=EE24,EC25/EE24,IF(EC25<=EE24+EG24,1+(EC25-EE24)/EG24,IF(EC25<=EE24+EG24+EI24,2+(EC25-EE24-EG24)/EI24,EC25*3/(EE24+EG24+EI24)))) -> 4.0673307 | ED26: 1.5 | EE26: =IF(EE25<=EG24,EE25/EG24,IF(EE25<=EG24+EI24,1+(EE25-EG24)/EI24,IF(EE25<=EG24+EI24+EK24,2+(EE25-EG24-EI24)/EK24,EE25*3/(EG24+EI24+EK24)))) -> 3.2465234 | EF26: 1.5 | EG26: =IF(EG25<=EI24,EG25/EI24,IF(EG25<=EI24+EK24,1+(EG25-EI24)/EK24,IF(EG25<=EI24+EK24+EM24,2+(EG25-EI24-EK24)/EM24,EG25*3/(EI24+EK24+EM24)))) -> 3.1602933 | EH26: 1.5 | EI26: =IF(EI25<=EK24,EI25/EK24,IF(EI25<=EK24+EM24,1+(EI25-EK24)/EM24,IF(EI25<=EK24+EM24+EO24,2+(EI25-EK24-EM24)/EO24,EI25*3/(EK24+EM24+EO24)))) -> 3.1099796 | EJ26: 2.5 | EK26: =IF(EK25<=EM24,EK25/EM24,IF(EK25<=EM24+EO24,1+(EK25-EM24)/EO24,IF(EK25<=EM24+EO24+EQ24,2+(EK25-EM24-EO24)/EQ24,EK25*3/(EM24+EO24+EQ24)))) -> 2.9993031 | EL26: 2.5 | EM26: =IF(EM25<=EO24,EM25/EO24,IF(EM25<=EO24+EQ24,1+(EM25-EO24)/EQ24,IF(EM25<=EO24+EQ24+ES24,2+(EM25-EO24-EQ24)/ES24,EM25*3/(EO24+EQ24+ES24)))) -> 3.6675749 | EN26: 2.5 | EO26: =IF(EO25<=EQ24,EO25/EQ24,IF(EO25<=EQ24+ES24,1+(EO25-EQ24)/ES24,IF(EO25<=EQ24+ES24+EU24,2+(EO25-EQ24-ES24)/EU24,EO25*3/(EQ24+ES24+EU24)))) -> 3.7125228 | EP26: 2.5 | EQ26: =IF(EQ25<=ES24,EQ25/ES24,IF(EQ25<=ES24+EU24,1+(EQ25-ES24)/EU24,IF(EQ25<=ES24+EU24+EW24,2+(EQ25-ES24-EU24)/EW24,EQ25*3/(ES24+EU24+EW24)))) -> 4.3206522 | ER26: 2.5 | ES26: =IF(ES25<=EU24,ES25/EU24,IF(ES25<=EU24+EW24,1+(ES25-EU24)/EW24,IF(ES25<=EU24+EW24+EY24,2+(ES25-EU24-EW24)/EY24,ES25*3/(EU24+EW24+EY24)))) -> #REF! | ET26: 2.5 | EU26: =IF(EU25<=EW24,EU25/EW24,IF(EU25<=EW24+EY24,1+(EU25-EW24)/EY24,IF(EU25<=EW24+EY24+FA24,2+(EU25-EW24-EY24)/FA24,EU25*3/(EW24+EY24+FA24)))) -> #REF! | EV26: 2.5 | EW26: =IF(EW25<=EY24,EW25/EY24,IF(EW25<=EY24+FA24,1+(EW25-EY24)/FA24,IF(EW25<=EY24+FA24+FC24,2+(EW25-EY24-FA24)/FC24,EW25*3/(EY24+FA24+FC24)))) -> #REF! | EX26: 2.5 | EY26: =IF(EY25<=FA24,EY25/FA24,IF(EY25<=FA24+FC24,1+(EY25-FA24)/FC24,IF(EY25<=FA24+FC24+FE24,2+(EY25-FA24-FC24)/FE24,EY25*3/(FA24+FC24+FE24)))) -> #REF! | EZ26: 2.5 | FA26: =IF(FA25<=FC24,FA25/FC24,IF(FA25<=FC24+FE24,1+(FA25-FC24)/FE24,IF(FA25<=FC24+FE24+FG24,2+(FA25-FC24-FE24)/FG24,FA25*3/(FC24+FE24+FG24)))) -> #REF! | FB26: 2.5 | FC26: =IF(FC25<=FE24,FC25/FE24,IF(FC25<=FE24+FG24,1+(FC25-FE24)/FG24,IF(FC25<=FE24+FG24+FI24,2+(FC25-FE24-FG24)/FI24,FC25*3/(FE24+FG24+FI24)))) -> #REF! | FD26: 2 | FE26: =IF(FE25<=FG24,FE25/FG24,IF(FE25<=FG24+FI24,1+(FE25-FG24)/FI24,IF(FE25<=FG24+FI24+FK24,2+(FE25-FG24-FI24)/FK24,FE25*3/(FG24+FI24+FK24)))) -> 3.2168373 | FF26: 2 | FG26: =IF(FG25<=FI24,FG25/FI24,IF(FG25<=FI24+FK24,1+(FG25-FI24)/FK24,IF(FG25<=FI24+FK24+FM24,2+(FG25-FI24-FK24)/FM24,FG25*3/(FI24+FK24+FM24)))) -> 2.7440252 | FH26: 2 | FI26: =IF(FI25<=FK24,FI25/FK24,IF(FI25<=FK24+FM24,1+(FI25-FK24)/FM24,IF(FI25<=FK24+FM24+FO24,2+(FI25-FK24-FM24)/FO24,FI25*3/(FK24+FM24+FO24)))) -> 2.8955498 | FJ26: 2 | FK26: =IF(FK25<=FM24,FK25/FM24,IF(FK25<=FM24+FO24,1+(FK25-FM24)/FO24,IF(FK25<=FM24+FO24+FQ24,2+(FK25-FM24-FO24)/FQ24,FK25*3/(FM24+FO24+FQ24)))) -> 2.427104 | FL26: 2 | FM26: =IF(FM25<=FO24,FM25/FO24,IF(FM25<=FO24+FQ24,1+(FM25-FO24)/FQ24,IF(FM25<=FO24+FQ24+FS24,2+(FM25-FO24-FQ24)/FS24,FM25*3/(FO24+FQ24+FS24)))) -> 2.3510779 | FN26: 2 | FO26: =IF(FO25<=FQ24,FO25/FQ24,IF(FO25<=FQ24+FS24,1+(FO25-FQ24)/FS24,IF(FO25<=FQ24+FS24+FU24,2+(FO25-FQ24-FS24)/FU24,FO25*3/(FQ24+FS24+FU24)))) -> 3.2827499 | FP26: 2 | FQ26: =IF(FQ25<=FS24,FQ25/FS24,IF(FQ25<=FS24+FU24,1+(FQ25-FS24)/FU24,IF(FQ25<=FS24+FU24+FW24,2+(FQ25-FS24-FU24)/FW24,FQ25*3/(FS24+FU24+FW24)))) -> 4.9752907 | FR26: 2 | FS26: =IF(FS25<=FU24,FS25/FU24,IF(FS25<=FU24+FW24,1+(FS25-FU24)/FW24,IF(FS25<=FU24+FW24+FY24,2+(FS25-FU24-FW24)/FY24,FS25*3/(FU24+FW24+FY24)))) -> 4.2799532 | FT26: =IF(FT25<=FV24,FT25/FV24,IF(FT25<=FV24+FX24,1+(FT25-FV24)/FX24,IF(FT25<=FV24+FX24+FZ24,2+(FT25-FV24-FX24)/FZ24,FT25*3/(FV24+FX24+FZ24)))) -> 2.9458619 | FU26: =IF(FU25<=FW24,FU25/FW24,IF(FU25<=FW24+FY24,1+(FU25-FW24)/FY24,IF(FU25<=FW24+FY24+GA24,2+(FU25-FW24-FY24)/GA24,FU25*3/(FW24+FY24+GA24)))) -> 3.6459404 | FV26: =IF(FV25<=FX24,FV25/FX24,IF(FV25<=FX24+FZ24,1+(FV25-FX24)/FZ24,IF(FV25<=FX24+FZ24+#REF!,2+(FV25-FX24-FZ24)/#REF!,FV25*3/(FX24+FZ24+#REF!)))) -> #REF! | FW26: =IF(FW25<=FY24,FW25/FY24,IF(FW25<=FY24+GA24,1+(FW25-FY24)/GA24,IF(FW25<=FY24+GA24+GB24,2+(FW25-FY24-GA24)/GB24,FW25*3/(FY24+GA24+GB24)))) -> 3.4805524 | FX26: =IF(FX25<=FZ24,FX25/FZ24,IF(FX25<=FZ24+#REF!,1+(FX25-FZ24)/#REF!,IF(FX25<=FZ24+#REF!+#REF!,2+(FX25-FZ24-#REF!)/#REF!,FX25*3/(FZ24+#REF!+#REF!)))) -> #REF! | FY26: =IF(FY25<=GA24,FY25/GA24,IF(FY25<=GA24+GB24,1+(FY25-GA24)/GB24,IF(FY25<=GA24+GB24+GC24,2+(FY25-GA24-GB24)/GC24,FY25*3/(GA24+GB24+GC24)))) -> 3.5727273 | FZ26: =IF(FZ25<=#REF!,FZ25/#REF!,IF(FZ25<=#REF!+#REF!,1+(FZ25-#REF!)/#REF!,IF(FZ25<=#REF!+#REF!+#REF!,2+(FZ25-#REF!-#REF!)/#REF!,FZ25*3/(#REF!+#REF!+#REF!)))) -> #REF! | GA26: =IF(GA25<=GB24,GA25/GB24,IF(GA25<=GB24+GC24,1+(GA25-GB24)/GC24,IF(GA25<=GB24+GC24+GD24,2+(GA25-GB24-GC24)/GD24,GA25*3/(GB24+GC24+GD24)))) -> 3.0478459 | GB26: =IF(GB25<=GC24,GB25/GC24,IF(GB25<=GC24+GD24,1+(GB25-GC24)/GD24,IF(GB25<=GC24+GD24+GE24,2+(GB25-GC24-GD24)/GE24,GB25*3/(GC24+GD24+GE24)))) -> 2.4886364 | GC26: =IF(GC25<=GD24,GC25/GD24,IF(GC25<=GD24+GE24,1+(GC25-GD24)/GE24,IF(GC25<=GD24+GE24+GF24,2+(GC25-GD24-GE24)/GF24,GC25*3/(GD24+GE24+GF24)))) -> 2.498031 | GD26: =IF(GD25<=GE24,GD25/GE24,IF(GD25<=GE24+GF24,1+(GD25-GE24)/GF24,IF(GD25<=GE24+GF24+GG24,2+(GD25-GE24-GF24)/GG24,GD25*3/(GE24+GF24+GG24)))) -> 2.2506321 | GE26: =IF(GE25<=GF24,GE25/GF24,IF(GE25<=GF24+GG24,1+(GE25-GF24)/GG24,IF(GE25<=GF24+GG24+GH24,2+(GE25-GF24-GG24)/GH24,GE25*3/(GF24+GG24+GH24)))) -> 2.2046154 | GF26: =IF(GF25<=GG24,GF25/GG24,IF(GF25<=GG24+GH24,1+(GF25-GG24)/GH24,IF(GF25<=GG24+GH24+GI24,2+(GF25-GG24-GH24)/GI24,GF25*3/(GG24+GH24+GI24)))) -> 1.7123077 | GG26: =IF(GG25<=GH24,GG25/GH24,IF(GG25<=GH24+GI24,1+(GG25-GH24)/GI24,IF(GG25<=GH24+GI24+GJ24,2+(GG25-GH24-GI24)/GJ24,GG25*3/(GH24+GI24+GJ24)))) -> 1.3686701 | GH26: =IF(GH25<=GI24,GH25/GI24,IF(GH25<=GI24+GJ24,1+(GH25-GI24)/GJ24,IF(GH25<=GI24+GJ24+GK24,2+(GH25-GI24-GJ24)/GK24,GH25*3/(GI24+GJ24+GK24)))) -> 1.7533523 | ... JO26: =IF(JO25<=JP24,JO25/JP24,IF(JO25<=JP24+JQ24,1+(JO25-JP24)/JQ24,IF(JO25<=JP24+JQ24+JR24,2+(JO25-JP24-JQ24)/JR24,JO25*3/(JP24+JQ24+JR24)))) -> #DIV/0!
B27: 4X4(S) | C27: 2 | D27: In | F27: 0.744 | G27: 0.541 | H27: 0.881 | I27: 0.377 | J27: =H28 -> 0.3 | K27: 0.135 | L27: =J28 -> 0.2 | M27: 1.539 | N27: 0.8 | O27: 1.236 | P27: 0.65 | Q27: 2.293 | R27: 0.4 | S27: 1.864 | T27: 0.5 | U27: 0.478 | V27: =T28 -> 0.5 | W27: 0.759 | X27: 0.9 | Y27: 0.911 | Z27: 1 | AA27: 0.81 | AB27: 0.6 | AC27: 0.581 | AD27: 0.3 | AE27: 0.491 | AF27: 0.183 | AG27: 0.118 | AH27: 0.162 | AI27: 0.572 | AJ27: 0.217 | AK27: 1.106 | AL27: 0.346 | AM27: 0.985 | AN27: 0.45 | AO27: 0.828 | AP27: 0.537 | AQ27: 0.324 | AR27: 0.389 | AS27: 0.124 | AT27: 0.411 | AU27: 0.023 | AV27: 0.545 | AW27: 0.536 | AX27: 0.818 | AY27: 0.335 | AZ27: 0.938 | BA27: 0.286 | BB27: 0.806 | BC27: 0.008 | BD27: 0.208 | BE27: 0.103 | BF27: 0.208 | BG27: 0.608 | BH27: 0.32 | BI27: 0.371 | BJ27: 0.368 | BK27: 0.256 | BL27: 0.364 | BM27: 0.238 | BN27: 0.392 | BO27: 0.72 | BP27: 0.336 | BQ27: 0.519 | BR27: 0.376 | BS27: 0.05 | BT27: 0.482 | BU27: 0.262 | BV27: 0.506 | BW27: 0.686 | BX27: 0.542 | BY27: 0.046 | BZ27: 0.458 | CA27: 0.276 | CB27: 0.224 | CC27: 0.031 | CD27: =+CD28 -> 0.196 | CE27: 0.112 | CF27: 0.299 | CG27: 0.327 | CH27: 0.272 | CI27: 0.676 | CJ27: 0.327 | CK27: 0 | CL27: 0.365 | CM27: 0.039 | CN27: 0.30105405 | CO27: 0.167 | CP27: 0.35352812 | CQ27: 1.5 | CR27: 0.38790136 | CS27: 0.765 | CT27: 0.771 | CU27: 0.073 | CV27: 0.784 | CW27: 0.132 | CX27: 0.4681538 | CY27: 0.264 | CZ27: 0.138 | DA27: 0.4 | DB27: 0.134 | DC27: 0.439 | DD27: 0.191 | DE27: 0.852 | DF27: 0.152 | DG27: =[12]PCR!$J$71 -> 1.412 | DH27: 0.155 | DI27: =[13]PCR!$J$73 -> 1.786 | DJ27: 0.207 | DK27: 1.423 | DL27: 0.21 | DM27: 1.033 | DN27: 0.246 | DO27: 0 | DP27: 0.276 | DQ27: 1.628 | DR27: 0.301 | DS27: 0.95 | DT27: 0.353 | DU27: =[14]PCR!$J$88 -> 0.631 | DV27: 0.338 | DW27: =[15]PCR!$J$83 -> 0.024 | DX27: 0.175 | DY27: =[16]PCR!$J$74 -> 0.388 | DZ27: 0.18 | EA27: =[17]PCR!$J$70 -> 0 | EB27: 0.262 | EC27: =[18]PCR!$J$73 -> 0.227 | ED27: 0.273 | EE27: =[19]PCR!$J$72 -> 0.579 | EF27: 0.311 | EG27: =[20]PCR!$J$75 -> 0.478 | EH27: 0.372 | EI27: =[21]PCR!$J$80 -> 0.102 | EJ27: 0.248 | EK27: =[22]PCR!$J$79 -> 0.222 | EL27: 0.29 | EM27: =[23]PCR!$J$93 -> 0.577 | EN27: 0.394 | EO27: =[24]PCR!$J$111 -> 0.648 | EP27: 0.511 | EQ27: =[25]PCR!$J$116 -> 0.488 | ER27: 0.591 | ES27: =[26]PCR!$J$105 -> 0.365 | ET27: 0.544 | EU27: =[27]PCR!$J$101 -> 0.332 | EV27: 0.179 | EW27: =[28]PCR!$J$92 -> 0.123 | EX27: 0.218 | EY27: =[29]PCR!$J$89 -> #REF! | EZ27: 0.249 | FA27: =[30]PCR!$J$88 -> 0.099 | FB27: 0.249 | FC27: 0.588 | FD27: 0.279 | FE27: =[31]PCR!$J$87 -> 0.262 | FF27: 0.331 | FG27: =[32]PCR!$J$87 -> 0.049 | FH27: 0.216 | FI27: =[33]PCR!$J$91 -> 0.156 | FJ27: 0.226 | FK27: =[34]PCR!$J$93 -> 0.293 | FL27: 0.25989446 | FM27: =[35]PCR!$J$103 -> 1.017 | FN27: 0.30986619 | FO27: =[36]PCR!$J$102 -> 0.527 | FP27: 0.315 | FQ27: =[37]PCR!$J$102 -> 0.265 | FR27: 0.305 | FS27: =[38]PCR!$J$93 -> 0.199 | FT27: 0.086 | FU27: =[39]PCR!$J$90 -> 0.013 | FV27: 0.161 | FW27: =[40]PCR!$J$86 -> 0.298 | FX27: 0.347 | FY27: =[41]PCR!$J$88 -> 0.559 | FZ27: 0.231 | GA27: =[42]PCR!$J$86 -> 0.292 | GB27: 0.216 | GC27: 0.049 | GD27: 0.337 | GE27: 0.497 | GF27: 0.522 | GG27: 0.26 | GH27: 0.534 | GI27: 0.55 | GJ27: 0.291 | GK27: 0.098 | GL27: 0.466 | GM27: 0.552 | GN27: 0.292 | GO27: 0.424 | GP27: 0.59 | GQ27: 0.686 | GR27: 0.233 | GS27: 0.544 | GT27: 0.875 | GU27: 0.15 | GV27: 0.025 | GW27: 0.892 | GX27: 0.779 | GY27: 0.286 | GZ27: 0.048 | HA27: 0 | HB27: 0.082 | HC27: 0.019 | HD27: 0.187 | HE27: 0.063 | HF27: 0.052 | HG27: 0.105 | HH27: =[43]PCR!$I$224 -> 0.1 | HI27: =[44]PCR!$I$224 -> 0 | HJ27: 0.692 | HK27: =[45]PCR!$I$224 -> 0.63 | HL27: =[50]PCR!$I$224 -> 0.398 | HM27: 0.053 | HN27: 0.24 | HO27: 0.378 | HP27: 0.034 | HQ27: 0.148 | HR27: 0.098 | HS27: 0.35 | HT27: 0 | HU27: 0.051 | HV27: 0 | HW27: 0.019 | HX27: 0.15 | HY27: =[46]Cate!I224 -> 0.081 | HZ27: 0.198 | IA27: =[47]Cate!I224 -> 0.142 | IB27: =[48]Cate!I224 -> 0.955 | IC27: 0.218 | ID27: =[49]PCR!$I$224 -> 0.1 | IE27: 0.295 | IF27: 0.014 | IG27: 0 | IH27: =[51]PCR!$I$224 -> 0.03 | II27: =[52]PCR!$I$224 -> 0.289 | IJ27: 0.582 | IK27: 0.424 | IL27: 0.127 | IM27: 0.94 | IN27: 0.084 | IO27: 0 | IP27: 0.132 | IQ27: 0.026 | IR27: 0 | IS27: 0 | IT27: 0.008 | IU27: 0 | IV27: 0.015 | IW27: 0.272 | IX27: 0.34 | IY27: 0.075 | IZ27: 0.345 | JA27: 0.14 | JB27: 0 | JC27: 0 | JD27: 0 | JE27: 0.008 | JF27: 0 | JG27: 0.074 | JH27: 0.049
D28: Out | F28: 0.7561 | G28: 0.947 | H28: 0.3 | I28: 0.86 | J28: 0.2 | K28: 0.344 | L28: 0.4 | M28: 0.746 | N28: 0.54 | O28: 0.658 | P28: 0.7 | Q28: 0.64 | R28: 0.8 | S28: 2.237 | T28: 0.5 | U28: 0.447 | V28: 0.3 | W28: 0.892 | X28: 0.6 | Y28: 0.76 | Z28: 0.9 | AA28: 2.451 | AB28: 1 | AC28: 1.428 | AD28: 0.76 | AE28: 0.925 | AF28: 0.183 | AG28: 0.229 | AH28: 0.162 | AI28: 0.294 | AJ28: 0.217 | AK28: 0.672 | AL28: 0.346 | AM28: 0.591 | AN28: 0.45 | AO28: 0.261 | AP28: 0.537 | AQ28: 0.644 | AR28: 0.389 | AS28: 0.761 | AT28: 0.411 | AU28: 0.174 | AV28: 0.545 | AW28: 0.424 | AX28: 0.818 | AY28: 0.281 | AZ28: 0.938 | BA28: 0.475 | BB28: 0.806 | BC28: 0.781 | BD28: 0.208 | BE28: 0.153 | BF28: 0.208 | BG28: 0.205 | BH28: 0.32 | BI28: 0.254 | BJ28: 0.368 | BK28: 0.292 | BL28: 0.364 | BM28: 0.389 | BN28: 0.392 | BO28: 0.312 | BP28: 0.336 | BQ28: 0.286 | BR28: 0.376 | BS28: 0.155 | BT28: 0.482 | BU28: 0.225 | BV28: =+BV27 -> 0.506 | BW28: 0.382 | BX28: =+BX27 -> 0.542 | BY28: 0.544 | BZ28: =+BZ27 -> 0.458 | CA28: 0.7 | CB28: =+CB27 -> 0.224 | CC28: 0.247 | CD28: 0.196 | CE28: 0.062 | CF28: 0.299 | CG28: 0.078 | CH28: 0.272 | CI28: 0.326 | CJ28: 0.327 | CK28: 0.535 | CL28: 0.365 | CM28: 0.38 | CN28: 0.30105405 | CO28: 0.211 | CP28: 0.35352812 | CQ28: 0.236 | CR28: 0.38790136 | CS28: 0.642 | CT28: =+CT27 -> 0.771 | CU28: 0.51 | CV28: =+CV27 -> 0.784 | CW28: 0.844 | CX28: 0.4681538 | CY28: 0.578 | CZ28: 0.138 | DA28: 0.595 | DB28: 0.134 | DC28: 0.442 | DD28: 0.191 | DE28: 0.726 | DF28: 0.152 | DG28: =[12]PCR!$J$72 -> 0.938 | DH28: 0.155 | DI28: =[13]PCR!$J$74 -> 0.814 | DJ28: 0.207 | DK28: 1.317 | DL28: =DL27 -> 0.21 | DM28: 1.202 | DN28: =DN27 -> 0.246 | DO28: 0.581 | DP28: =DP27 -> 0.276 | DQ28: 0.252 | DR28: =DR27 -> 0.301 | DS28: -0.17 | DT28: =DT27 -> 0.353 | DU28: =[14]PCR!$J$89 -> 1.386 | DV28: =DV27 -> 0.338 | DW28: =[15]PCR!$J$84 -> 0.326 | DX28: =DX27 -> 0.175 | DY28: =[16]PCR!$J$75 -> 1.871 | DZ28: =DZ27 -> 0.18 | EA28: =[17]PCR!$J$71 -> 0.476 | EB28: =EB27 -> 0.262 | EC28: =[18]PCR!$J$74 -> 0.133 | ED28: =ED27 -> 0.273 | EE28: =[19]PCR!$J$73 -> 0.177 | EF28: =EF27 -> 0.311 | EG28: =[20]PCR!$J$76 -> 0.499 | EH28: =EH27 -> 0.372 | EI28: =[21]PCR!$J$81 -> 0.282 | EJ28: =EJ27 -> 0.248 | EK28: =[22]PCR!$J$80 -> 0.285 | EL28: =EL27 -> 0.29 | EM28: =[23]PCR!$J$94 -> 0.357 | EN28: =EN27 -> 0.394 | EO28: =[24]PCR!$J$112 -> 0.39 | EP28: =EP27 -> 0.511 | EQ28: =[25]PCR!$J$117 -> 0.403 | ER28: =ER27 -> 0.591 | ES28: =[26]PCR!$J$106 -> 0.517 | ET28: =ET27 -> 0.544 | EU28: =[27]PCR!$J$102 -> 0.546 | EV28: =EV27 -> 0.179 | EW28: =[28]PCR!$J$93 -> 0.414 | EX28: =EX27 -> 0.218 | EY28: =[29]PCR!$J$90 -> #REF! | EZ28: =EZ27 -> 0.249 | FA28: =[30]PCR!$J$89 -> 0.171 | FB28: =FB27 -> 0.249 | FC28: 0.213 | FD28: =FD27 -> 0.279 | FE28: =[31]PCR!$J$88 -> 0.255 | FF28: =FF27 -> 0.331 | FG28: =[32]PCR!$J$88 -> 0.207 | FH28: 0.216 | FI28: =[33]PCR!$J$92 -> 0.429 | FJ28: 0.226 | FK28: =[34]PCR!$J$94 -> 0.42 | FL28: =FL27 -> 0.25989446 | FM28: =[35]PCR!$J$104 -> 0.152 | FN28: 0.30986619 | FO28: =[36]PCR!$J$103 -> 0.519 | FP28: 0.315 | FQ28: =[37]PCR!$J$103 -> 0.501 | FR28: 0.305 | FS28: =[38]PCR!$J$94 -> 0.507 | FT28: 0.264 | FU28: =[39]PCR!$J$91 -> 0.179 | FV28: 0.206 | FW28: =[40]PCR!$J$87 -> 0.176 | FX28: 0.166 | FY28: =[41]PCR!$J$89 -> 0.288 | FZ28: 0.295 | GA28: =[42]PCR!$J$87 -> 0.306 | GB28: 0.236 | GC28: 0.347 | GD28: 0.447 | GE28: 0.233 | GF28: 0.534 | GG28: 0.221 | GH28: 0.628 | GI28: 0.51 | GJ28: 0.208 | GK28: 0.084 | GL28: 0.249 | GM28: 0.34 | GN28: 0.364 | GO28: 0.358 | GP28: 0.478 | GQ28: 0.472 | GR28: 0.413 | GS28: 0.491 | GT28: 0.95 | GU28: 0.262 | GV28: 0.049 | GW28: 0.35 | GX28: 0.195 | GY28: 0.331 | GZ28: 0.235 | HA28: 0.096 | HB28: 0.089 | HC28: 0.055 | HD28: 0.388 | HE28: 0.372 | HF28: 0.529 | HG28: 0.886 | HH28: =[43]PCR!$I$225 -> 0.094 | HI28: =[44]PCR!$I$225 -> 0.492 | HJ28: 0.53 | HK28: =[45]PCR!$J$224 -> 0.087 | HL28: =[50]PCR!$I$225 -> 0.184 | HM28: 0.36 | HN28: 0.253 | HO28: 0.205 | HP28: 0.274 | HQ28: 0.358 | HR28: 0.201 | HS28: 0.164 | HT28: 0.037 | HU28: 0.022 | HV28: 0 | HW28: 0.194 | HX28: 0.088 | HY28: =[46]Cate!J224 -> 0.086 | HZ28: 0.23 | IA28: =[47]Cate!J224 -> 0.196 | IB28: =[48]Cate!J224 -> 0.583 | IC28: 0.358 | ID28: =[49]PCR!$J$224 -> 0.2 | IE28: 0.339 | IF28: 0.294 | IG28: 0.016 | IH28: =[51]PCR!$J$224 -> 0.021 | II28: =[52]PCR!$J$224 -> 0.225 | IJ28: 0.383 | IK28: 0.272 | IL28: 0.06 | IM28: 0.234 | IN28: 0.032 | IO28: 0.165 | IP28: 0.356 | IQ28: 0.432 | IR28: 0.019 | IS28: 0.17 | IT28: 0.042 | IU28: 0.13 | IV28: 0.026 | IW28: 0.142 | IX28: 0.09 | IY28: 0.064 | IZ28: 0.29 | JA28: 0.085 | JB28: 0.036 | JC28: 0.087 | JD28: 0.151 | JE28: 0.044 | JF28: 0.595 | JG28: 0.289 | JH28: 0.118
D29: Inventory | F29: 1.3467 | G29: 1.102 | H29: =F29+H27-H28 -> 1.9277 | I29: =G29+I27-I28 -> 0.619 | J29: =H29+J27-J28 -> 2.0277 | K29: =I29+K27-K28 -> 0.41 | L29: =J29+L27-L28 -> 1.8277 | M29: =K29+M27-M28 -> 1.203 | N29: =L29+N27-N28 -> 2.0877 | O29: =M29+O27-O28 -> 1.781 | ... Z29: =X29+Z27-Z28 -> 2.2377 | AA29: 1.937 | AB29: =Z29+AB27-AB28 -> 1.8377 | AC29: =AA29+AC27-AC28 -> 1.09 | AD29: =AB29+AD27-AD28 -> 1.3777 | AE29: =AC29+AE27-AE28 -> 0.656 | AF29: =AD29+AF27-AF28 -> 1.3777 | AG29: =AE29+AG27-AG28 -> 0.545 | AH29: =AF29+AH27-AH28 -> 1.3777 | AI29: =AG29+AI27-AI28 -> 0.823 | ... AK29: =AI29+AK27-AK28 -> 1.257 | AL29: =N29*1.137 -> 2.3737149 | AM29: =AK29+AM27-AM28 -> 1.651 | AN29: =P29*1.137 -> 2.3168649 | AO29: =AM29+AO27-AO28 -> 2.218 | AP29: =R29*1.137 -> 1.8620649 | AQ29: 1.902 | AR29: =T29*1.137 -> 1.8620649 | AS29: =AQ29+AS27-AS28 -> 1.265 | AT29: =V29*1.137 -> 2.0894649 | AU29: =AS29+AU27-AU28 -> 1.114 | AV29: =X29*1.137 -> 2.4305649 | AW29: =AU29+AW27-AW28 -> 1.226 | AX29: =Z29*1.137 -> 2.5442649 | AY29: =AW29+AY27-AY28 -> 1.28 | AZ29: 2.0894649 | BA29: 1.091 | BB29: 1.5664449 | BC29: 0.318 | BD29: 1.5664449 | BE29: 0.268 | BF29: =BD29+BF27-BF28 -> 1.5664449 | BG29: 0.976 | BH29: =AJ29*1.137 -> 1.5664449 | BI29: =BG29+BI27-BI28 -> 1.093 | BJ29: =AL29*1.137 -> 2.6989138 | BK29: =BI29+BK27-BK28 -> 1.057 | BL29: =AN29*1.137 -> 2.6342754 | BM29: =BK29+BM27-BM28 -> 0.906 | BN29: =AP29*1.137 -> 2.1171678 | BO29: =BM29+BO27-BO28 -> 1.314 | BP29: =AR29*1.137 -> 2.1171678 | BQ29: =BO29+BQ27-BQ28 -> 1.547 | BR29: =AT29*1.137 -> 2.3757216 | BS29: =BQ29+BS27-BS28 -> 1.442 | BT29: =AV29*1.137 -> 2.7635523 | BU29: =BS29+BU27-BU28 -> 1.479 | BV29: =AX29*1.137 -> 2.8928292 | BW29: =BU29+BW27-BW28 -> 1.783 | BX29: =AZ29*1.137 -> 2.3757216 | BY29: =BW29+BY27-BY28 -> 1.285 | BZ29: =BB29*1.137 -> 1.7810479 | CA29: =BY29+CA27-CA28 -> 0.861 | CB29: =BD29*1.137 -> 1.7810479 | CC29: =CA29+CC27-CC28 -> 0.645 | CD29: =BF29*1.137 -> 1.7810479 | CE29: =CC29+CE27-CE28 -> 0.695 | CF29: =BH29*1.137 -> 1.7810479 | CG29: =CE29+CG27-CG28 -> 0.944 | CH29: =BJ29*1.137 -> 3.068665 | CI29: =CG29+CI27-CI28 -> 1.294 | CJ29: =BL29*1.137 -> 2.9951711 | CK29: =CI29+CK27-CK28 -> 0.759 | CL29: =BN29*1.137 -> 2.4072198 | CM29: =CK29+CM27-CM28 -> 0.418 | CN29: =BP29*1.137 -> 2.4072198 | CO29: =CM29+CO27-CO28 -> 0.374 | CP29: =BR29*1.137 -> 2.7011954 | CQ29: =CO29+CQ27-CQ28 -> 1.638 | CR29: =BT29*1.137 -> 3.142159 | CS29: =CQ29+CS27-CS28 -> 1.761 | CT29: =BV29*1.137 -> 3.2891468 | CU29: =CS29+CU27-CU28 -> 1.324 | CV29: =BX29*1.137 -> 2.7011954 | CW29: =CU29+CW27-CW28 -> 0.612 | CX29: =BZ29*1.137 -> 2.0250514 | CY29: =CW29+CY27-CY28 -> 0.298 | CZ29: =CB29*1.137 -> 2.0250514 | DA29: =CY29+DA27-DA28 -> 0.103 | DB29: =CD29*1.137 -> 2.0250514 | DC29: =DA29+DC27-DC28 -> 0.1 | DD29: =CF29*1.137 -> 2.0250514 | DE29: =DC29+DE27-DE28 -> 0.226 | DF29: =CF29*1.137 -> 2.0250514 | DG29: =DE29+DG27-DG28 -> 0.7 | DH29: =CH29*1.137 -> 3.4890721 | DI29: =DG29+DI27-DI28 -> 1.672 | DJ29: =CH29*1.137 -> 3.4890721 | DK29: =DI29+DK27-DK28 -> 1.778 | DL29: =CJ29*1.137 -> 3.4055096 | DM29: =DK29+DM27-DM28 -> 1.609 | DN29: =CL29*1.137 -> 2.7370089 | DO29: =DM29+DO27-DO28 -> 1.028 | DP29: =CN29*1.137 -> 2.7370089 | DQ29: =DO29+DQ27-DQ28 -> 2.404 | DR29: =CP29*1.137 -> 3.0712592 | DS29: =DQ29+DS27-DS28 -> 3.524 | DT29: =CR29*1.137 -> 3.5726347 | DU29: =DS29+DU27-DU28 -> 2.769 | DV29: =CT29*1.137 -> 3.7397599 | DW29: =DU29+DW27-DW28 -> 2.467 | DX29: =CV29*1.137 -> 3.0712592 | DY29: =DW29+DY27-DY28 -> 0.984 | DZ29: =CX29*1.137 -> 2.3024834 | EA29: =DY29+EA27-EA28 -> 0.508 | EB29: =CZ29*1.137 -> 2.3024834 | EC29: =EA29+EC27-EC28 -> 0.602 | ED29: =DB29*1.137 -> 2.3024834 | EE29: =EC29+EE27-EE28 -> 1.004 | EF29: =DD29*1.137 -> 2.3024834 | EG29: =EE29+EG27-EG28 -> 0.983 | EH29: =DF29*1.137 -> 2.3024834 | EI29: =EG29+EI27-EI28 -> 0.803 | EJ29: =DH29*1.137 -> 3.967075 | EK29: =EI29+EK27-EK28 -> 0.74 | EL29: =DJ29*1.137 -> 3.967075 | EM29: =EK29+EM27-EM28 -> 0.96 | EN29: =DL29*1.137 -> 3.8720644 | EO29: 1.218 | EP29: =DN29*1.137 -> 3.1119791 | EQ29: =EO29+EQ27-EQ28 -> 1.303 | ER29: =DP29*1.137 -> 3.1119791 | ES29: =EQ29+ES27-ES28 -> 1.151 | ET29: =DR29*1.137 -> 3.4920217 | EU29: =ES29+EU27-EU28 -> 0.937 | EV29: =DT29*1.137 -> 4.0620857 | EW29: =EU29+EW27-EW28 -> 0.646 | EX29: =DV29*1.137 -> 4.252107 | EY29: =EW29+EY27-EY28 -> #REF! | EZ29: =DX29*1.137 -> 3.4920217 | FA29: =EY29+FA27-FA28 -> #REF! | FB29: =DZ29*1.137 -> 2.6179237 | FC29: =FA29+FC27-FC28 -> #REF! | FD29: =EB29*1.137 -> 2.6179237 | FE29: 0.974 | FF29: =ED29*1.137 -> 2.6179237 | FG29: =FE29+FG27-FG28 -> 0.816 | FH29: =EF29*1.137 -> 2.6179237 | FI29: =FG29+FI27-FI28 -> 0.543 | FJ29: =EH29*1.137 -> 2.6179237 | FK29: =FI29+FK27-FK28 -> 0.416 | FL29: =EJ29*1.137 -> 4.5105643 | FM29: =FK29+FM27-FM28 -> 1.281 | FN29: =EL29*1.137 -> 4.5105643 | FO29: =FM29+FO27-FO28 -> 1.289 | FP29: =EN29*1.137 -> 4.4025372 | FQ29: =FO29+FQ27-FQ28 -> 1.053 | FR29: 0.86 | FS29: =FQ29+FS27-FS28 -> 0.745 | FT29: =FR29+FT27-FT28 -> 0.682 | FU29: =FS29+FU27-FU28 -> 0.579 | FV29: =FT29+FV27-FV28 -> 0.637 | FW29: =FU29+FW27-FW28 -> 0.701 | FX29: =FV29+FX27-FX28 -> 0.818 | FY29: =FW29+FY27-FY28 -> 0.972 | FZ29: 0.908 | GA29: =FY29+GA27-GA28 -> 0.958 | GB29: =GA29+GB27-GB28 -> 0.938 | GC29: =GB29+GC27-GC28 -> 0.64 | GD29: =GC29+GD27-GD28 -> 0.53 | GE29: =GD29+GE27-GE28 -> 0.794 | GF29: =GE29+GF27-GF28 -> 0.782 | GG29: =GF29+GG27-GG28 -> 0.821 | GH29: =GG29+GH27-GH28 -> 0.727 | GI29: =GH29+GI27-GI28 -> 0.767 | ... HB29: =HA29+HB27-HB28 -> 2.066 | HC29: 2.997 | HD29: =HC29+HD27-HD28 -> 2.796 | HE29: =HD29+HE27-HE28 -> 2.487 | HF29: =HE29+HF27-HF28 -> 2.01 | HG29: =HF29+HG27-HG28 -> 1.229 | HH29: =HG29+HH27-HH28 -> 1.235 | HI29: =HH29+HI27-HI28 -> 0.743 | HJ29: =HI29+HJ27-HJ28 -> 0.905 | HK29: =HJ29+HK27-HK28 -> 1.448 | ... HU29: =HT29+HU27-HU28 -> 1.14 | HV29: 1.157 | HW29: =HV29+HW27-HW28 -> 0.982 | HX29: =HW29+HX27-HX28 -> 1.044 | HY29: =HX29+HY27-HY28 -> 1.039 | HZ29: =HY29+HZ27-HZ28 -> 1.007 | IA29: =HZ29+IA27-IA28 -> 0.953 | IB29: =IA29+IB27-IB28 -> 1.325 | IC29: =IB29+IC27-IC28 -> 1.185 | ID29: =IC29+ID27-ID28 -> 1.085 | ... IL29: =IK29+IL27-IL28 -> 1.236 | IM29: 1.942 | IN29: =IM29+IN27-IN28 -> 1.994 | IO29: =IN29+IO27-IO28 -> 1.829 | IP29: =IO29+IP27-IP28 -> 1.605 | IQ29: =IP29+IQ27-IQ28 -> 1.199 | IR29: =IQ29+IR27-IR28 -> 1.18 | IS29: =IR29+IS27-IS28 -> 1.01 | IT29: =IS29+IT27-IT28 -> 0.976 | IU29: =IT29+IU27-IU28 -> 0.846 | ... JO29: =JN29+JO27-JO28 -> 0.147
D30: month | E30: 1.6 | F30: 1.8890889 | G30: 3.6733333 | H30: =IF(H29<=J28,H29/J28,IF(H29<=J28+L28,1+(H29-J28)/L28,IF(H29<=J28+L28+N28,2+(H29-J28-L28)/N28,H29*3/(J28+L28+N28)))) -> 5.0728947 | I30: =IF(I29<=K28,I29/K28,IF(I29<=K28+M28,1+(I29-K28)/M28,IF(I29<=K28+M28+O28,2+(I29-K28-M28)/O28,I29*3/(K28+M28+O28)))) -> 1.3686327 | J30: =IF(J29<=L28,J29/L28,IF(J29<=L28+N28,1+(J29-L28)/N28,IF(J29<=L28+N28+P28,2+(J29-L28-N28)/P28,J29*3/(L28+N28+P28)))) -> 3.7092073 | K30: =IF(K29<=M28,K29/M28,IF(K29<=M28+O28,1+(K29-M28)/O28,IF(K29<=M28+O28+Q28,2+(K29-M28-O28)/Q28,K29*3/(M28+O28+Q28)))) -> 0.54959786 | L30: =IF(L29<=N28,L29/N28,IF(L29<=N28+P28,1+(L29-N28)/P28,IF(L29<=N28+P28+R28,2+(L29-N28-P28)/R28,L29*3/(N28+P28+R28)))) -> 2.734625 | M30: =IF(M29<=O28,M29/O28,IF(M29<=O28+Q28,1+(M29-O28)/Q28,IF(M29<=O28+Q28+S28,2+(M29-O28-Q28)/S28,M29*3/(O28+Q28+S28)))) -> 1.8515625 | N30: =IF(N29<=P28,N29/P28,IF(N29<=P28+R28,1+(N29-P28)/R28,IF(N29<=P28+R28+T28,2+(N29-P28-R28)/T28,N29*3/(P28+R28+T28)))) -> 3.13155 | O30: =IF(O29<=Q28,O29/Q28,IF(O29<=Q28+S28,1+(O29-Q28)/S28,IF(O29<=Q28+S28+U28,2+(O29-Q28-S28)/U28,O29*3/(Q28+S28+U28)))) -> 1.5100581 | ... CI30: =IF(CI29<=CK28,CI29/CK28,IF(CI29<=CK28+CM28,1+(CI29-CK28)/CM28,IF(CI29<=CK28+CM28+CO28,2+(CI29-CK28-CM28)/CO28,CI29*3/(CK28+CM28+CO28)))) -> 3.4476021 | CJ30: =IF(CJ29<=CL28,CJ29/CL28,IF(CJ29<=CL28+CN28,1+(CJ29-CL28)/CN28,IF(CJ29<=CL28+CN28+#REF!,2+(CJ29-CL28-CN28)/#REF!,CJ29*3/(CL28+CN28+#REF!)))) -> #REF! | CK30: =IF(CK29<=CM28,CK29/CM28,IF(CK29<=CM28+CO28,1+(CK29-CM28)/CO28,IF(CK29<=CM28+CO28+CQ28,2+(CK29-CM28-CO28)/CQ28,CK29*3/(CM28+CO28+CQ28)))) -> 2.7118644 | CL30: =IF(CL29<=CN28,CL29/CN28,IF(CL29<=CN28+CP28,1+(CL29-CN28)/CP28,IF(CL29<=CN28+CP28+#REF!,2+(CL29-CN28-CP28)/#REF!,CL29*3/(CN28+CP28+#REF!)))) -> #REF! | CM30: =IF(CM29<=CO28,CM29/CO28,IF(CM29<=CO28+CQ28,1+(CM29-CO28)/CQ28,IF(CM29<=CO28+CQ28+CS28,2+(CM29-CO28-CQ28)/CS28,CM29*3/(CO28+CQ28+CS28)))) -> 1.8771186 | CN30: =IF(CN29<=CP28,CN29/CP28,IF(CN29<=CP28+CR28,1+(CN29-CP28)/CR28,IF(CN29<=CP28+CR28+#REF!,2+(CN29-CP28-CR28)/#REF!,CN29*3/(CP28+CR28+#REF!)))) -> #REF! | CO30: =IF(CO29<=CQ28,CO29/CQ28,IF(CO29<=CQ28+CS28,1+(CO29-CQ28)/CS28,IF(CO29<=CQ28+CS28+CU28,2+(CO29-CQ28-CS28)/CU28,CO29*3/(CQ28+CS28+CU28)))) -> 1.2149533 | CP30: =IF(CP29<=CR28,CP29/CR28,IF(CP29<=CR28+CT28,1+(CP29-CR28)/CT28,IF(CP29<=CR28+CT28+#REF!,2+(CP29-CR28-CT28)/#REF!,CP29*3/(CR28+CT28+#REF!)))) -> #REF! | CQ30: =IF(CQ29<=CS28,CQ29/CS28,IF(CQ29<=CS28+CU28,1+(CQ29-CS28)/CU28,IF(CQ29<=CS28+CU28+CW28,2+(CQ29-CS28-CU28)/CW28,CQ29*3/(CS28+CU28+CW28)))) -> 2.5758294 | CR30: =IF(CR29<=CT28,CR29/CT28,IF(CR29<=CT28+CV28,1+(CR29-CT28)/CV28,IF(CR29<=CT28+CV28+#REF!,2+(CR29-CT28-CV28)/#REF!,CR29*3/(CT28+CV28+#REF!)))) -> #REF! | CS30: =IF(CS29<=CU28,CS29/CU28,IF(CS29<=CU28+CW28,1+(CS29-CU28)/CW28,IF(CS29<=CU28+CW28+CY28,2+(CS29-CU28-CW28)/CY28,CS29*3/(CU28+CW28+CY28)))) -> 2.7041522 | CT30: =IF(CT29<=CV28,CT29/CV28,IF(CT29<=CV28+CZ28,1+(CT29-CV28)/CZ28,IF(CT29<=CV28+CZ28+#REF!,2+(CT29-CV28-CZ28)/#REF!,CT29*3/(CV28+CZ28+#REF!)))) -> #REF! | CU30: =IF(CU29<=CW28,CU29/CW28,IF(CU29<=CW28+CY28,1+(CU29-CW28)/CY28,IF(CU29<=CW28+CY28+DA28,2+(CU29-CW28-CY28)/DA28,CU29*3/(CW28+CY28+DA28)))) -> 1.8304498 | CV30: =IF(CV29<=CX28,CV29/CX28,IF(CV29<=CX28+#REF!,1+(CV29-CX28)/#REF!,IF(CV29<=CX28+#REF!+#REF!,2+(CV29-CX28-#REF!)/#REF!,CV29*3/(CX28+#REF!+#REF!)))) -> #REF! | CW30: =IF(CW29<=CY28,CW29/CY28,IF(CW29<=CY28+DA28,1+(CW29-CY28)/DA28,IF(CW29<=CY28+DA28+DC28,2+(CW29-CY28-DA28)/DC28,CW29*3/(CY28+DA28+DC28)))) -> 1.0571429 | CX30: =IF(CX29<=CZ28,CX29/CZ28,IF(CX29<=CZ28+#REF!,1+(CX29-CZ28)/#REF!,IF(CX29<=CZ28+#REF!+#REF!,2+(CX29-CZ28-#REF!)/#REF!,CX29*3/(CZ28+#REF!+#REF!)))) -> #REF! | CY30: =IF(CY29<=DA28,CY29/DA28,IF(CY29<=DA28+DC28,1+(CY29-DA28)/DC28,IF(CY29<=DA28+DC28+DE28,2+(CY29-DA28-DC28)/DE28,CY29*3/(DA28+DC28+DE28)))) -> 0.50084034 | CZ30: =CB30*1.137 -> 7.9206704 | DA30: =IF(DA29<=DC28,DA29/DC28,IF(DA29<=DC28+DE28,1+(DA29-DC28)/DE28,IF(DA29<=DC28+DE28+DG28,2+(DA29-DC28-DE28)/DG28,DA29*3/(DC28+DE28+DG28)))) -> 0.23303167 | DB30: =CD30*1.137 -> 6.7652051 | DC30: =IF(DC29<=DE28,DC29/DE28,IF(DC29<=DE28+DG28,1+(DC29-DE28)/DG28,IF(DC29<=DE28+DG28+DI28,2+(DC29-DE28-DG28)/DI28,DC29*3/(DE28+DG28+DI28)))) -> 0.13774105 | DD30: =CF30*1.137 -> 6.3020272 | DE30: =IF(DE29<=DG28,DE29/DG28,IF(DE29<=DG28+DI28,1+(DE29-DG28)/DI28,IF(DE29<=DG28+DI28+DK28,2+(DE29-DG28-DI28)/DK28,DE29*3/(DG28+DI28+DK28)))) -> 0.24093817 | DF30: =CH30*1.137 -> 10.54043 | DG30: =IF(DG29<=DI28,DG29/DI28,IF(DG29<=DI28+DK28,1+(DG29-DI28)/DK28,IF(DG29<=DI28+DK28+DM28,2+(DG29-DI28-DK28)/DM28,DG29*3/(DI28+DK28+DM28)))) -> 0.85995086 | DH30: =CJ30*1.137 -> #REF! | DI30: =IF(DI29<=DK28,DI29/DK28,IF(DI29<=DK28+DM28,1+(DI29-DK28)/DM28,IF(DI29<=DK28+DM28+DO28,2+(DI29-DK28-DM28)/DO28,DI29*3/(DK28+DM28+DO28)))) -> 1.2953411 | DJ30: 1.5 | DK30: =IF(DK29<=DM28,DK29/DM28,IF(DK29<=DM28+DO28,1+(DK29-DM28)/DO28,IF(DK29<=DM28+DO28+DQ28,2+(DK29-DM28-DO28)/DQ28,DK29*3/(DM28+DO28+DQ28)))) -> 1.9913941 | DL30: 1.5 | DM30: =IF(DM29<=DO28,DM29/DO28,IF(DM29<=DO28+DQ28,1+(DM29-DO28)/DQ28,IF(DM29<=DO28+DQ28+DS28,2+(DM29-DO28-DQ28)/DS28,DM29*3/(DO28+DQ28+DS28)))) -> 7.280543 | DN30: 1.5 | DO30: =IF(DO29<=DQ28,DO29/DQ28,IF(DO29<=DQ28+DS28,1+(DO29-DQ28)/DS28,IF(DO29<=DQ28+DS28+DU28,2+(DO29-DQ28-DS28)/DU28,DO29*3/(DQ28+DS28+DU28)))) -> 2.6825397 | DP30: 1.5 | DQ30: =IF(DQ29<=DS28,DQ29/DS28,IF(DQ29<=DS28+DU28,1+(DQ29-DS28)/DU28,IF(DQ29<=DS28+DU28+DW28,2+(DQ29-DS28-DU28)/DW28,DQ29*3/(DS28+DU28+DW28)))) -> 4.6770428 | DR30: 1.5 | DS30: =IF(DS29<=DU28,DS29/DU28,IF(DS29<=DU28+DW28,1+(DS29-DU28)/DW28,IF(DS29<=DU28+DW28+DY28,2+(DS29-DU28-DW28)/DY28,DS29*3/(DU28+DW28+DY28)))) -> 2.9684661 | DT30: 1.5 | DU30: =IF(DU29<=DW28,DU29/DW28,IF(DU29<=DW28+DY28,1+(DU29-DW28)/DY28,IF(DU29<=DW28+DY28+EA28,2+(DU29-DW28-DY28)/EA28,DU29*3/(DW28+DY28+EA28)))) -> 3.1077441 | DV30: 1.5 | DW30: =IF(DW29<=DY28,DW29/DY28,IF(DW29<=DY28+EA28,1+(DW29-DY28)/EA28,IF(DW29<=DY28+EA28+EC28,2+(DW29-DY28-EA28)/EC28,DW29*3/(DY28+EA28+EC28)))) -> 2.9022556 | DX30: 1.5 | DY30: =IF(DY29<=EA28,DY29/EA28,IF(DY29<=EA28+EC28,1+(DY29-EA28)/EC28,IF(DY29<=EA28+EC28+EE28,2+(DY29-EA28-EC28)/EE28,DY29*3/(EA28+EC28+EE28)))) -> 3.7557252 | DZ30: 1.5 | EA30: =IF(EA29<=EC28,EA29/EC28,IF(EA29<=EC28+EE28,1+(EA29-EC28)/EE28,IF(EA29<=EC28+EE28+EG28,2+(EA29-EC28-EE28)/EG28,EA29*3/(EC28+EE28+EG28)))) -> 2.3967936 | EB30: 1.5 | EC30: =IF(EC29<=EE28,EC29/EE28,IF(EC29<=EE28+EG28,1+(EC29-EE28)/EG28,IF(EC29<=EE28+EG28+EI28,2+(EC29-EE28-EG28)/EI28,EC29*3/(EE28+EG28+EI28)))) -> 1.8517034 | ED30: 1.5 | EE30: =IF(EE29<=EG28,EE29/EG28,IF(EE29<=EG28+EI28,1+(EE29-EG28)/EI28,IF(EE29<=EG28+EI28+EK28,2+(EE29-EG28-EI28)/EK28,EE29*3/(EG28+EI28+EK28)))) -> 2.7824561 | EF30: 1.5 | EG30: =IF(EG29<=EI28,EG29/EI28,IF(EG29<=EI28+EK28,1+(EG29-EI28)/EK28,IF(EG29<=EI28+EK28+EM28,2+(EG29-EI28-EK28)/EM28,EG29*3/(EI28+EK28+EM28)))) -> 3.1915584 | EH30: 1.5 | EI30: =IF(EI29<=EK28,EI29/EK28,IF(EI29<=EK28+EM28,1+(EI29-EK28)/EM28,IF(EI29<=EK28+EM28+EO28,2+(EI29-EK28-EM28)/EO28,EI29*3/(EK28+EM28+EO28)))) -> 2.4128205 | EJ30: 2.5 | EK30: =IF(EK29<=EM28,EK29/EM28,IF(EK29<=EM28+EO28,1+(EK29-EM28)/EO28,IF(EK29<=EM28+EO28+EQ28,2+(EK29-EM28-EO28)/EQ28,EK29*3/(EM28+EO28+EQ28)))) -> 1.9820513 | EL30: 2.5 | EM30: =IF(EM29<=EO28,EM29/EO28,IF(EM29<=EO28+EQ28,1+(EM29-EO28)/EQ28,IF(EM29<=EO28+EQ28+ES28,2+(EM29-EO28-EQ28)/ES28,EM29*3/(EO28+EQ28+ES28)))) -> 2.3230174 | EN30: 2.5 | EO30: =IF(EO29<=EQ28,EO29/EQ28,IF(EO29<=EQ28+ES28,1+(EO29-EQ28)/ES28,IF(EO29<=EQ28+ES28+EU28,2+(EO29-EQ28-ES28)/EU28,EO29*3/(EQ28+ES28+EU28)))) -> 2.5457875 | EP30: 2.5 | EQ30: =IF(EQ29<=ES28,EQ29/ES28,IF(EQ29<=ES28+EU28,1+(EQ29-ES28)/EU28,IF(EQ29<=ES28+EU28+EW28,2+(EQ29-ES28-EU28)/EW28,EQ29*3/(ES28+EU28+EW28)))) -> 2.5797101 | ER30: 2.5 | ES30: =IF(ES29<=EU28,ES29/EU28,IF(ES29<=EU28+EW28,1+(ES29-EU28)/EW28,IF(ES29<=EU28+EW28+EY28,2+(ES29-EU28-EW28)/EY28,ES29*3/(EU28+EW28+EY28)))) -> #REF! | ET30: 2.5 | EU30: =IF(EU29<=EW28,EU29/EW28,IF(EU29<=EW28+EY28,1+(EU29-EW28)/EY28,IF(EU29<=EW28+EY28+FA28,2+(EU29-EW28-EY28)/FA28,EU29*3/(EW28+EY28+FA28)))) -> #REF! | EV30: 2.5 | EW30: =IF(EW29<=EY28,EW29/EY28,IF(EW29<=EY28+FA28,1+(EW29-EY28)/FA28,IF(EW29<=EY28+FA28+FC28,2+(EW29-EY28-FA28)/FC28,EW29*3/(EY28+FA28+FC28)))) -> #REF! | EX30: 2.5 | EY30: =IF(EY29<=FA28,EY29/FA28,IF(EY29<=FA28+FC28,1+(EY29-FA28)/FC28,IF(EY29<=FA28+FC28+FE28,2+(EY29-FA28-FC28)/FE28,EY29*3/(FA28+FC28+FE28)))) -> #REF! | EZ30: 2.5 | FA30: =IF(FA29<=FC28,FA29/FC28,IF(FA29<=FC28+FE28,1+(FA29-FC28)/FE28,IF(FA29<=FC28+FE28+FG28,2+(FA29-FC28-FE28)/FG28,FA29*3/(FC28+FE28+FG28)))) -> #REF! | FB30: 2.5 | FC30: =IF(FC29<=FE28,FC29/FE28,IF(FC29<=FE28+FG28,1+(FC29-FE28)/FG28,IF(FC29<=FE28+FG28+FI28,2+(FC29-FE28-FG28)/FI28,FC29*3/(FE28+FG28+FI28)))) -> #REF! | FD30: 2 | FE30: =IF(FE29<=FG28,FE29/FG28,IF(FE29<=FG28+FI28,1+(FE29-FG28)/FI28,IF(FE29<=FG28+FI28+FK28,2+(FE29-FG28-FI28)/FK28,FE29*3/(FG28+FI28+FK28)))) -> 2.8047619 | FF30: 2 | FG30: =IF(FG29<=FI28,FG29/FI28,IF(FG29<=FI28+FK28,1+(FG29-FI28)/FK28,IF(FG29<=FI28+FK28+FM28,2+(FG29-FI28-FK28)/FM28,FG29*3/(FI28+FK28+FM28)))) -> 1.9214286 | FH30: 2 | FI30: =IF(FI29<=FK28,FI29/FK28,IF(FI29<=FK28+FM28,1+(FI29-FK28)/FM28,IF(FI29<=FK28+FM28+FO28,2+(FI29-FK28-FM28)/FO28,FI29*3/(FK28+FM28+FO28)))) -> 1.8092105 | FJ30: 2 | FK30: =IF(FK29<=FM28,FK29/FM28,IF(FK29<=FM28+FO28,1+(FK29-FM28)/FO28,IF(FK29<=FM28+FO28+FQ28,2+(FK29-FM28-FO28)/FQ28,FK29*3/(FM28+FO28+FQ28)))) -> 1.5086705 | FL30: 2 | FM30: =IF(FM29<=FO28,FM29/FO28,IF(FM29<=FO28+FQ28,1+(FM29-FO28)/FQ28,IF(FM29<=FO28+FQ28+FS28,2+(FM29-FO28-FQ28)/FS28,FM29*3/(FO28+FQ28+FS28)))) -> 2.5147929 | FN30: 2 | FO30: =IF(FO29<=FQ28,FO29/FQ28,IF(FO29<=FQ28+FS28,1+(FO29-FQ28)/FS28,IF(FO29<=FQ28+FS28+FU28,2+(FO29-FQ28-FS28)/FU28,FO29*3/(FQ28+FS28+FU28)))) -> 3.2577928 | FP30: 2 | FQ30: =IF(FQ29<=FS28,FQ29/FS28,IF(FQ29<=FS28+FU28,1+(FQ29-FS28)/FU28,IF(FQ29<=FS28+FU28+FW28,2+(FQ29-FS28-FU28)/FW28,FQ29*3/(FS28+FU28+FW28)))) -> 3.6647332 | FR30: 2 | FS30: =IF(FS29<=FU28,FS29/FU28,IF(FS29<=FU28+FW28,1+(FS29-FU28)/FW28,IF(FS29<=FU28+FW28+FY28,2+(FS29-FU28-FW28)/FY28,FS29*3/(FU28+FW28+FY28)))) -> 3.4758942 | FT30: =IF(FT29<=FV28,FT29/FV28,IF(FT29<=FV28+FX28,1+(FT29-FV28)/FX28,IF(FT29<=FV28+FX28+FZ28,2+(FT29-FV28-FX28)/FZ28,FT29*3/(FV28+FX28+FZ28)))) -> 3.0674663 | FU30: =IF(FU29<=FW28,FU29/FW28,IF(FU29<=FW28+FY28,1+(FU29-FW28)/FY28,IF(FU29<=FW28+FY28+GA28,2+(FU29-FW28-FY28)/GA28,FU29*3/(FW28+FY28+GA28)))) -> 2.375817 | FV30: =IF(FV29<=FX28,FV29/FX28,IF(FV29<=FX28+FZ28,1+(FV29-FX28)/FZ28,IF(FV29<=FX28+FZ28+#REF!,2+(FV29-FX28-FZ28)/#REF!,FV29*3/(FX28+FZ28+#REF!)))) -> #REF! | FW30: =IF(FW29<=FY28,FW29/FY28,IF(FW29<=FY28+GA28,1+(FW29-FY28)/GA28,IF(FW29<=FY28+GA28+GB28,2+(FW29-FY28-GA28)/GB28,FW29*3/(FY28+GA28+GB28)))) -> 2.4533898 | FX30: =IF(FX29<=FZ28,FX29/FZ28,IF(FX29<=FZ28+#REF!,1+(FX29-FZ28)/#REF!,IF(FX29<=FZ28+#REF!+#REF!,2+(FX29-FZ28-#REF!)/#REF!,FX29*3/(FZ28+#REF!+#REF!)))) -> #REF! | FY30: =IF(FY29<=GA28,FY29/GA28,IF(FY29<=GA28+GB28,1+(FY29-GA28)/GB28,IF(FY29<=GA28+GB28+GC28,2+(FY29-GA28-GB28)/GC28,FY29*3/(GA28+GB28+GC28)))) -> 3.28009 | FZ30: =IF(FZ29<=#REF!,FZ29/#REF!,IF(FZ29<=#REF!+#REF!,1+(FZ29-#REF!)/#REF!,IF(FZ29<=#REF!+#REF!+#REF!,2+(FZ29-#REF!-#REF!)/#REF!,FZ29*3/(#REF!+#REF!+#REF!)))) -> #REF! | GA30: =IF(GA29<=GB28,GA29/GB28,IF(GA29<=GB28+GC28,1+(GA29-GB28)/GC28,IF(GA29<=GB28+GC28+GD28,2+(GA29-GB28-GC28)/GD28,GA29*3/(GB28+GC28+GD28)))) -> 2.8389262 | GB30: =IF(GB29<=GC28,GB29/GC28,IF(GB29<=GC28+GD28,1+(GB29-GC28)/GD28,IF(GB29<=GC28+GD28+GE28,2+(GB29-GC28-GD28)/GE28,GB29*3/(GC28+GD28+GE28)))) -> 2.6180258 | GC30: =IF(GC29<=GD28,GC29/GD28,IF(GC29<=GD28+GE28,1+(GC29-GD28)/GE28,IF(GC29<=GD28+GE28+GF28,2+(GC29-GD28-GE28)/GF28,GC29*3/(GD28+GE28+GF28)))) -> 1.8283262 | GD30: =IF(GD29<=GE28,GD29/GE28,IF(GD29<=GE28+GF28,1+(GD29-GE28)/GF28,IF(GD29<=GE28+GF28+GG28,2+(GD29-GE28-GF28)/GG28,GD29*3/(GE28+GF28+GG28)))) -> 1.5561798 | GE30: =IF(GE29<=GF28,GE29/GF28,IF(GE29<=GF28+GG28,1+(GE29-GF28)/GG28,IF(GE29<=GF28+GG28+GH28,2+(GE29-GF28-GG28)/GH28,GE29*3/(GF28+GG28+GH28)))) -> 2.0621019 | GF30: =IF(GF29<=GG28,GF29/GG28,IF(GF29<=GG28+GH28,1+(GF29-GG28)/GH28,IF(GF29<=GG28+GH28+GI28,2+(GF29-GG28-GH28)/GI28,GF29*3/(GG28+GH28+GI28)))) -> 1.8933121 | GG30: =IF(GG29<=GH28,GG29/GH28,IF(GG29<=GH28+GI28,1+(GG29-GH28)/GI28,IF(GG29<=GH28+GI28+GJ28,2+(GG29-GH28-GI28)/GJ28,GG29*3/(GH28+GI28+GJ28)))) -> 1.3784314 | GH30: =IF(GH29<=GI28,GH29/GI28,IF(GH29<=GI28+GJ28,1+(GH29-GI28)/GJ28,IF(GH29<=GI28+GJ28+GK28,2+(GH29-GI28-GJ28)/GK28,GH29*3/(GI28+GJ28+GK28)))) -> 2.1071429 | ... JO30: =IF(JO29<=JP28,JO29/JP28,IF(JO29<=JP28+JQ28,1+(JO29-JP28)/JQ28,IF(JO29<=JP28+JQ28+JR28,2+(JO29-JP28-JQ28)/JR28,JO29*3/(JP28+JQ28+JR28)))) -> #DIV/0!
B31: 16" | C31: 1.5 | D31: In | F31: 1.89 | G31: 0.858 | H31: 0.654 | I31: 0.224 | J31: =H32 -> 1 | K31: 0.365 | L31: 2 | M31: 1.187 | N31: 2.2 | O31: 1.236 | P31: 2.3 | Q31: 5.152 | R31: 1.5 | S31: 1.815 | T31: 1.6 | U31: 2.611 | V31: 2.4 | W31: 3.806 | X31: 2.8 | Y31: 1.622 | Z31: 2.5 | AA31: 1.313 | AB31: 1.5 | AC31: 0.937 | AD31: 1 | AE31: 0.142 | AF31: 0.812 | AG31: 0.158 | AH31: 0.731 | AI31: 0.976 | AJ31: 1.252 | AK31: 1.265 | AL31: 1.736 | AM31: 3.772 | AN31: 2.123 | AO31: 1.314 | AP31: 2.447 | AQ31: 1.38 | AR31: 1.667 | AS31: 3.808 | AT31: 1.603 | AU31: 1.282 | AV31: 2.469 | AW31: 4.054 | AX31: 2.439 | AY31: 2.37 | AZ31: 2.63 | BA31: 3.11 | BB31: 2.692 | BC31: 1.126 | BD31: 1.212 | BE31: 1.137 | BF31: 1.442 | BG31: 0.324 | BH31: 1.91 | BI31: 3.852 | BJ31: 1.758 | BK31: 2.226 | BL31: 1.804 | BM31: 0.799 | BN31: 2.206 | BO31: 1.278 | BP31: 2.265 | BQ31: 2.795 | BR31: 2.249 | BS31: 1.524 | BT31: 2.296 | BU31: 2.928 | BV31: 3.22 | BW31: 2.481 | BX31: 3.21 | BY31: 1.172 | BZ31: 3.249 | CA31: 1.5 | CB31: 1.983 | CC31: 1.317 | CD31: =+CD32 -> 1.743 | CE31: 2.497 | CF31: 2.64 | CG31: 2.254 | CH31: 2.405 | CI31: 0.754 | CJ31: 2.878 | CK31: 0.875 | CL31: 3.23 | CM31: 2.326 | CN31: 2.8176629 | CO31: 3.218 | CP31: 3.283 | CQ31: 6.539 | CR31: 3.5872236 | CS31: 1.796 | CT31: 4.449 | CU31: 2.925 | CV31: 4.888 | CW31: 2.526 | CX31: 4.3483466 | CY31: 0.762 | CZ31: 1.306 | DA31: 1.603 | DB31: 1.289 | DC31: 0.516 | DD31: 1.8232 | DE31: 1.412 | DF31: 2.42 | DG31: =[12]PCR!$J$172 -> 2.05 | DH31: 2.576 | DI31: =[13]PCR!$J$171 -> 2.96 | DJ31: 3.446 | DK31: 3.341 | DL31: 2.679 | DM31: 2.297 | DN31: 3.14 | DO31: 0.768 | DP31: 3.528 | DQ31: 5.861 | DR31: 3.843 | DS31: 17.291 | DT31: 4.51 | DU31: =[14]PCR!$J$226 -> 1.511 | DV31: 4.316 | DW31: =[15]PCR!$J$227 -> 4.146 | DX31: 2.391 | DY31: =[16]PCR!$J$195 -> 3.224 | DZ31: 2.447 | EA31: =[17]PCR!$J$180 -> 0.793 | EB31: 3.581 | EC31: =[18]PCR!$J$182 -> 0.471 | ED31: 3.713 | EE31: =[19]PCR!$J$181 -> 0.385 | EF31: 4.232 | EG31: =[20]PCR!$J$183 -> 1.424 | EH31: 4.852 | EI31: =[21]PCR!$J$199 -> 0.994 | EJ31: 2.678 | EK31: =[22]PCR!$J$206 -> 1.905 | EL31: 3.087 | EM31: =[23]PCR!$J$230 -> 4.46 | EN31: 5.087 | EO31: =[24]PCR!$J$252 -> 2.726 | EP31: 7.11 | EQ31: =[25]PCR!$J$258 -> 1.402 | ER31: 7.646 | ES31: =[26]PCR!$J$231 -> 1.141 | ET31: 6.448 | EU31: =[27]PCR!$J$216 -> 1.064 | EV31: 1.206 | EW31: =[28]PCR!$J$191 -> 0.12 | EX31: 1.525 | EY31: =[29]PCR!$J$195 -> #REF! | EZ31: 1.799 | FA31: =[30]PCR!$J$196 -> 1.793 | FB31: 2.18 | FC31: 2.753 | FD31: 2.443 | FE31: =[31]PCR!$J$184 -> 0.987 | FF31: 2.867 | FG31: =[32]PCR!$J$192 -> 3.508 | FH31: 2.8499062 | FI31: =[33]PCR!$J$203 -> 3.521 | FJ31: 2.8740415 | FK31: =[34]PCR!$J$202 -> 2.994 | FL31: 5.2650475 | FM31: =[35]PCR!$J$212 -> 3.885 | FN31: 7.9609445 | FO31: =[36]PCR!$J$207 -> 5.153 | FP31: 7.412 | FQ31: =[37]PCR!$J$206 -> 1.858 | FR31: 5.524 | FS31: =[38]PCR!$J$194 -> 1.077 | FT31: 0.783 | FU31: =[39]PCR!$J$187 -> 1.028 | FV31: 1.55 | FW31: =[40]PCR!$J$181 -> 1.745 | FX31: 2.475 | FY31: =[41]PCR!$J$173 -> 2.729 | FZ31: 0.833 | GA31: =[42]PCR!$J$170 -> 0.588 | GB31: 1.391 | GC31: 6.108 | GD31: 4.139 | GE31: 7.078 | GF31: 4.481 | GG31: 3.62 | GH31: 1.544 | GI31: 0.907 | GJ31: 1.524 | GK31: 1.802 | GL31: 2.606 | GM31: 1.952 | GN31: 1.444 | GO31: 2.742 | GP31: 5.723 | GQ31: 6.219 | GR31: 6.515 | GS31: 4.462 | GT31: 3.973 | GU31: 2.002 | GV31: 1.247 | GW31: 3.815 | GX31: 3.921 | GY31: 5.007 | GZ31: 0.997 | HA31: 5.243 | HB31: 10.581 | HC31: 14.352 | HD31: 9.074 | HE31: 1.85 | HF31: 3.951 | HG31: 1.723 | HH31: =[43]PCR!$I$371 -> 0.99 | HI31: =[44]PCR!$I$371 -> 2.689 | HJ31: 1.691 | HK31: =[45]PCR!$I$371 -> 2.699 | HL31: =[50]PCR!$I$371 -> 2.911 | HM31: 4.503 | HN31: 13.828 | HO31: 12.411 | HP31: 10.333 | HQ31: 3.508 | HR31: 2.006 | HS31: 3.499 | HT31: 0.441 | HU31: 2.622 | HV31: 2.159 | HW31: 2.157 | HX31: 3.284 | HY31: =[46]Cate!I371 -> 1.219 | HZ31: 3.909 | IA31: =[47]Cate!I371 -> 3.338 | IB31: =[48]Cate!I371 -> 4.556 | IC31: 1.574 | ID31: =[49]PCR!$I$371 -> 3.012 | IE31: 4.655 | IF31: 1.026 | IG31: 0.066 | IH31: =[51]PCR!$I$371 -> 0.862 | II31: 0.707 | IJ31: 0.543 | IK31: 3.021 | IL31: 2.148 | IM31: 6.399 | IN31: 2.305 | IO31: 0.566 | IP31: 5.215 | IQ31: 0.055 | IR31: 1.593 | IS31: 0 | IT31: 0 | IU31: 0.125 | IV31: 0.687 | IW31: 1.136 | IX31: 2.936 | IY31: 1.074 | IZ31: 0.148 | JA31: 0.167 | JB31: 0.202 | JC31: 0.036 | JD31: 0.468 | JE31: 0 | JF31: 0.052 | JG31: 1.496 | JH31: 0.908
D32: Out | F32: 2.7746219 | G32: 2.519 | H32: 1 | I32: 0.61 | J32: 0.9 | K32: 0.687 | L32: 1.5 | M32: 1.147 | N32: 1.5 | O32: 1.456 | P32: 2 | Q32: 3.061 | R32: 2.322 | S32: 1.801 | T32: 2 | U32: 0.85 | V32: 1.236 | W32: 1.718 | X32: 2 | Y32: 2.177 | Z32: 2.5 | AA32: 1.609 | AB32: 3 | AC32: 3.383 | AD32: 2 | AE32: 2.616 | AF32: 0.812 | AG32: 0.323 | AH32: 0.731 | AI32: 0.792 | AJ32: 1.252 | AK32: 1.133 | AL32: 1.736 | AM32: 1.187 | AN32: 2.123 | AO32: 2.202 | AP32: 2.447 | AQ32: 1.503 | AR32: 1.667 | AS32: 2.743 | AT32: 1.603 | AU32: 2.744 | AV32: 2.469 | AW32: 1.384 | AX32: 2.439 | AY32: 2.14 | AZ32: 2.63 | BA32: 3.287 | BB32: 2.692 | BC32: 2.981 | BD32: 1.212 | BE32: 1.113 | BF32: 1.442 | BG32: 0.929 | BH32: 1.91 | BI32: 2.588 | BJ32: 1.758 | BK32: 1.494 | BL32: 1.804 | BM32: 1.529 | BN32: 2.206 | BO32: 1.836 | BP32: 2.265 | BQ32: 2.407 | BR32: 2.249 | BS32: 1.876 | BT32: 2.296 | BU32: 1.934 | BV32: =+BV31 -> 3.22 | BW32: 2.813 | BX32: =+BX31 -> 3.21 | BY32: 1.869 | BZ32: =+BZ31 -> 3.249 | CA32: 2.893 | CB32: =+CB31 -> 1.983 | CC32: 1.234 | CD32: 1.743 | CE32: 2.036 | CF32: 2.64 | CG32: 1.084 | CH32: 2.405 | CI32: 1.748 | CJ32: 2.878 | CK32: 1.568 | CL32: 3.23 | CM32: 2.889 | CN32: =+CN31 -> 2.8176629 | CO32: 1.398 | CP32: 3.283 | CQ32: 2.279 | CR32: 3.5872236 | CS32: 4.065 | CT32: =+CT31 -> 4.449 | CU32: 3.697 | CV32: =+CV31 -> 4.888 | CW32: 4.82 | CX32: 4.3483466 | CY32: 1.835 | CZ32: 1.306 | DA32: 1.083 | DB32: 1.289 | DC32: 0.966 | DD32: 1.8232 | DE32: 1.818 | DF32: 2.42 | DG32: =[12]PCR!$J$173 -> 1.919 | DH32: 2.576 | DI32: =[13]PCR!$J$172 -> 1.963 | DJ32: 3.446 | DK32: 3.19 | DL32: =DL31 -> 2.679 | DM32: 1.647 | DN32: =DN31 -> 3.14 | DO32: 1.798 | DP32: =DP31 -> 3.528 | DQ32: 2.672 | DR32: =DR31 -> 3.843 | DS32: 9.875 | DT32: =DT31 -> 4.51 | DU32: =[14]PCR!$J$227 -> 4.856 | DV32: =DV31 -> 4.316 | DW32: =[15]PCR!$J$228 -> 4.3 | DX32: =DX31 -> 2.391 | DY32: =[16]PCR!$J$196 -> 1.29 | DZ32: =DZ31 -> 2.447 | EA32: =[17]PCR!$J$181 -> 2.522 | EB32: =EB31 -> 3.581 | EC32: =[18]PCR!$J$183 -> 1.344 | ED32: =ED31 -> 3.713 | EE32: =[19]PCR!$J$182 -> 1.101 | EF32: =EF31 -> 4.232 | EG32: =[20]PCR!$J$184 -> 1.23 | EH32: =EH31 -> 4.852 | EI32: =[21]PCR!$J$200 -> 1.058 | EJ32: =EJ31 -> 2.678 | EK32: =[22]PCR!$J$207 -> 1.091 | EL32: =EL31 -> 3.087 | EM32: =[23]PCR!$J$231 -> 2.095 | EN32: =EN31 -> 5.087 | EO32: =[24]PCR!$J$253 -> 1.376 | EP32: =EP31 -> 7.11 | EQ32: =[25]PCR!$J$259 -> 4.776 | ER32: =ER31 -> 7.646 | ES32: =[26]PCR!$J$232 -> 3.799 | ET32: =ET31 -> 6.448 | EU32: =[27]PCR!$J$217 -> 3.487 | EV32: =EV31 -> 1.206 | EW32: =[28]PCR!$J$192 -> 0.824 | EX32: =EX31 -> 1.525 | EY32: =[29]PCR!$J$196 -> #REF! | EZ32: =EZ31 -> 1.799 | FA32: =[30]PCR!$J$197 -> 1.643 | FB32: =FB31 -> 2.18 | FC32: 1.778 | FD32: =FD31 -> 2.443 | FE32: =[31]PCR!$J$185 -> 1.378 | FF32: =FF31 -> 2.867 | FG32: =[32]PCR!$J$193 -> 2.508 | FH32: =FH31 -> 2.8499062 | FI32: =[33]PCR!$J$204 -> 2.046 | FJ32: 2.8740415 | FK32: =[34]PCR!$J$203 -> 1.791 | FL32: 5.2650475 | FM32: =[35]PCR!$J$213 -> 5.039 | FN32: 7.9609445 | FO32: =[36]PCR!$J$208 -> 3.831 | FP32: 7.412 | FQ32: =[37]PCR!$J$207 -> 3.614 | FR32: 5.524 | FS32: =[38]PCR!$J$195 -> 3.529 | FT32: 0.745 | FU32: =[39]PCR!$J$188 -> 0.756 | FV32: 0.887 | FW32: =[40]PCR!$J$182 -> 2.378 | FX32: 1.903 | FY32: =[41]PCR!$J$174 -> 2.276 | FZ32: 2.179 | GA32: =[42]PCR!$J$171 -> 1.691 | GB32: 1.406 | GC32: 2.19 | GD32: 2.066 | GE32: 2.557 | GF32: 6.238 | GG32: 4.175 | GH32: 4.373 | GI32: 2.942 | GJ32: 1.514 | GK32: 1.535 | GL32: 1.808 | GM32: 3.134 | GN32: 1.852 | GO32: 2.473 | GP32: 2.482 | GQ32: 3.21 | GR32: 4.316 | GS32: 12.732 | GT32: 2.88 | GU32: 4.9 | GV32: 1.146 | GW32: 1.659 | GX32: 1.662 | GY32: 3.875 | GZ32: 3.142 | HA32: 6.316 | HB32: 2.659 | HC32: 13.053 | HD32: 11.595 | HE32: 5.648 | HF32: 4.068 | HG32: 5.774 | HH32: =[43]PCR!$I$372 -> 0.954 | HI32: =[44]PCR!$I$372 -> 0.625 | HJ32: 1.005 | HK32: =[45]PCR!$J$371 -> 2.058 | HL32: =[50]PCR!$I$372 -> 2.285 | HM32: 4.825 | HN32: 7.412 | HO32: 10.071 | HP32: 13.872 | HQ32: 11.228 | HR32: 3.789 | HS32: 3.308 | HT32: 1.093 | HU32: 1.441 | HV32: 2.017 | HW32: 2.283 | HX32: 3.452 | HY32: =[46]Cate!J371 -> 2.825 | HZ32: 1.699 | IA32: =[47]Cate!J371 -> 3.314 | IB32: =[48]Cate!J371 -> 4.2 | IC32: 2.022 | ID32: =[49]PCR!$J$371 -> 2.068 | IE32: 4.812 | IF32: 1.341 | IG32: 1.602 | IH32: =[51]PCR!$J$371 -> 1.157 | II32: 1.254 | IJ32: 1.424 | IK32: 2.391 | IL32: 1.223 | IM32: 1.528 | IN32: 0.896 | IO32: 0.599 | IP32: 1.351 | IQ32: 5.027 | IR32: 0.363 | IS32: 0.845 | IT32: 0.998 | IU32: 1.591 | IV32: 0.904 | IW32: 0.635 | IX32: 1.197 | IY32: 0.823 | IZ32: 1.542 | JA32: 2.158 | JB32: 1.916 | JC32: 3.32 | JD32: 0.379 | JE32: 0.197 | JF32: 0.442 | JG32: 0.595 | JH32: 0.7
D33: Inventory | F33: 2.5185489 | G33: 2.589 | H33: =F33+H31-H32 -> 2.1725489 | I33: =G33+I31-I32 -> 2.203 | J33: =H33+J31-J32 -> 2.2725489 | K33: =I33+K31-K32 -> 1.881 | L33: =J33+L31-L32 -> 2.7725489 | M33: =K33+M31-M32 -> 1.921 | N33: =L33+N31-N32 -> 3.4725489 | O33: =M33+O31-O32 -> 1.701 | ... AK33: =AI33+AK31-AK32 -> 2.035 | AL33: =N33*1.137 -> 3.9482881 | AM33: =AK33+AM31-AM32 -> 4.62 | AN33: =P33*1.137 -> 4.2893881 | AO33: =AM33+AO31-AO32 -> 3.732 | AP33: =R33*1.137 -> 3.3547741 | AQ33: 3.131 | AR33: =T33*1.137 -> 2.8999741 | AS33: =AQ33+AS31-AS32 -> 4.196 | AT33: =V33*1.137 -> 4.2234421 | AU33: =AS33+AU31-AU32 -> 2.734 | AV33: =X33*1.137 -> 5.1330421 | AW33: =AU33+AW31-AW32 -> 5.404 | AX33: =Z33*1.137 -> 5.1330421 | AY33: =AW33+AY31-AY32 -> 5.634 | AZ33: 5.7015421 | BA33: 5.457 | BB33: 4.5645421 | BC33: 3.602 | BD33: 4.5645421 | BE33: 3.626 | BF33: =BD33+BF31-BF32 -> 4.5645421 | BG33: =BE33+BG31-BG32 -> 3.021 | BH33: =AJ33*1.137 -> 2.2905421 | BI33: =BG33+BI31-BI32 -> 4.285 | BJ33: =AL33*1.137 -> 4.4892036 | BK33: =BI33+BK31-BK32 -> 5.017 | BL33: =AN33*1.137 -> 4.8770343 | BM33: =BK33+BM31-BM32 -> 4.287 | BN33: =AP33*1.137 -> 3.8143782 | BO33: =BM33+BO31-BO32 -> 3.729 | BP33: =AR33*1.137 -> 3.2972706 | BQ33: =BO33+BQ31-BQ32 -> 4.117 | BR33: =AT33*1.137 -> 4.8020537 | BS33: =BQ33+BS31-BS32 -> 3.765 | BT33: =AV33*1.137 -> 5.8362689 | BU33: =BS33+BU31-BU32 -> 4.759 | BV33: =AX33*1.137 -> 5.8362689 | BW33: =BU33+BW31-BW32 -> 4.427 | BX33: =AZ33*1.137 -> 6.4826534 | BY33: =BW33+BY31-BY32 -> 3.73 | BZ33: =BB33*1.137 -> 5.1898844 | CA33: =BY33+CA31-CA32 -> 2.337 | CB33: =BD33*1.137 -> 5.1898844 | CC33: =CA33+CC31-CC32 -> 2.42 | CD33: =BF33*1.137 -> 5.1898844 | CE33: =CC33+CE31-CE32 -> 2.881 | CF33: =BH33*1.137 -> 2.6043464 | CG33: =CE33+CG31-CG32 -> 4.051 | CH33: =BJ33*1.137 -> 5.1042245 | CI33: =CG33+CI31-CI32 -> 3.057 | CJ33: =BL33*1.137 -> 5.545188 | CK33: =CI33+CK31-CK32 -> 2.364 | CL33: =BN33*1.137 -> 4.336948 | CM33: =CK33+CM31-CM32 -> 1.801 | CN33: 2.6676629 | CO33: =CM33+CO31-CO32 -> 3.621 | CP33: =BR33*1.137 -> 5.4599351 | CQ33: =CO33+CQ31-CQ32 -> 7.881 | CR33: =BT33*1.137 -> 6.6358378 | CS33: =CQ33+CS31-CS32 -> 5.612 | CT33: =BV33*1.137 -> 6.6358378 | CU33: =CS33+CU31-CU32 -> 4.84 | CV33: =BX33*1.137 -> 7.3707769 | CW33: =CU33+CW31-CW32 -> 2.546 | CX33: =BZ33*1.137 -> 5.9008986 | CY33: 1.233 | CZ33: =CB33*1.137 -> 5.9008986 | DA33: =CY33+DA31-DA32 -> 1.753 | DB33: =CD33*1.137 -> 5.9008986 | DC33: =DA33+DC31-DC32 -> 1.303 | DD33: =CF33*1.137 -> 2.9611419 | DE33: =DC33+DE31-DE32 -> 0.897 | DF33: =CF33*1.137 -> 2.9611419 | DG33: =DE33+DG31-DG32 -> 1.028 | DH33: =CH33*1.137 -> 5.8035033 | DI33: =DG33+DI31-DI32 -> 2.025 | DJ33: =CH33*1.137 -> 5.8035033 | DK33: =DI33+DK31-DK32 -> 2.176 | DL33: =CJ33*1.137 -> 6.3048788 | DM33: =DK33+DM31-DM32 -> 2.826 | DN33: =CL33*1.137 -> 4.9311099 | DO33: =DM33+DO31-DO32 -> 1.796 | DP33: =CN33*1.137 -> 3.0331328 | DQ33: =DO33+DQ31-DQ32 -> 4.985 | DR33: =CP33*1.137 -> 6.2079462 | DS33: =DQ33+DS31-DS32 -> 12.401 | DT33: =CR33*1.137 -> 7.5449475 | DU33: =DS33+DU31-DU32 -> 9.056 | DV33: =CT33*1.137 -> 7.5449475 | DW33: =DU33+DW31-DW32 -> 8.902 | DX33: =CV33*1.137 -> 8.3805734 | DY33: =DW33+DY31-DY32 -> 10.836 | DZ33: =CX33*1.137 -> 6.7093217 | EA33: =DY33+EA31-EA32 -> 9.107 | EB33: =CZ33*1.137 -> 6.7093217 | EC33: =EA33+EC31-EC32 -> 8.234 | ED33: =DB33*1.137 -> 6.7093217 | EE33: =EC33+EE31-EE32 -> 7.518 | EF33: =DD33*1.137 -> 3.3668183 | EG33: =EE33+EG31-EG32 -> 7.712 | EH33: =DF33*1.137 -> 3.3668183 | EI33: =EG33+EI31-EI32 -> 7.648 | EJ33: =DH33*1.137 -> 6.5985832 | EK33: =EI33+EK31-EK32 -> 8.462 | EL33: =DJ33*1.137 -> 6.5985832 | EM33: =EK33+EM31-EM32 -> 10.827 | EN33: =DL33*1.137 -> 7.1686472 | EO33: 12.184 | EP33: =DN33*1.137 -> 5.6066719 | EQ33: =EO33+EQ31-EQ32 -> 8.81 | ER33: =DP33*1.137 -> 3.4486719 | ES33: =EQ33+ES31-ES32 -> 6.152 | ET33: =DR33*1.137 -> 7.0584348 | EU33: =ES33+EU31-EU32 -> 3.729 | EV33: =DT33*1.137 -> 8.5786053 | EW33: =EU33+EW31-EW32 -> 3.025 | EX33: =DV33*1.137 -> 8.5786053 | EY33: =EW33+EY31-EY32 -> #REF! | EZ33: =DX33*1.137 -> 9.5287119 | FA33: =EY33+FA31-FA32 -> #REF! | FB33: =DZ33*1.137 -> 7.6284988 | FC33: =FA33+FC31-FC32 -> #REF! | FD33: =EB33*1.137 -> 7.6284988 | FE33: 4.322 | FF33: =ED33*1.137 -> 7.6284988 | FG33: =FE33+FG31-FG32 -> 5.322 | FH33: =EF33*1.137 -> 3.8280724 | FI33: =FG33+FI31-FI32 -> 6.797 | FJ33: =EH33*1.137 -> 3.8280724 | FK33: =FI33+FK31-FK32 -> 8 | FL33: =EJ33*1.137 -> 7.5025891 | FM33: =FK33+FM31-FM32 -> 6.846 | FN33: =EL33*1.137 -> 7.5025891 | FO33: =FM33+FO31-FO32 -> 8.168 | FP33: =EN33*1.137 -> 8.1507518 | FQ33: =FO33+FQ31-FQ32 -> 6.412 | FR33: 3.648 | FS33: =FQ33+FS31-FS32 -> 3.96 | FT33: =FR33+FT31-FT32 -> 3.686 | FU33: =FS33+FU31-FU32 -> 4.232 | FV33: =FT33+FV31-FV32 -> 4.349 | FW33: =FU33+FW31-FW32 -> 3.599 | FX33: =FV33+FX31-FX32 -> 4.921 | FY33: =FW33+FY31-FY32 -> 4.052 | FZ33: 2.706 | GA33: =FY33+GA31-GA32 -> 2.949 | GB33: =GA33+GB31-GB32 -> 2.934 | GC33: =GB33+GC31-GC32 -> 6.852 | GD33: =GC33+GD31-GD32 -> 8.925 | GE33: =GD33+GE31-GE32 -> 13.446 | GF33: =GE33+GF31-GF32 -> 11.689 | GG33: =GF33+GG31-GG32 -> 11.134 | GH33: =GG33+GH31-GH32 -> 8.305 | GI33: =GH33+GI31-GI32 -> 6.27 | ... HB33: =HA33+HB31-HB32 -> 14.75 | HC33: 15.2 | HD33: =HC33+HD31-HD32 -> 12.679 | HE33: =HD33+HE31-HE32 -> 8.881 | HF33: =HE33+HF31-HF32 -> 8.764 | HG33: =HF33+HG31-HG32 -> 4.713 | HH33: =HG33+HH31-HH32 -> 4.749 | HI33: =HH33+HI31-HI32 -> 6.813 | HJ33: =HI33+HJ31-HJ32 -> 7.499 | HK33: =HJ33+HK31-HK32 -> 8.14 | ... HU33: =HT33+HU31-HU32 -> 4.878 | HV33: 5.287 | HW33: =HV33+HW31-HW32 -> 5.161 | HX33: =HW33+HX31-HX32 -> 4.993 | HY33: =HX33+HY31-HY32 -> 3.387 | HZ33: =HY33+HZ31-HZ32 -> 5.597 | IA33: =HZ33+IA31-IA32 -> 5.621 | IB33: =IA33+IB31-IB32 -> 5.977 | IC33: =IB33+IC31-IC32 -> 5.529 | ID33: =IC33+ID31-ID32 -> 6.473 | ... IL33: =IK33+IL31-IL32 -> 4.297 | IM33: 9.168 | IN33: =IM33+IN31-IN32 -> 10.577 | IO33: =IN33+IO31-IO32 -> 10.544 | IP33: =IO33+IP31-IP32 -> 14.408 | IQ33: =IP33+IQ31-IQ32 -> 9.436 | IR33: =IQ33+IR31-IR32 -> 10.666 | IS33: =IR33+IS31-IS32 -> 9.821 | IT33: =IS33+IT31-IT32 -> 8.823 | IU33: =IT33+IU31-IU32 -> 7.357 | ... JO33: =JN33+JO31-JO32 -> 1.859
D34: month | E34: 1.6 | F34: 1.7685033 | G34: 2.4593333 | H34: =IF(H33<=J32,H33/J32,IF(H33<=J32+L32,1+(H33-J32)/L32,IF(H33<=J32+L32+N32,2+(H33-J32-L32)/N32,H33*3/(J32+L32+N32)))) -> 1.848366 | I34: =IF(I33<=K32,I33/K32,IF(I33<=K32+M32,1+(I33-K32)/M32,IF(I33<=K32+M32+O32,2+(I33-K32-M32)/O32,I33*3/(K32+M32+O32)))) -> 2.2534341 | J34: =IF(J33<=L32,J33/L32,IF(J33<=L32+N32,1+(J33-L32)/N32,IF(J33<=L32+N32+P32,2+(J33-L32-N32)/P32,J33*3/(L32+N32+P32)))) -> 1.5150326 | K34: =IF(K33<=M32,K33/M32,IF(K33<=M32+O32,1+(K33-M32)/O32,IF(K33<=M32+O32+Q32,2+(K33-M32-O32)/Q32,K33*3/(M32+O32+Q32)))) -> 1.5041209 | L34: =IF(L33<=N32,L33/N32,IF(L33<=N32+P32,1+(L33-N32)/P32,IF(L33<=N32+P32+R32,2+(L33-N32-P32)/R32,L33*3/(N32+P32+R32)))) -> 1.6362745 | M34: =IF(M33<=O32,M33/O32,IF(M33<=O32+Q32,1+(M33-O32)/Q32,IF(M33<=O32+Q32+S32,2+(M33-O32-Q32)/S32,M33*3/(O32+Q32+S32)))) -> 1.1519111 | N34: =IF(N33<=P32,N33/P32,IF(N33<=P32+R32,1+(N33-P32)/R32,IF(N33<=P32+R32+T32,2+(N33-P32-R32)/T32,N33*3/(P32+R32+T32)))) -> 1.6341727 | O34: =IF(O33<=Q32,O33/Q32,IF(O33<=Q32+S32,1+(O33-Q32)/S32,IF(O33<=Q32+S32+U32,2+(O33-Q32-S32)/U32,O33*3/(Q32+S32+U32)))) -> 0.55570075 | ... CS34: =IF(CS33<=CU32,CS33/CU32,IF(CS33<=CU32+CW32,1+(CS33-CU32)/CW32,IF(CS33<=CU32+CW32+CY32,2+(CS33-CU32-CW32)/CY32,CS33*3/(CU32+CW32+CY32)))) -> 1.3973029 | CT34: =IF(CT33<=CV32,CT33/CV32,IF(CT33<=CV32+CX32,1+(CT33-CV32)/CX32,IF(CT33<=CV32+CX32+#REF!,2+(CT33-CV32-CX32)/#REF!,CT33*3/(CV32+CX32+#REF!)))) -> 1.4019546 | CU34: =IF(CU33<=CW32,CU33/CW32,IF(CU33<=CW32+CY32,1+(CU33-CW32)/CY32,IF(CU33<=CW32+CY32+DA32,2+(CU33-CW32-CY32)/DA32,CU33*3/(CW32+CY32+DA32)))) -> 1.0108992 | CV34: =IF(CV33<=CX32,CV33/CX32,IF(CV33<=CX32+CZ32,1+(CV33-CX32)/CZ32,IF(CV33<=CX32+CZ32+#REF!,2+(CV33-CX32-CZ32)/#REF!,CV33*3/(CX32+CZ32+#REF!)))) -> #REF! | CW34: =IF(CW33<=CY32,CW33/CY32,IF(CW33<=CY32+DA32,1+(CW33-CY32)/DA32,IF(CW33<=CY32+DA32+DC32,2+(CW33-CY32-DA32)/DC32,CW33*3/(CY32+DA32+DC32)))) -> 1.6565097 | CX34: =IF(CX33<=CZ32,CX33/CZ32,IF(CX33<=CZ32+DB32,1+(CX33-CZ32)/DB32,IF(CX33<=CZ32+DB32+#REF!,2+(CX33-CZ32-DB32)/#REF!,CX33*3/(CZ32+DB32+#REF!)))) -> #REF! | CY34: =IF(CY33<=DA32,CY33/DA32,IF(CY33<=DA32+DC32,1+(CY33-DA32)/DC32,IF(CY33<=DA32+DC32+DE32,2+(CY33-DA32-DC32)/DE32,CY33*3/(DA32+DC32+DE32)))) -> 1.1552795 | CZ34: =IF(CZ33<=DB32,CZ33/DB32,IF(CZ33<=DB32+DD32,1+(CZ33-DB32)/DD32,IF(CZ33<=DB32+DD32+#REF!,2+(CZ33-DB32-DD32)/#REF!,CZ33*3/(DB32+DD32+#REF!)))) -> #REF! | DA34: =IF(DA33<=DC32,DA33/DC32,IF(DA33<=DC32+DE32,1+(DA33-DC32)/DE32,IF(DA33<=DC32+DE32+DG32,2+(DA33-DC32-DE32)/DG32,DA33*3/(DC32+DE32+DG32)))) -> 1.4328933 | DB34: =IF(DB33<=DD32,DB33/DD32,IF(DB33<=DD32+DF32,1+(DB33-DD32)/DF32,IF(DB33<=DD32+DF32+DH32,2+(DB33-DD32-DF32)/DH32,DB33*3/(DD32+DF32+DH32)))) -> 2.6435165 | DC34: =IF(DC33<=DE32,DC33/DE32,IF(DC33<=DE32+DG32,1+(DC33-DE32)/DG32,IF(DC33<=DE32+DG32+DI32,2+(DC33-DE32-DG32)/DI32,DC33*3/(DE32+DG32+DI32)))) -> 0.71672167 | DD34: =IF(DD33<=DF32,DD33/DF32,IF(DD33<=DF32+DH32,1+(DD33-DF32)/DH32,IF(DD33<=DF32+DH32+DJ32,2+(DD33-DF32-DH32)/DJ32,DD33*3/(DF32+DH32+DJ32)))) -> 1.2100706 | DE34: =IF(DE33<=DG32,DE33/DG32,IF(DE33<=DG32+DI32,1+(DE33-DG32)/DI32,IF(DE33<=DG32+DI32+DK32,2+(DE33-DG32-DI32)/DK32,DE33*3/(DG32+DI32+DK32)))) -> 0.46743095 | DF34: =IF(DF33<=DH32,DF33/DH32,IF(DF33<=DH32+DJ32,1+(DF33-DH32)/DJ32,IF(DF33<=DH32+DJ32+DL32,2+(DF33-DH32-DJ32)/DL32,DF33*3/(DH32+DJ32+DL32)))) -> 1.1117649 | DG34: =IF(DG33<=DI32,DG33/DI32,IF(DG33<=DI32+DK32,1+(DG33-DI32)/DK32,IF(DG33<=DI32+DK32+DM32,2+(DG33-DI32-DK32)/DM32,DG33*3/(DI32+DK32+DM32)))) -> 0.52368823 | DH34: =IF(DH33<=DJ32,DH33/DJ32,IF(DH33<=DJ32+DL32,1+(DH33-DJ32)/DL32,IF(DH33<=DJ32+DL32+DN32,2+(DH33-DJ32-DL32)/DN32,DH33*3/(DJ32+DL32+DN32)))) -> 1.8799938 | DI34: =IF(DI33<=DK32,DI33/DK32,IF(DI33<=DK32+DM32,1+(DI33-DK32)/DM32,IF(DI33<=DK32+DM32+DO32,2+(DI33-DK32-DM32)/DO32,DI33*3/(DK32+DM32+DO32)))) -> 0.63479624 | DJ34: 1.5 | DK34: =IF(DK33<=DM32,DK33/DM32,IF(DK33<=DM32+DO32,1+(DK33-DM32)/DO32,IF(DK33<=DM32+DO32+DQ32,2+(DK33-DM32-DO32)/DQ32,DK33*3/(DM32+DO32+DQ32)))) -> 1.2942158 | DL34: 1.5 | DM34: =IF(DM33<=DO32,DM33/DO32,IF(DM33<=DO32+DQ32,1+(DM33-DO32)/DQ32,IF(DM33<=DO32+DQ32+DS32,2+(DM33-DO32-DQ32)/DS32,DM33*3/(DO32+DQ32+DS32)))) -> 1.3847305 | DN34: 1.5 | DO34: =IF(DO33<=DQ32,DO33/DQ32,IF(DO33<=DQ32+DS32,1+(DO33-DQ32)/DS32,IF(DO33<=DQ32+DS32+DU32,2+(DO33-DQ32-DS32)/DU32,DO33*3/(DQ32+DS32+DU32)))) -> 0.67215569 | DP34: 1.5 | DQ34: =IF(DQ33<=DS32,DQ33/DS32,IF(DQ33<=DS32+DU32,1+(DQ33-DS32)/DU32,IF(DQ33<=DS32+DU32+DW32,2+(DQ33-DS32-DU32)/DW32,DQ33*3/(DS32+DU32+DW32)))) -> 0.50481013 | DR34: 1.5 | DS34: =IF(DS33<=DU32,DS33/DU32,IF(DS33<=DU32+DW32,1+(DS33-DU32)/DW32,IF(DS33<=DU32+DW32+DY32,2+(DS33-DU32-DW32)/DY32,DS33*3/(DU32+DW32+DY32)))) -> 3.5614589 | DT34: 1.5 | DU34: =IF(DU33<=DW32,DU33/DW32,IF(DU33<=DW32+DY32,1+(DU33-DW32)/DY32,IF(DU33<=DW32+DY32+EA32,2+(DU33-DW32-DY32)/EA32,DU33*3/(DW32+DY32+EA32)))) -> 3.3491124 | DV34: 1.5 | DW34: =IF(DW33<=DY32,DW33/DY32,IF(DW33<=DY32+EA32,1+(DW33-DY32)/EA32,IF(DW33<=DY32+EA32+EC32,2+(DW33-DY32-EA32)/EC32,DW33*3/(DY32+EA32+EC32)))) -> 5.1795966 | DX34: 1.5 | DY34: =IF(DY33<=EA32,DY33/EA32,IF(DY33<=EA32+EC32,1+(DY33-EA32)/EC32,IF(DY33<=EA32+EC32+EE32,2+(DY33-EA32-EC32)/EE32,DY33*3/(EA32+EC32+EE32)))) -> 6.5447957 | DZ34: 1.5 | EA34: =IF(EA33<=EC32,EA33/EC32,IF(EA33<=EC32+EE32,1+(EA33-EC32)/EE32,IF(EA33<=EC32+EE32+EG32,2+(EA33-EC32-EE32)/EG32,EA33*3/(EC32+EE32+EG32)))) -> 7.4342857 | EB34: 1.5 | EC34: =IF(EC33<=EE32,EC33/EE32,IF(EC33<=EE32+EG32,1+(EC33-EE32)/EG32,IF(EC33<=EE32+EG32+EI32,2+(EC33-EE32-EG32)/EI32,EC33*3/(EE32+EG32+EI32)))) -> 7.2888758 | ED34: 1.5 | EE34: =IF(EE33<=EG32,EE33/EG32,IF(EE33<=EG32+EI32,1+(EE33-EG32)/EI32,IF(EE33<=EG32+EI32+EK32,2+(EE33-EG32-EI32)/EK32,EE33*3/(EG32+EI32+EK32)))) -> 6.6747558 | EF34: 1.5 | EG34: =IF(EG33<=EI32,EG33/EI32,IF(EG33<=EI32+EK32,1+(EG33-EI32)/EK32,IF(EG33<=EI32+EK32+EM32,2+(EG33-EI32-EK32)/EM32,EG33*3/(EI32+EK32+EM32)))) -> 5.4514609 | EH34: 1.5 | EI34: =IF(EI33<=EK32,EI33/EK32,IF(EI33<=EK32+EM32,1+(EI33-EK32)/EM32,IF(EI33<=EK32+EM32+EO32,2+(EI33-EK32-EM32)/EO32,EI33*3/(EK32+EM32+EO32)))) -> 5.0293731 | EJ34: 2.5 | EK34: =IF(EK33<=EM32,EK33/EM32,IF(EK33<=EM32+EO32,1+(EK33-EM32)/EO32,IF(EK33<=EM32+EO32+EQ32,2+(EK33-EM32-EO32)/EQ32,EK33*3/(EM32+EO32+EQ32)))) -> 3.0782103 | EL34: 2.5 | EM34: =IF(EM33<=EO32,EM33/EO32,IF(EM33<=EO32+EQ32,1+(EM33-EO32)/EQ32,IF(EM33<=EO32+EQ32+ES32,2+(EM33-EO32-EQ32)/ES32,EM33*3/(EO32+EQ32+ES32)))) -> 3.2640941 | EN34: 2.5 | EO34: =IF(EO33<=EQ32,EO33/EQ32,IF(EO33<=EQ32+ES32,1+(EO33-EQ32)/ES32,IF(EO33<=EQ32+ES32+EU32,2+(EO33-EQ32-ES32)/EU32,EO33*3/(EQ32+ES32+EU32)))) -> 3.0303432 | EP34: 2.5 | EQ34: =IF(EQ33<=ES32,EQ33/ES32,IF(EQ33<=ES32+EU32,1+(EQ33-ES32)/EU32,IF(EQ33<=ES32+EU32+EW32,2+(EQ33-ES32-EU32)/EW32,EQ33*3/(ES32+EU32+EW32)))) -> 3.2589396 | ER34: 2.5 | ES34: =IF(ES33<=EU32,ES33/EU32,IF(ES33<=EU32+EW32,1+(ES33-EU32)/EW32,IF(ES33<=EU32+EW32+EY32,2+(ES33-EU32-EW32)/EY32,ES33*3/(EU32+EW32+EY32)))) -> #REF! | ET34: 2.5 | EU34: =IF(EU33<=EW32,EU33/EW32,IF(EU33<=EW32+EY32,1+(EU33-EW32)/EY32,IF(EU33<=EW32+EY32+FA32,2+(EU33-EW32-EY32)/FA32,EU33*3/(EW32+EY32+FA32)))) -> #REF! | EV34: 2.5 | EW34: =IF(EW33<=EY32,EW33/EY32,IF(EW33<=EY32+FA32,1+(EW33-EY32)/FA32,IF(EW33<=EY32+FA32+FC32,2+(EW33-EY32-FA32)/FC32,EW33*3/(EY32+FA32+FC32)))) -> #REF! | EX34: 2.5 | EY34: =IF(EY33<=FA32,EY33/FA32,IF(EY33<=FA32+FC32,1+(EY33-FA32)/FC32,IF(EY33<=FA32+FC32+FE32,2+(EY33-FA32-FC32)/FE32,EY33*3/(FA32+FC32+FE32)))) -> #REF! | EZ34: 2.5 | FA34: =IF(FA33<=FC32,FA33/FC32,IF(FA33<=FC32+FE32,1+(FA33-FC32)/FE32,IF(FA33<=FC32+FE32+FG32,2+(FA33-FC32-FE32)/FG32,FA33*3/(FC32+FE32+FG32)))) -> #REF! | FB34: 2.5 | FC34: =IF(FC33<=FE32,FC33/FE32,IF(FC33<=FE32+FG32,1+(FC33-FE32)/FG32,IF(FC33<=FE32+FG32+FI32,2+(FC33-FE32-FG32)/FI32,FC33*3/(FE32+FG32+FI32)))) -> #REF! | FD34: 2 | FE34: =IF(FE33<=FG32,FE33/FG32,IF(FE33<=FG32+FI32,1+(FE33-FG32)/FI32,IF(FE33<=FG32+FI32+FK32,2+(FE33-FG32-FI32)/FK32,FE33*3/(FG32+FI32+FK32)))) -> 1.886608 | FF34: 2 | FG34: =IF(FG33<=FI32,FG33/FI32,IF(FG33<=FI32+FK32,1+(FG33-FI32)/FK32,IF(FG33<=FI32+FK32+FM32,2+(FG33-FI32-FK32)/FM32,FG33*3/(FI32+FK32+FM32)))) -> 2.2947013 | FH34: 2 | FI34: =IF(FI33<=FK32,FI33/FK32,IF(FI33<=FK32+FM32,1+(FI33-FK32)/FM32,IF(FI33<=FK32+FM32+FO32,2+(FI33-FK32-FM32)/FO32,FI33*3/(FK32+FM32+FO32)))) -> 1.9934511 | FJ34: 2 | FK34: =IF(FK33<=FM32,FK33/FM32,IF(FK33<=FM32+FO32,1+(FK33-FM32)/FO32,IF(FK33<=FM32+FO32+FQ32,2+(FK33-FM32-FO32)/FQ32,FK33*3/(FM32+FO32+FQ32)))) -> 1.7729052 | FL34: 2 | FM34: =IF(FM33<=FO32,FM33/FO32,IF(FM33<=FO32+FQ32,1+(FM33-FO32)/FQ32,IF(FM33<=FO32+FQ32+FS32,2+(FM33-FO32-FQ32)/FS32,FM33*3/(FO32+FQ32+FS32)))) -> 1.8342557 | FN34: 2 | FO34: =IF(FO33<=FQ32,FO33/FQ32,IF(FO33<=FQ32+FS32,1+(FO33-FQ32)/FS32,IF(FO33<=FQ32+FS32+FU32,2+(FO33-FQ32-FS32)/FU32,FO33*3/(FQ32+FS32+FU32)))) -> 3.1021648 | FP34: 2 | FQ34: =IF(FQ33<=FS32,FQ33/FS32,IF(FQ33<=FS32+FU32,1+(FQ33-FS32)/FU32,IF(FQ33<=FS32+FU32+FW32,2+(FQ33-FS32-FU32)/FW32,FQ33*3/(FS32+FU32+FW32)))) -> 2.8944491 | FR34: 2 | FS34: =IF(FS33<=FU32,FS33/FU32,IF(FS33<=FU32+FW32,1+(FS33-FU32)/FW32,IF(FS33<=FU32+FW32+FY32,2+(FS33-FU32-FW32)/FY32,FS33*3/(FU32+FW32+FY32)))) -> 2.3629174 | FT34: =IF(FT33<=FV32,FT33/FV32,IF(FT33<=FV32+FX32,1+(FT33-FV32)/FX32,IF(FT33<=FV32+FX32+FZ32,2+(FT33-FV32-FX32)/FZ32,FT33*3/(FV32+FX32+FZ32)))) -> 2.4111978 | FU34: =IF(FU33<=FW32,FU33/FW32,IF(FU33<=FW32+FY32,1+(FU33-FW32)/FY32,IF(FU33<=FW32+FY32+GA32,2+(FU33-FW32-FY32)/GA32,FU33*3/(FW32+FY32+GA32)))) -> 1.814587 | FV34: =IF(FV33<=FX32,FV33/FX32,IF(FV33<=FX32+FZ32,1+(FV33-FX32)/FZ32,IF(FV33<=FX32+FZ32+#REF!,2+(FV33-FX32-FZ32)/#REF!,FV33*3/(FX32+FZ32+#REF!)))) -> #REF! | FW34: =IF(FW33<=FY32,FW33/FY32,IF(FW33<=FY32+GA32,1+(FW33-FY32)/GA32,IF(FW33<=FY32+GA32+GB32,2+(FW33-FY32-GA32)/GB32,FW33*3/(FY32+GA32+GB32)))) -> 1.7823773 | FX34: =IF(FX33<=FZ32,FX33/FZ32,IF(FX33<=FZ32+#REF!,1+(FX33-FZ32)/#REF!,IF(FX33<=FZ32+#REF!+#REF!,2+(FX33-FZ32-#REF!)/#REF!,FX33*3/(FZ32+#REF!+#REF!)))) -> #REF! | FY34: =IF(FY33<=GA32,FY33/GA32,IF(FY33<=GA32+GB32,1+(FY33-GA32)/GB32,IF(FY33<=GA32+GB32+GC32,2+(FY33-GA32-GB32)/GC32,FY33*3/(GA32+GB32+GC32)))) -> 2.4360731 | FZ34: =IF(FZ33<=#REF!,FZ33/#REF!,IF(FZ33<=#REF!+#REF!,1+(FZ33-#REF!)/#REF!,IF(FZ33<=#REF!+#REF!+#REF!,2+(FZ33-#REF!-#REF!)/#REF!,FZ33*3/(#REF!+#REF!+#REF!)))) -> #REF! | GA34: =IF(GA33<=GB32,GA33/GB32,IF(GA33<=GB32+GC32,1+(GA33-GB32)/GC32,IF(GA33<=GB32+GC32+GD32,2+(GA33-GB32-GC32)/GD32,GA33*3/(GB32+GC32+GD32)))) -> 1.7045662 | GB34: =IF(GB33<=GC32,GB33/GC32,IF(GB33<=GC32+GD32,1+(GB33-GC32)/GD32,IF(GB33<=GC32+GD32+GE32,2+(GB33-GC32-GD32)/GE32,GB33*3/(GC32+GD32+GE32)))) -> 1.3601162 | GC34: =IF(GC33<=GD32,GC33/GD32,IF(GC33<=GD32+GE32,1+(GC33-GD32)/GE32,IF(GC33<=GD32+GE32+GF32,2+(GC33-GD32-GE32)/GF32,GC33*3/(GD32+GE32+GF32)))) -> 2.3573261 | GD34: =IF(GD33<=GE32,GD33/GE32,IF(GD33<=GE32+GF32,1+(GD33-GE32)/GF32,IF(GD33<=GE32+GF32+GG32,2+(GD33-GE32-GF32)/GG32,GD33*3/(GE32+GF32+GG32)))) -> 2.0311377 | GE34: =IF(GE33<=GF32,GE33/GF32,IF(GE33<=GF32+GG32,1+(GE33-GF32)/GG32,IF(GE33<=GF32+GG32+GH32,2+(GE33-GF32-GG32)/GH32,GE33*3/(GF32+GG32+GH32)))) -> 2.6935742 | GF34: =IF(GF33<=GG32,GF33/GG32,IF(GF33<=GG32+GH32,1+(GF33-GG32)/GH32,IF(GF33<=GG32+GH32+GI32,2+(GF33-GG32-GH32)/GI32,GF33*3/(GG32+GH32+GI32)))) -> 3.0519582 | GG34: =IF(GG33<=GH32,GG33/GH32,IF(GG33<=GH32+GI32,1+(GG33-GH32)/GI32,IF(GG33<=GH32+GI32+GJ32,2+(GG33-GH32-GI32)/GJ32,GG33*3/(GH32+GI32+GJ32)))) -> 3.7832144 | GH34: =IF(GH33<=GI32,GH33/GI32,IF(GH33<=GI32+GJ32,1+(GH33-GI32)/GJ32,IF(GH33<=GI32+GJ32+GK32,2+(GH33-GI32-GJ32)/GK32,GH33*3/(GI32+GJ32+GK32)))) -> 4.1587381 | ... JO34: =IF(JO33<=JP32,JO33/JP32,IF(JO33<=JP32+JQ32,1+(JO33-JP32)/JQ32,IF(JO33<=JP32+JQ32+JR32,2+(JO33-JP32-JQ32)/JR32,JO33*3/(JP32+JQ32+JR32)))) -> #DIV/0!
B35: 15" | C35: 1.5 | D35: In | F35: 3.85 | G35: 6.181 | H35: 1.54 | I35: 1.622 | J35: =H36 -> 1.6 | K35: 0.763 | L35: 3.5 | M35: 0.251 | N35: 3.5 | O35: 1.251 | P35: 3.3 | Q35: 3.517 | R35: 2.8 | S35: 3.64 | T35: 2.8 | U35: 0.605 | V35: 3.2 | W35: 4.804 | X35: 4 | Y35: 1.434 | Z35: 4 | AA35: 1.176 | AB35: 3.2 | AC35: 0.196 | AD35: 1.8 | AE35: 2.521 | AF35: 0.958 | AG35: 0.217 | AH35: 0.867 | AI35: 0.165 | AJ35: 1.42 | AK35: 1.527 | AL35: 1.964 | AM35: 1.364 | AN35: 2.399 | AO35: 1.544 | AP35: 2.761 | AQ35: 2.09 | AR35: 1.845 | AS35: 1.541 | AT35: 2.073 | AU35: 1.463 | AV35: 2.264 | AW35: 0.539 | AX35: 2.692 | AY35: 1.598 | AZ35: 3.607 | BA35: 1.296 | BB35: 3.152 | BC35: 2.181 | BD35: 0.664 | BE35: 0.024 | BF35: 0.68 | BG35: 0 | BH35: 1.124 | BI35: 3.824 | BJ35: 1.14 | BK35: 0.571 | BL35: 1.278 | BM35: 0.967 | BN35: 1.374 | BO35: 0.15 | BP35: 0.869 | BQ35: 1.716 | BR35: 0.888 | BS35: 0.329 | BT35: 1.3 | BU35: 1.713 | BV35: 1.476 | BW35: 1.033 | BX35: 1.668 | BY35: 2.253 | BZ35: 1.837 | CA35: 0.471 | CB35: 0.721 | CC35: 0.223 | CD35: =+CD36 -> 0.635 | CE35: 0.964 | CF35: 0.958 | CG35: 1.11 | CH35: 0.873 | CI35: 0.721 | CJ35: 1.048 | CK35: 1.22 | CL35: 1.174 | CM35: 0.926 | CN35: 0.97031538 | CO35: 2.889 | CP35: 1.1394425 | CQ35: 2.029 | CR35: 1.2502295 | CS35: 5.11 | CT35: 1.456 | CU35: 1.043 | CV35: 1.591 | CW35: 1.469 | CX35: 1.508888 | CY35: 0.408 | CZ35: 0.299 | DA35: 0.653 | DB35: 0.295 | DC35: 0.164 | DD35: 0.407 | DE35: 0.7 | DF35: 0.837 | DG35: =[12]PCR!$J$113 -> 0.256 | DH35: 1.092 | DI35: =[13]PCR!$J$115 -> 0.649 | DJ35: 0.805 | DK35: 1.347 | DL35: 0.817 | DM35: 0.254 | DN35: 0.957 | DO35: 0.575 | DP35: 1.075 | DQ35: 5.325 | DR35: 1.172 | DS35: 11.453 | DT35: 1.375 | DU35: =[14]PCR!$J$147 -> 0.796 | DV35: 1.316 | DW35: =[15]PCR!$J$144 -> 2.24 | DX35: 0.729 | DY35: =[16]PCR!$J$127 -> 2.508 | DZ35: 0.745 | EA35: =[17]PCR!$J$118 -> 0.449 | EB35: 1.089 | EC35: =[18]PCR!$J$120 -> 0.049 | ED35: 1.132 | EE35: =[19]PCR!$J$119 -> 0.04 | EF35: 1.29 | EG35: =[20]PCR!$J$123 -> 0.062 | EH35: 1.466 | EI35: =[21]PCR!$J$132 -> 0.064 | EJ35: 1.031 | EK35: =[22]PCR!$J$135 -> 0.616 | EL35: 1.192 | EM35: =[23]PCR!$J$149 -> 5.011 | EN35: 2.097 | EO35: =[24]PCR!$J$171 -> 2.652 | EP35: 3.06 | EQ35: =[25]PCR!$J$178 -> 1.751 | ER35: 3.327 | ES35: =[26]PCR!$J$158 -> 0.399 | ET35: 2.769 | EU35: =[27]PCR!$J$149 -> 0.805 | EV35: 0.411 | EW35: =[28]PCR!$J$136 -> 0 | EX35: 0.525 | EY35: =[29]PCR!$J$136 -> #REF! | EZ35: 0.637 | FA35: =[30]PCR!$J$134 -> 0.121 | FB35: 0.962 | FC35: 1.066 | FD35: 1.076 | FE35: =[31]PCR!$J$130 -> 1.22 | FF35: 1.267 | FG35: =[32]PCR!$J$133 -> 1.175 | FH35: 1.2457607 | FI35: =[33]PCR!$J$140 -> 3.075 | FJ35: 1.2569993 | FK35: =[34]PCR!$J$140 -> 1.359 | FL35: 2.4036144 | FM35: =[35]PCR!$J$150 -> 2.486 | FN35: 3.7147526 | FO35: =[36]PCR!$J$146 -> 4.809 | FP35: 3.927 | FQ35: =[37]PCR!$J$145 -> 1.123 | FR35: 3.151 | FS35: =[38]PCR!$J$137 -> 0.223 | FT35: 0.484 | FU35: =[39]PCR!$J$132 -> 0.545 | FV35: 0.649 | FW35: =[40]PCR!$J$128 -> 1.737 | FX35: 0.885 | FY35: =[41]PCR!$J$126 -> 0.294 | FZ35: 1.287 | GA35: =[42]PCR!$J$122 -> 1.182 | GB35: 0.144 | GC35: 3.717 | GD35: 2.912 | GE35: 7.385 | GF35: 4.081 | GG35: 0.701 | GH35: 1.188 | GI35: 0.144 | GJ35: 0.568 | GK35: 0.373 | GL35: 0.45 | GM35: 2.15 | GN35: 0.4 | GO35: 1.61 | GP35: 3.32 | GQ35: 6.945 | GR35: 3.525 | GS35: 2.242 | GT35: 1.462 | GU35: 0.67 | GV35: 1.142 | GW35: 0.934 | GX35: 3.05 | GY35: 2.611 | GZ35: 1.07 | HA35: 2.323 | HB35: 5.901 | HC35: 8.693 | HD35: 8.213 | HE35: 3.178 | HF35: 1.034 | HG35: 0.617 | HH35: =[43]PCR!$I$289 -> 0.778 | HI35: =[44]PCR!$I$289 -> 0.256 | HJ35: 1.437 | HK35: =[45]PCR!$I$289 -> 0.926 | HL35: =[50]PCR!$I$289 -> 1.047 | HM35: 4.968 | HN35: 5.682 | HO35: 10.157 | HP35: 14.079 | HQ35: 2.361 | HR35: 0.877 | HS35: 2.085 | HT35: 1.462 | HU35: 2.337 | HV35: 1.596 | HW35: 0.58 | HX35: 2.052 | HY35: =[46]Cate!I289 -> 1.859 | HZ35: 1.934 | IA35: =[47]Cate!I289 -> 3.548 | IB35: =[48]Cate!I289 -> 1.765 | IC35: 1.633 | ID35: =[49]PCR!$I$289 -> 1.402 | IE35: 4.231 | IF35: 0.922 | IG35: 0 | IH35: =[51]PCR!$I$289 -> 0.308 | II35: 0.805 | IJ35: 0.123 | IK35: 0.75 | IL35: 1.844 | IM35: 6.657 | IN35: 1.101 | IO35: 0.931 | IP35: 2.371 | IQ35: 0.038 | IR35: 0.709 | IS35: 0.082 | IT35: 0.276 | IU35: 0.06 | IV35: 0.424 | IW35: 1.434 | IX35: 1.282 | IY35: 0.817 | IZ35: 0.397 | JA35: 0.457 | JB35: 0.382 | JC35: 0 | JD35: 0.745 | JE35: 0.24 | JF35: 0.534 | JG35: 1.087 | JH35: 0.839
D36: Out | F36: 4.1929664 | G36: 4.373 | H36: 1.6 | I36: 1.473 | J36: 1.4 | K36: 1.62 | L36: 2.025 | M36: 2.083 | N36: 2.7 | O36: 1.626 | P36: 3.5 | Q36: 3.858 | R36: 3.5 | S36: 2.769 | T36: 3 | U36: 0.716 | V36: 2 | W36: 1.106 | X36: 3 | Y36: 2.403 | Z36: 4 | AA36: 1.192 | AB36: 4 | AC36: 2.983 | AD36: 4.335 | AE36: 2.252 | AF36: 0.958 | AG36: 0.31 | AH36: 0.867 | AI36: 0.594 | AJ36: 1.42 | AK36: 1.097 | AL36: 1.964 | AM36: 0.783 | AN36: 2.399 | AO36: 1.564 | AP36: 2.761 | AQ36: 1.014 | AR36: 1.845 | AS36: 1.873 | AT36: 2.073 | AU36: 0.723 | AV36: 2.264 | AW36: 4.09 | AX36: 2.692 | AY36: 0.882 | AZ36: 3.607 | BA36: 1.552 | BB36: 3.152 | BC36: 2.4 | BD36: 0.664 | BE36: 1.118 | BF36: 0.68 | BG36: 0.355 | BH36: 1.124 | BI36: 1.688 | BJ36: 1.14 | BK36: 1.019 | BL36: 1.278 | BM36: 0.902 | BN36: 1.374 | BO36: 0.969 | BP36: 0.869 | BQ36: 1.68 | BR36: 0.888 | BS36: 0.993 | BT36: 1.3 | BU36: 1.291 | BV36: =+BV35 -> 1.476 | BW36: 1.716 | BX36: =+BX35 -> 1.668 | BY36: 1.984 | BZ36: =+BZ35 -> 1.837 | CA36: 1.502 | CB36: =+CB35 -> 0.721 | CC36: 0.367 | CD36: 0.635 | CE36: 0.934 | CF36: 0.958 | CG36: 0.645 | CH36: 0.873 | CI36: 0.828 | CJ36: 1.048 | CK36: 0.762 | CL36: 1.174 | CM36: 1.479 | CN36: 0.97031538 | CO36: 0.775 | CP36: =+CP35 -> 1.1394425 | CQ36: 0.827 | CR36: 1.2502295 | CS36: 2.55 | CT36: =+CT35 -> 1.456 | CU36: 3.624 | CV36: =+CV35 -> 1.591 | CW36: 3.961 | CX36: 1.508888 | CY36: 1.416 | CZ36: 0.299 | DA36: 0.644 | DB36: 0.295 | DC36: 0.543 | DD36: 0.407 | DE36: 0.42 | DF36: 0.837 | DG36: =[12]PCR!$J$114 -> 0.407 | DH36: 1.092 | DI36: =[13]PCR!$J$116 -> 0.552 | DJ36: 0.805 | DK36: 0.754 | DL36: =DL35 -> 0.817 | DM36: 0.717 | DN36: =DN35 -> 0.957 | DO36: 0.792 | DP36: =DP35 -> 1.075 | DQ36: 3.96 | DR36: =DR35 -> 1.172 | DS36: 6.776 | DT36: =DT35 -> 1.375 | DU36: =[14]PCR!$J$148 -> 1.763 | DV36: =DV35 -> 1.316 | DW36: =[15]PCR!$J$145 -> 3.469 | DX36: =DX35 -> 0.729 | DY36: =[16]PCR!$J$128 -> 0.538 | DZ36: =DZ35 -> 0.745 | EA36: =[17]PCR!$J$119 -> 0.377 | EB36: =EB35 -> 1.089 | EC36: =[18]PCR!$J$121 -> 0.758 | ED36: =ED35 -> 1.132 | EE36: =[19]PCR!$J$120 -> 0.525 | EF36: =EF35 -> 1.29 | EG36: =[20]PCR!$J$124 -> 0.398 | EH36: =EH35 -> 1.466 | EI36: =[21]PCR!$J$133 -> 0.409 | EJ36: =EJ35 -> 1.031 | EK36: =[22]PCR!$J$136 -> 0.488 | EL36: =EL35 -> 1.192 | EM36: =[23]PCR!$J$150 -> 0.781 | EN36: =EN35 -> 2.097 | EO36: =[24]PCR!$J$172 -> 2.217 | EP36: =EP35 -> 3.06 | EQ36: =[25]PCR!$J$179 -> 6.48 | ER36: =ER35 -> 3.327 | ES36: =[26]PCR!$J$159 -> 3.405 | ET36: =ET35 -> 2.769 | EU36: =[27]PCR!$J$150 -> 1.584 | EV36: =EV35 -> 0.411 | EW36: =[28]PCR!$J$137 -> 0.106 | EX36: =EX35 -> 0.525 | EY36: =[29]PCR!$J$137 -> #REF! | EZ36: =EZ35 -> 0.637 | FA36: =[30]PCR!$J$135 -> 0.348 | FB36: =FB35 -> 0.962 | FC36: 0.578 | FD36: =FD35 -> 1.076 | FE36: =[31]PCR!$J$131 -> 0.948 | FF36: =FF35 -> 1.267 | FG36: =[32]PCR!$J$134 -> 1.114 | FH36: 1.2457607 | FI36: =[33]PCR!$J$141 -> 0.873 | FJ36: 1.2569993 | FK36: =[34]PCR!$J$141 -> 1.186 | FL36: 2.4036144 | FM36: =[35]PCR!$J$151 -> 3.726 | FN36: 3.7147526 | FO36: =[36]PCR!$J$147 -> 4.09 | FP36: 3.927 | FQ36: =[37]PCR!$J$146 -> 1.781 | FR36: 3.151 | FS36: =[38]PCR!$J$138 -> 1.018 | FT36: 0.318 | FU36: =[39]PCR!$J$133 -> 0.423 | FV36: 0.39 | FW36: =[40]PCR!$J$129 -> 2.008 | FX36: 0.761 | FY36: =[41]PCR!$J$127 -> 1.149 | FZ36: 0.957 | GA36: =[42]PCR!$J$123 -> 0.768 | GB36: 0.537 | GC36: 0.846 | GD36: 1.546 | GE36: 1.575 | GF36: 4.37 | GG36: 5.599 | GH36: 1.916 | GI36: 1.397 | GJ36: 0.714 | GK36: 1.17 | GL36: 0.538 | GM36: 1.077 | GN36: 1.677 | GO36: 0.63 | GP36: 1.249 | GQ36: 3.181 | GR36: 1.751 | GS36: 8.878 | GT36: 2.082 | GU36: 2.204 | GV36: 0.852 | GW36: 1.042 | GX36: 0.914 | GY36: 1.929 | GZ36: 1.477 | HA36: 3.451 | HB36: 1.764 | HC36: 7.543 | HD36: 9.079 | HE36: 5.35 | HF36: 2.819 | HG36: 2.032 | HH36: =[43]PCR!$I$290 -> 1.095 | HI36: =[44]PCR!$I$290 -> 0.676 | HJ36: 1.323 | HK36: =[45]PCR!$J$289 -> 0.803 | HL36: =[50]PCR!$I$290 -> 0.991 | HM36: 3.29 | HN36: 4.568 | HO36: 6.558 | HP36: 12.301 | HQ36: 10.509 | HR36: 2.04 | HS36: 0.811 | HT36: 1.375 | HU36: 0.728 | HV36: 1.591 | HW36: 1.179 | HX36: 1.45 | HY36: =[46]Cate!J289 -> 1.845 | HZ36: 1.879 | IA36: =[47]Cate!J289 -> 3.076 | IB36: =[48]Cate!J289 -> 1.621 | IC36: 1.017 | ID36: =[49]PCR!$J$289 -> 2.275 | IE36: 3.222 | IF36: 0.86 | IG36: 0.869 | IH36: =[51]PCR!$J$289 -> 0.655 | II36: 2.4 | IJ36: 1.296 | IK36: 0.593 | IL36: 0.876 | IM36: 1.263 | IN36: 1.001 | IO36: 0.604 | IP36: 0.811 | IQ36: 4.017 | IR36: 0.714 | IS36: 0.368 | IT36: 0.769 | IU36: 0.614 | IV36: 0.948 | IW36: 0.434 | IX36: 0.68 | IY36: 0.973 | IZ36: 1.178 | JA36: 0.913 | JB36: 0.93 | JC36: 1.49 | JD36: 0.492 | JE36: 0.54 | JF36: 0.85 | JG36: 0.803 | JH36: 0.603
D37: Inventory | F37: 3.5170525 | G37: 6.563 | H37: =F37+H35-H36 -> 3.4570525 | I37: =G37+I35-I36 -> 6.712 | J37: =H37+J35-J36 -> 3.6570525 | K37: =I37+K35-K36 -> 5.855 | L37: =J37+L35-L36 -> 5.1320525 | M37: =K37+M35-M36 -> 4.023 | N37: =L37+N35-N36 -> 5.9320525 | O37: =M37+O35-O36 -> 3.648 | ... AK37: =AI37+AK35-AK36 -> 4.17 | AL37: =N37*1.137 -> 6.7447437 | AM37: =AK37+AM35-AM36 -> 4.751 | AN37: =P37*1.137 -> 6.5173437 | AO37: =AM37+AO35-AO36 -> 4.731 | AP37: =R37*1.137 -> 5.7214437 | AQ37: 5.718 | AR37: =T37*1.137 -> 5.4940437 | AS37: =AQ37+AS35-AS36 -> 5.386 | AT37: =V37*1.137 -> 6.8584437 | AU37: =AS37+AU35-AU36 -> 6.126 | AV37: =X37*1.137 -> 7.9954437 | AW37: =AU37+AW35-AW36 -> 2.575 | AX37: =Z37*1.137 -> 7.9954437 | AY37: =AW37+AY35-AY36 -> 3.291 | AZ37: 11.633844 | BA37: 3.035 | BB37: 8.7515487 | BC37: 2.816 | BD37: 8.7515487 | BE37: 1.722 | BF37: =BD37+BF35-BF36 -> 8.7515487 | BG37: =BE37+BG35-BG36 -> 1.367 | BH37: =AJ37*1.137 -> 4.2035487 | BI37: =BG37+BI35-BI36 -> 3.503 | BJ37: =AL37*1.137 -> 7.6687736 | BK37: =BI37+BK35-BK36 -> 3.055 | BL37: =AN37*1.137 -> 7.4102198 | BM37: =BK37+BM35-BM36 -> 3.12 | BN37: =AP37*1.137 -> 6.5052815 | BO37: =BM37+BO35-BO36 -> 2.301 | BP37: =AR37*1.137 -> 6.2467277 | BQ37: =BO37+BQ35-BQ36 -> 2.337 | BR37: =AT37*1.137 -> 7.7980505 | BS37: =BQ37+BS35-BS36 -> 1.673 | BT37: =AV37*1.137 -> 9.0908195 | BU37: =BS37+BU35-BU36 -> 2.095 | BV37: =AX37*1.137 -> 9.0908195 | BW37: =BU37+BW35-BW36 -> 1.412 | BX37: =AZ37*1.137 -> 13.22768 | BY37: =BW37+BY35-BY36 -> 1.681 | BZ37: =BB37*1.137 -> 9.9505108 | CA37: =BY37+CA35-CA36 -> 0.65 | CB37: =BD37*1.137 -> 9.9505108 | CC37: =CA37+CC35-CC36 -> 0.506 | CD37: =BF37*1.137 -> 9.9505108 | CE37: =CC37+CE35-CE36 -> 0.536 | CF37: =BH37*1.137 -> 4.7794348 | CG37: =CE37+CG35-CG36 -> 1.001 | CH37: =BJ37*1.137 -> 8.7193955 | CI37: =CG37+CI35-CI36 -> 0.894 | CJ37: =BL37*1.137 -> 8.4254199 | CK37: =CI37+CK35-CK36 -> 1.352 | CL37: =BN37*1.137 -> 7.396505 | CM37: =CK37+CM35-CM36 -> 0.799 | CN37: =BP37*1.137 -> 7.1025293 | CO37: =CM37+CO35-CO36 -> 2.913 | CP37: =BR37*1.137 -> 8.8663834 | CQ37: =CO37+CQ35-CQ36 -> 4.115 | CR37: =BT37*1.137 -> 10.336262 | CS37: =CQ37+CS35-CS36 -> 6.675 | CT37: =BV37*1.137 -> 10.336262 | CU37: =CS37+CU35-CU36 -> 4.094 | CV37: =BX37*1.137 -> 15.039872 | CW37: =CU37+CW35-CW36 -> 1.602 | CX37: =BZ37*1.137 -> 11.313731 | CY37: 0.931 | CZ37: =CB37*1.137 -> 11.313731 | DA37: =CY37+DA35-DA36 -> 0.94 | DB37: =CD37*1.137 -> 11.313731 | DC37: =DA37+DC35-DC36 -> 0.561 | DD37: =CF37*1.137 -> 5.4342174 | DE37: =DC37+DE35-DE36 -> 0.841 | DF37: =CF37*1.137 -> 5.4342174 | DG37: =DE37+DG35-DG36 -> 0.69 | DH37: =CH37*1.137 -> 9.9139527 | DI37: =DG37+DI35-DI36 -> 0.787 | DJ37: =CH37*1.137 -> 9.9139527 | DK37: =DI37+DK35-DK36 -> 1.38 | DL37: =CJ37*1.137 -> 9.5797024 | DM37: =DK37+DM35-DM36 -> 0.917 | DN37: =CL37*1.137 -> 8.4098262 | DO37: =DM37+DO35-DO36 -> 0.7 | DP37: =CN37*1.137 -> 8.0755759 | DQ37: =DO37+DQ35-DQ36 -> 2.065 | DR37: =CP37*1.137 -> 10.081078 | DS37: =DQ37+DS35-DS36 -> 6.742 | DT37: =CR37*1.137 -> 11.75233 | DU37: =DS37+DU35-DU36 -> 5.775 | DV37: =CT37*1.137 -> 11.75233 | DW37: =DU37+DW35-DW36 -> 4.546 | DX37: =CV37*1.137 -> 17.100335 | DY37: =DW37+DY35-DY36 -> 6.516 | DZ37: =CX37*1.137 -> 12.863712 | EA37: =DY37+EA35-EA36 -> 6.588 | EB37: =CZ37*1.137 -> 12.863712 | EC37: =EA37+EC35-EC36 -> 5.879 | ED37: =DB37*1.137 -> 12.863712 | EE37: =EC37+EE35-EE36 -> 5.394 | EF37: =DD37*1.137 -> 6.1787052 | EG37: =EE37+EG35-EG36 -> 5.058 | EH37: =DF37*1.137 -> 6.1787052 | EI37: =EG37+EI35-EI36 -> 4.713 | EJ37: =DH37*1.137 -> 11.272164 | EK37: =EI37+EK35-EK36 -> 4.841 | EL37: =DJ37*1.137 -> 11.272164 | EM37: =EK37+EM35-EM36 -> 9.071 | EN37: =DL37*1.137 -> 10.892122 | EO37: =EM37+EO35-EO36 -> 9.506 | EP37: =DN37*1.137 -> 9.5619724 | EQ37: =EO37+EQ35-EQ36 -> 4.777 | ER37: =DP37*1.137 -> 9.1819298 | ES37: =EQ37+ES35-ES36 -> 1.771 | ET37: =DR37*1.137 -> 11.462186 | EU37: =ES37+EU35-EU36 -> 0.992 | EV37: =DT37*1.137 -> 13.362399 | EW37: =EU37+EW35-EW36 -> 0.886 | EX37: =DV37*1.137 -> 13.362399 | EY37: =EW37+EY35-EY36 -> #REF! | EZ37: =DX37*1.137 -> 19.443081 | FA37: =EY37+FA35-FA36 -> #REF! | FB37: =DZ37*1.137 -> 14.62604 | FC37: =FA37+FC35-FC36 -> #REF! | FD37: =EB37*1.137 -> 14.62604 | FE37: 1.612 | FF37: =ED37*1.137 -> 14.62604 | FG37: =FE37+FG35-FG36 -> 1.673 | FH37: =EF37*1.137 -> 7.0251878 | FI37: =FG37+FI35-FI36 -> 3.875 | FJ37: =EH37*1.137 -> 7.0251878 | FK37: =FI37+FK35-FK36 -> 4.048 | FL37: =EJ37*1.137 -> 12.816451 | FM37: =FK37+FM35-FM36 -> 2.808 | FN37: =EL37*1.137 -> 12.816451 | FO37: =FM37+FO35-FO36 -> 3.527 | FP37: =EN37*1.137 -> 12.384342 | FQ37: =FO37+FQ35-FQ36 -> 2.869 | FR37: 1.611 | FS37: =FQ37+FS35-FS36 -> 2.074 | FT37: =FR37+FT35-FT36 -> 1.777 | FU37: =FS37+FU35-FU36 -> 2.196 | FV37: =FT37+FV35-FV36 -> 2.036 | FW37: =FU37+FW35-FW36 -> 1.925 | FX37: =FV37+FX35-FX36 -> 2.16 | FY37: =FW37+FY35-FY36 -> 1.07 | FZ37: 1.412 | GA37: =FY37+GA35-GA36 -> 1.484 | GB37: =GA37+GB35-GB36 -> 1.091 | GC37: =GB37+GC35-GC36 -> 3.962 | GD37: =GC37+GD35-GD36 -> 5.328 | GE37: =GD37+GE35-GE36 -> 11.138 | GF37: =GE37+GF35-GF36 -> 10.849 | GG37: =GF37+GG35-GG36 -> 5.951 | GH37: =GG37+GH35-GH36 -> 5.223 | GI37: =GH37+GI35-GI36 -> 3.97 | ... HB37: =HA37+HB35-HB36 -> 8.136 | HC37: 9.238 | HD37: =HC37+HD35-HD36 -> 8.372 | HE37: =HD37+HE35-HE36 -> 6.2 | HF37: =HE37+HF35-HF36 -> 4.415 | HG37: =HF37+HG35-HG36 -> 3 | HH37: =HG37+HH35-HH36 -> 2.683 | HI37: =HH37+HI35-HI36 -> 2.263 | HJ37: =HI37+HJ35-HJ36 -> 2.377 | HK37: =HJ37+HK35-HK36 -> 2.5 | ... HU37: =HT37+HU35-HU36 -> 4.384 | HV37: 3.327 | HW37: =HV37+HW35-HW36 -> 2.728 | HX37: =HW37+HX35-HX36 -> 3.33 | HY37: =HX37+HY35-HY36 -> 3.344 | HZ37: =HY37+HZ35-HZ36 -> 3.399 | IA37: =HZ37+IA35-IA36 -> 3.871 | IB37: =IA37+IB35-IB36 -> 4.015 | IC37: =IB37+IC35-IC36 -> 4.631 | ID37: =IC37+ID35-ID36 -> 3.758 | ... IL37: =IK37+IL35-IL36 -> 1.97 | IM37: 7.364 | IN37: =IM37+IN35-IN36 -> 7.464 | IO37: =IN37+IO35-IO36 -> 7.791 | IP37: =IO37+IP35-IP36 -> 9.351 | IQ37: =IP37+IQ35-IQ36 -> 5.372 | IR37: =IQ37+IR35-IR36 -> 5.367 | IS37: =IR37+IS35-IS36 -> 5.081 | IT37: =IS37+IT35-IT36 -> 4.588 | IU37: =IT37+IU35-IU36 -> 4.034 | ... JO37: =JN37+JO35-JO36 -> 1.838
D38: month | E38: 1.6 | F38: 1.6599417 | G38: 3.918209 | H38: =IF(H37<=J36,H37/J36,IF(H37<=J36+L36,1+(H37-J36)/L36,IF(H37<=J36+L36+N36,2+(H37-J36-L36)/N36,H37*3/(J36+L36+N36)))) -> 2.0118713 | I38: =IF(I37<=K36,I37/K36,IF(I37<=K36+M36,1+(I37-K36)/M36,IF(I37<=K36+M36+O36,2+(I37-K36-M36)/O36,I37*3/(K36+M36+O36)))) -> 3.7785701 | J38: =IF(J37<=L36,J37/L36,IF(J37<=L36+N36,1+(J37-L36)/N36,IF(J37<=L36+N36+P36,2+(J37-L36-N36)/P36,J37*3/(L36+N36+P36)))) -> 1.6044639 | K38: =IF(K37<=M36,K37/M36,IF(K37<=M36+O36,1+(K37-M36)/O36,IF(K37<=M36+O36+Q36,2+(K37-M36-O36)/Q36,K37*3/(M36+O36+Q36)))) -> 2.5562468 | L38: =IF(L37<=N36,L37/N36,IF(L37<=N36+P36,1+(L37-N36)/P36,IF(L37<=N36+P36+R36,2+(L37-N36-P36)/R36,L37*3/(N36+P36+R36)))) -> 1.6948721 | M38: =IF(M37<=O36,M37/O36,IF(M37<=O36+Q36,1+(M37-O36)/Q36,IF(M37<=O36+Q36+S36,2+(M37-O36-Q36)/S36,M37*3/(O36+Q36+S36)))) -> 1.6213064 | N38: =IF(N37<=P36,N37/P36,IF(N37<=P36+R36,1+(N37-P36)/R36,IF(N37<=P36+R36+T36,2+(N37-P36-R36)/T36,N37*3/(P36+R36+T36)))) -> 1.6948721 | O38: =IF(O37<=Q36,O37/Q36,IF(O37<=Q36+S36,1+(O37-Q36)/S36,IF(O37<=Q36+S36+U36,2+(O37-Q36-S36)/U36,O37*3/(Q36+S36+U36)))) -> 0.94556765 | ... CS38: =IF(CS37<=CU36,CS37/CU36,IF(CS37<=CU36+CW36,1+(CS37-CU36)/CW36,IF(CS37<=CU36+CW36+CY36,2+(CS37-CU36-CW36)/CY36,CS37*3/(CU36+CW36+CY36)))) -> 1.77026 | CT38: =IF(CT37<=CV36,CT37/CV36,IF(CT37<=CV36+CZ36,1+(CT37-CV36)/CZ36,IF(CT37<=CV36+CZ36+#REF!,2+(CT37-CV36-CZ36)/#REF!,CT37*3/(CV36+CZ36+#REF!)))) -> #REF! | CU38: =IF(CU37<=CW36,CU37/CW36,IF(CU37<=CW36+CY36,1+(CU37-CW36)/CY36,IF(CU37<=CW36+CY36+DA36,2+(CU37-CW36-CY36)/DA36,CU37*3/(CW36+CY36+DA36)))) -> 1.0939266 | CV38: =IF(CV37<=CZ36,CV37/CZ36,IF(CV37<=CZ36+#REF!,1+(CV37-CZ36)/#REF!,IF(CV37<=CZ36+#REF!+#REF!,2+(CV37-CZ36-#REF!)/#REF!,CV37*3/(CZ36+#REF!+#REF!)))) -> #REF! | CW38: =IF(CW37<=CY36,CW37/CY36,IF(CW37<=CY36+DA36,1+(CW37-CY36)/DA36,IF(CW37<=CY36+DA36+DC36,2+(CW37-CY36-DA36)/DC36,CW37*3/(CY36+DA36+DC36)))) -> 1.2888199 | CX38: =IF(CX37<=#REF!,CX37/#REF!,IF(CX37<=#REF!+#REF!,1+(CX37-#REF!)/#REF!,IF(CX37<=#REF!+#REF!+#REF!,2+(CX37-#REF!-#REF!)/#REF!,CX37*3/(#REF!+#REF!+#REF!)))) -> #REF! | CY38: =IF(CY37<=DA36,CY37/DA36,IF(CY37<=DA36+DC36,1+(CY37-DA36)/DC36,IF(CY37<=DA36+DC36+DE36,2+(CY37-DA36-DC36)/DE36,CY37*3/(DA36+DC36+DE36)))) -> 1.5285451 | CZ38: =IF(CZ37<=#REF!,CZ37/#REF!,IF(CZ37<=#REF!+#REF!,1+(CZ37-#REF!)/#REF!,IF(CZ37<=#REF!+#REF!+#REF!,2+(CZ37-#REF!-#REF!)/#REF!,CZ37*3/(#REF!+#REF!+#REF!)))) -> #REF! | DA38: =IF(DA37<=DC36,DA37/DC36,IF(DA37<=DC36+DE36,1+(DA37-DC36)/DE36,IF(DA37<=DC36+DE36+DG36,2+(DA37-DC36-DE36)/DG36,DA37*3/(DC36+DE36+DG36)))) -> 1.9452381 | DB38: =IF(DB37<=DD36,DB37/DD36,IF(DB37<=DD36+DF36,1+(DB37-DD36)/DF36,IF(DB37<=DD36+DF36+DH36,2+(DB37-DD36-DF36)/DH36,DB37*3/(DD36+DF36+DH36)))) -> 14.52962 | DC38: =IF(DC37<=DE36,DC37/DE36,IF(DC37<=DE36+DG36,1+(DC37-DE36)/DG36,IF(DC37<=DE36+DG36+DI36,2+(DC37-DE36-DG36)/DI36,DC37*3/(DE36+DG36+DI36)))) -> 1.3464373 | DD38: =IF(DD37<=#REF!,DD37/#REF!,IF(DD37<=#REF!+#REF!,1+(DD37-#REF!)/#REF!,IF(DD37<=#REF!+#REF!+#REF!,2+(DD37-#REF!-#REF!)/#REF!,DD37*3/(#REF!+#REF!+#REF!)))) -> #REF! | DE38: =IF(DE37<=DG36,DE37/DG36,IF(DE37<=DG36+DI36,1+(DE37-DG36)/DI36,IF(DE37<=DG36+DI36+DK36,2+(DE37-DG36-DI36)/DK36,DE37*3/(DG36+DI36+DK36)))) -> 1.7862319 | DF38: =IF(DF37<=#REF!,DF37/#REF!,IF(DF37<=#REF!+#REF!,1+(DF37-#REF!)/#REF!,IF(DF37<=#REF!+#REF!+#REF!,2+(DF37-#REF!-#REF!)/#REF!,DF37*3/(#REF!+#REF!+#REF!)))) -> #REF! | DG38: =IF(DG37<=DI36,DG37/DI36,IF(DG37<=DI36+DK36,1+(DG37-DI36)/DK36,IF(DG37<=DI36+DK36+DM36,2+(DG37-DI36-DK36)/DM36,DG37*3/(DI36+DK36+DM36)))) -> 1.1830239 | DH38: =IF(DH37<=#REF!,DH37/#REF!,IF(DH37<=#REF!+#REF!,1+(DH37-#REF!)/#REF!,IF(DH37<=#REF!+#REF!+#REF!,2+(DH37-#REF!-#REF!)/#REF!,DH37*3/(#REF!+#REF!+#REF!)))) -> #REF! | DI38: =IF(DI37<=DK36,DI37/DK36,IF(DI37<=DK36+DM36,1+(DI37-DK36)/DM36,IF(DI37<=DK36+DM36+DO36,2+(DI37-DK36-DM36)/DO36,DI37*3/(DK36+DM36+DO36)))) -> 1.0460251 | DJ38: 1.5 | DK38: =IF(DK37<=DM36,DK37/DM36,IF(DK37<=DM36+DO36,1+(DK37-DM36)/DO36,IF(DK37<=DM36+DO36+DQ36,2+(DK37-DM36-DO36)/DQ36,DK37*3/(DM36+DO36+DQ36)))) -> 1.8371212 | DL38: 1.5 | DM38: =IF(DM37<=DO36,DM37/DO36,IF(DM37<=DO36+DQ36,1+(DM37-DO36)/DQ36,IF(DM37<=DO36+DQ36+DS36,2+(DM37-DO36-DQ36)/DS36,DM37*3/(DO36+DQ36+DS36)))) -> 1.0315657 | DN38: 1.5 | DO38: =IF(DO37<=DQ36,DO37/DQ36,IF(DO37<=DQ36+DS36,1+(DO37-DQ36)/DS36,IF(DO37<=DQ36+DS36+DU36,2+(DO37-DQ36-DS36)/DU36,DO37*3/(DQ36+DS36+DU36)))) -> 0.17676768 | DP38: 1.5 | DQ38: =IF(DQ37<=DS36,DQ37/DS36,IF(DQ37<=DS36+DU36,1+(DQ37-DS36)/DU36,IF(DQ37<=DS36+DU36+DW36,2+(DQ37-DS36-DU36)/DW36,DQ37*3/(DS36+DU36+DW36)))) -> 0.30475207 | DR38: 1.5 | DS38: =IF(DS37<=DU36,DS37/DU36,IF(DS37<=DU36+DW36,1+(DS37-DU36)/DW36,IF(DS37<=DU36+DW36+DY36,2+(DS37-DU36-DW36)/DY36,DS37*3/(DU36+DW36+DY36)))) -> 3.5053726 | DT38: 1.5 | DU38: =IF(DU37<=DW36,DU37/DW36,IF(DU37<=DW36+DY36,1+(DU37-DW36)/DY36,IF(DU37<=DW36+DY36+EA36,2+(DU37-DW36-DY36)/EA36,DU37*3/(DW36+DY36+EA36)))) -> 3.9518704 | DV38: 1.5 | DW38: =IF(DW37<=DY36,DW37/DY36,IF(DW37<=DY36+EA36,1+(DW37-DY36)/EA36,IF(DW37<=DY36+EA36+EC36,2+(DW37-DY36-EA36)/EC36,DW37*3/(DY36+EA36+EC36)))) -> 8.1518231 | DX38: 1.5 | DY38: =IF(DY37<=EA36,DY37/EA36,IF(DY37<=EA36+EC36,1+(DY37-EA36)/EC36,IF(DY37<=EA36+EC36+EE36,2+(DY37-EA36-EC36)/EE36,DY37*3/(EA36+EC36+EE36)))) -> 11.775904 | DZ38: 1.5 | EA38: =IF(EA37<=EC36,EA37/EC36,IF(EA37<=EC36+EE36,1+(EA37-EC36)/EE36,IF(EA37<=EC36+EE36+EG36,2+(EA37-EC36-EE36)/EG36,EA37*3/(EC36+EE36+EG36)))) -> 11.757287 | EB38: 1.5 | EC38: =IF(EC37<=EE36,EC37/EE36,IF(EC37<=EE36+EG36,1+(EC37-EE36)/EG36,IF(EC37<=EE36+EG36+EI36,2+(EC37-EE36-EG36)/EI36,EC37*3/(EE36+EG36+EI36)))) -> 13.240991 | ED38: 1.5 | EE38: =IF(EE37<=EG36,EE37/EG36,IF(EE37<=EG36+EI36,1+(EE37-EG36)/EI36,IF(EE37<=EG36+EI36+EK36,2+(EE37-EG36-EI36)/EK36,EE37*3/(EG36+EI36+EK36)))) -> 12.495753 | EF38: 1.5 | EG38: =IF(EG37<=EI36,EG37/EI36,IF(EG37<=EI36+EK36,1+(EG37-EI36)/EK36,IF(EG37<=EI36+EK36+EM36,2+(EG37-EI36-EK36)/EM36,EG37*3/(EI36+EK36+EM36)))) -> 9.0429082 | EH38: 1.5 | EI38: =IF(EI37<=EK36,EI37/EK36,IF(EI37<=EK36+EM36,1+(EI37-EK36)/EM36,IF(EI37<=EK36+EM36+EO36,2+(EI37-EK36-EM36)/EO36,EI37*3/(EK36+EM36+EO36)))) -> 4.055938 | EJ38: 2.5 | EK38: =IF(EK37<=EM36,EK37/EM36,IF(EK37<=EM36+EO36,1+(EK37-EM36)/EO36,IF(EK37<=EM36+EO36+EQ36,2+(EK37-EM36-EO36)/EQ36,EK37*3/(EM36+EO36+EQ36)))) -> 2.2844136 | EL38: 2.5 | EM38: =IF(EM37<=EO36,EM37/EO36,IF(EM37<=EO36+EQ36,1+(EM37-EO36)/EQ36,IF(EM37<=EO36+EQ36+ES36,2+(EM37-EO36-EQ36)/ES36,EM37*3/(EO36+EQ36+ES36)))) -> 2.1098385 | EN38: 2.5 | EO38: =IF(EO37<=EQ36,EO37/EQ36,IF(EO37<=EQ36+ES36,1+(EO37-EQ36)/ES36,IF(EO37<=EQ36+ES36+EU36,2+(EO37-EQ36-ES36)/EU36,EO37*3/(EQ36+ES36+EU36)))) -> 1.8886931 | EP38: 2.5 | EQ38: =IF(EQ37<=ES36,EQ37/ES36,IF(EQ37<=ES36+EU36,1+(EQ37-ES36)/EU36,IF(EQ37<=ES36+EU36+EW36,2+(EQ37-ES36-EU36)/EW36,EQ37*3/(ES36+EU36+EW36)))) -> 1.8661616 | ER38: 2.5 | ES38: =IF(ES37<=EU36,ES37/EU36,IF(ES37<=EU36+EW36,1+(ES37-EU36)/EW36,IF(ES37<=EU36+EW36+EY36,2+(ES37-EU36-EW36)/EY36,ES37*3/(EU36+EW36+EY36)))) -> #REF! | ET38: 2.5 | EU38: =IF(EU37<=EW36,EU37/EW36,IF(EU37<=EW36+EY36,1+(EU37-EW36)/EY36,IF(EU37<=EW36+EY36+FA36,2+(EU37-EW36-EY36)/FA36,EU37*3/(EW36+EY36+FA36)))) -> #REF! | EV38: 2.5 | EW38: =IF(EW37<=EY36,EW37/EY36,IF(EW37<=EY36+FA36,1+(EW37-EY36)/FA36,IF(EW37<=EY36+FA36+FC36,2+(EW37-EY36-FA36)/FC36,EW37*3/(EY36+FA36+FC36)))) -> #REF! | EX38: 2.5 | EY38: =IF(EY37<=FA36,EY37/FA36,IF(EY37<=FA36+FC36,1+(EY37-FA36)/FC36,IF(EY37<=FA36+FC36+FE36,2+(EY37-FA36-FC36)/FE36,EY37*3/(FA36+FC36+FE36)))) -> #REF! | EZ38: 2.5 | FA38: =IF(FA37<=FC36,FA37/FC36,IF(FA37<=FC36+FE36,1+(FA37-FC36)/FE36,IF(FA37<=FC36+FE36+FG36,2+(FA37-FC36-FE36)/FG36,FA37*3/(FC36+FE36+FG36)))) -> #REF! | FB38: 2.5 | FC38: =IF(FC37<=FE36,FC37/FE36,IF(FC37<=FE36+FG36,1+(FC37-FE36)/FG36,IF(FC37<=FE36+FG36+FI36,2+(FC37-FE36-FG36)/FI36,FC37*3/(FE36+FG36+FI36)))) -> #REF! | FD38: 2 | FE38: =IF(FE37<=FG36,FE37/FG36,IF(FE37<=FG36+FI36,1+(FE37-FG36)/FI36,IF(FE37<=FG36+FI36+FK36,2+(FE37-FG36-FI36)/FK36,FE37*3/(FG36+FI36+FK36)))) -> 1.5704467 | FF38: 2 | FG38: =IF(FG37<=FI36,FG37/FI36,IF(FG37<=FI36+FK36,1+(FG37-FI36)/FK36,IF(FG37<=FI36+FK36+FM36,2+(FG37-FI36-FK36)/FM36,FG37*3/(FI36+FK36+FM36)))) -> 1.6745363 | FH38: 2 | FI38: =IF(FI37<=FK36,FI37/FK36,IF(FI37<=FK36+FM36,1+(FI37-FK36)/FM36,IF(FI37<=FK36+FM36+FO36,2+(FI37-FK36-FM36)/FO36,FI37*3/(FK36+FM36+FO36)))) -> 1.7216855 | FJ38: 2 | FK38: =IF(FK37<=FM36,FK37/FM36,IF(FK37<=FM36+FO36,1+(FK37-FM36)/FO36,IF(FK37<=FM36+FO36+FQ36,2+(FK37-FM36-FO36)/FQ36,FK37*3/(FM36+FO36+FQ36)))) -> 1.0787286 | FL38: 2 | FM38: =IF(FM37<=FO36,FM37/FO36,IF(FM37<=FO36+FQ36,1+(FM37-FO36)/FQ36,IF(FM37<=FO36+FQ36+FS36,2+(FM37-FO36-FQ36)/FS36,FM37*3/(FO36+FQ36+FS36)))) -> 0.68655257 | FN38: 2 | FO38: =IF(FO37<=FQ36,FO37/FQ36,IF(FO37<=FQ36+FS36,1+(FO37-FQ36)/FS36,IF(FO37<=FQ36+FS36+FU36,2+(FO37-FQ36-FS36)/FU36,FO37*3/(FQ36+FS36+FU36)))) -> 3.2839851 | FP38: 2 | FQ38: =IF(FQ37<=FS36,FQ37/FS36,IF(FQ37<=FS36+FU36,1+(FQ37-FS36)/FU36,IF(FQ37<=FS36+FU36+FW36,2+(FQ37-FS36-FU36)/FW36,FQ37*3/(FS36+FU36+FW36)))) -> 2.7111554 | FR38: 2 | FS38: =IF(FS37<=FU36,FS37/FU36,IF(FS37<=FU36+FW36,1+(FS37-FU36)/FW36,IF(FS37<=FU36+FW36+FY36,2+(FS37-FU36-FW36)/FY36,FS37*3/(FU36+FW36+FY36)))) -> 1.8222112 | FT38: =IF(FT37<=FV36,FT37/FV36,IF(FT37<=FV36+FX36,1+(FT37-FV36)/FX36,IF(FT37<=FV36+FX36+FZ36,2+(FT37-FV36-FX36)/FZ36,FT37*3/(FV36+FX36+FZ36)))) -> 2.6541275 | FU38: =IF(FU37<=FW36,FU37/FW36,IF(FU37<=FW36+FY36,1+(FU37-FW36)/FY36,IF(FU37<=FW36+FY36+GA36,2+(FU37-FW36-FY36)/GA36,FU37*3/(FW36+FY36+GA36)))) -> 1.1636205 | FV38: =IF(FV37<=FX36,FV37/FX36,IF(FV37<=FX36+FZ36,1+(FV37-FX36)/FZ36,IF(FV37<=FX36+FZ36+#REF!,2+(FV37-FX36-FZ36)/#REF!,FV37*3/(FX36+FZ36+#REF!)))) -> #REF! | FW38: =IF(FW37<=FY36,FW37/FY36,IF(FW37<=FY36+GA36,1+(FW37-FY36)/GA36,IF(FW37<=FY36+GA36+GB36,2+(FW37-FY36-GA36)/GB36,FW37*3/(FY36+GA36+GB36)))) -> 2.0148976 | FX38: =IF(FX37<=FZ36,FX37/FZ36,IF(FX37<=FZ36+#REF!,1+(FX37-FZ36)/#REF!,IF(FX37<=FZ36+#REF!+#REF!,2+(FX37-FZ36-#REF!)/#REF!,FX37*3/(FZ36+#REF!+#REF!)))) -> #REF! | FY38: =IF(FY37<=GA36,FY37/GA36,IF(FY37<=GA36+GB36,1+(FY37-GA36)/GB36,IF(FY37<=GA36+GB36+GC36,2+(FY37-GA36-GB36)/GC36,FY37*3/(GA36+GB36+GC36)))) -> 1.5623836 | FZ38: =IF(FZ37<=#REF!,FZ37/#REF!,IF(FZ37<=#REF!+#REF!,1+(FZ37-#REF!)/#REF!,IF(FZ37<=#REF!+#REF!+#REF!,2+(FZ37-#REF!-#REF!)/#REF!,FZ37*3/(#REF!+#REF!+#REF!)))) -> #REF! | GA38: =IF(GA37<=GB36,GA37/GB36,IF(GA37<=GB36+GC36,1+(GA37-GB36)/GC36,IF(GA37<=GB36+GC36+GD36,2+(GA37-GB36-GC36)/GD36,GA37*3/(GB36+GC36+GD36)))) -> 2.0653299 | GB38: =IF(GB37<=GC36,GB37/GC36,IF(GB37<=GC36+GD36,1+(GB37-GC36)/GD36,IF(GB37<=GC36+GD36+GE36,2+(GB37-GC36-GD36)/GE36,GB37*3/(GC36+GD36+GE36)))) -> 1.1584735 | GC38: =IF(GC37<=GD36,GC37/GD36,IF(GC37<=GD36+GE36,1+(GC37-GD36)/GE36,IF(GC37<=GD36+GE36+GF36,2+(GC37-GD36-GE36)/GF36,GC37*3/(GD36+GE36+GF36)))) -> 2.1924485 | GD38: =IF(GD37<=GE36,GD37/GE36,IF(GD37<=GE36+GF36,1+(GD37-GE36)/GF36,IF(GD37<=GE36+GF36+GG36,2+(GD37-GE36-GF36)/GG36,GD37*3/(GE36+GF36+GG36)))) -> 1.8588101 | GE38: =IF(GE37<=GF36,GE37/GF36,IF(GE37<=GF36+GG36,1+(GE37-GF36)/GG36,IF(GE37<=GF36+GG36+GH36,2+(GE37-GF36-GG36)/GH36,GE37*3/(GF36+GG36+GH36)))) -> 2.6101253 | GF38: =IF(GF37<=GG36,GF37/GG36,IF(GF37<=GG36+GH36,1+(GF37-GG36)/GH36,IF(GF37<=GG36+GH36+GI36,2+(GF37-GG36-GH36)/GI36,GF37*3/(GG36+GH36+GI36)))) -> 3.6520422 | GG38: =IF(GG37<=GH36,GG37/GH36,IF(GG37<=GH36+GI36,1+(GG37-GH36)/GI36,IF(GG37<=GH36+GI36+GJ36,2+(GG37-GH36-GI36)/GJ36,GG37*3/(GH36+GI36+GJ36)))) -> 4.4333251 | GH38: =IF(GH37<=GI36,GH37/GI36,IF(GH37<=GI36+GJ36,1+(GH37-GI36)/GJ36,IF(GH37<=GI36+GJ36+GK36,2+(GH37-GI36-GJ36)/GK36,GH37*3/(GI36+GJ36+GK36)))) -> 4.7756781 | ... JO38: =IF(JO37<=JP36,JO37/JP36,IF(JO37<=JP36+JQ36,1+(JO37-JP36)/JQ36,IF(JO37<=JP36+JQ36+JR36,2+(JO37-JP36-JQ36)/JR36,JO37*3/(JP36+JQ36+JR36)))) -> #DIV/0!
